Workbook

Sheet README
B2: blyp. authoritative product workbook
B3: One evidence-backed record for every defined feature, implementation path, verification state and production conclusion.
B6: Workbook anchor | C6: Reviewed source revision: 8bc0dcb2a1da1b21368c5536aaeef829d587f316. Generated: 2026-08-02T04:33:11+00:00. The repository had a pre-existing working-tree modification to backend/blyp-live-service/src/economy/infra.ts; source conclusions otherwise use the clean archived revision.
B7: What one row means | C7: Each Feature Register row is an independently traceable product requirement. Parent and record-type fields preserve hierarchy. Implementation, reachability, completeness, verification and production conclusion are separate facts.
B8: Implementation | C8: Describes what is physically present in the reviewed source: client screens, routes, services, stores, workers, external systems, configuration and deployable boundaries. `Not found` means no mapped implementation was found; `Unknown` means available evidence is insufficient.
B9: How it runs | C9: Use Runtime Path ID and Runtime Path Narrative in the Feature Register, then inspect the Runtime Paths sheet for the end-to-end actor, entrypoint, client, server, data, asynchronous work, external dependencies and failure behaviour.
B10: Finished | C10: Functional Completeness compares the mapped implementation with the stated requirement. It does not certify security, scale, legal approval, store acceptance or release operations.
B11: Production ready | C11: A feature may be marked Production ready only when every applicable production gate passes on the exact release candidate, no unresolved blocker remains, and Approved By plus Approved At are populated. This workbook currently contains zero production-ready approvals.
B12: Evidence | C12: Source, test and observed evidence identifiers link to the Evidence Ledger. Documentation and historical audits are leads only unless tied to exact revision, build or observed-runtime evidence.
B13: Editing | C13: Use the controlled dropdowns in the Feature Register. Do not replace Unknown with a positive status without evidence. Add new evidence to the Evidence Ledger first, preserve revision/build identifiers, and record material decisions in Decisions & Changes.
B14: Live streaming | C14: The feature is implemented and user-reachable. It remains blocked because later signed-device candidates retained a black host preview and the Firebase HLS and separate AWS IVS paths are not reconciled.
B15: Wallet and gifting | C15: The visible wallet and gift interface is implemented. It remains blocked because the current mobile Firestore economy and the hosted PostgreSQL economy are conflicting authorities, with no current executed transaction and reconciliation proof.

Sheet Executive Summary
A1: blyp. product source of truth
A2: 633 normalized feature records • evidence anchored to 8bc0dcb2a1da • generated 2026-08-02T04:33:11+00:00
A4: Defined records | D4: Product areas | G4: Implemented in some form | J4: Complete against requirement | M4: Physical-device observed | P4: Production ready
A5: =COUNTA('Feature Register'!$A$2:$A$634) | D5: =COUNTA($A$66:$A$95) | G5: =COUNTIF('Feature Register'!$S$2:$S$634,"Scaffold only")+COUNTIF('Feature Register'!$S$2:$S$634,"UI only")+COUNTIF('Feature Register'!$S$2:$S$634,"Backend only")+COUNTIF('Feature Register'!$S$2:$S$634,"Partial")+COUNTIF('Feature Register'!$S$2:$S$634,"End-to-end present")+COUNTIF('Feature Register'!$S$2:$S$634,"Conflicting implementations") | J5: =COUNTIF('Feature Register'!$AG$2:$AG$634,"Complete against stated requirement") | M5: =COUNTIF('Feature Register'!$AJ$2:$AJ$634,"Physical device observed") | P5: =COUNTIF('Feature Register'!$BE$2:$BE$634,"Production ready")
A7: No feature is automatically production-approved. `Production ready` requires every applicable gate, an exact release candidate, and accountable approval.
A9: Physical implementation
A10: Status | B10: Count | C10: % of 633
A11: End-to-end present | B11: =COUNTIF('Feature Register'!$S$2:$S$634,A11) | C11: =B11/$A$5
A12: Partial | B12: =COUNTIF('Feature Register'!$S$2:$S$634,A12) | C12: =B12/$A$5
A13: UI only | B13: =COUNTIF('Feature Register'!$S$2:$S$634,A13) | C13: =B13/$A$5
A14: Backend only | B14: =COUNTIF('Feature Register'!$S$2:$S$634,A14) | C14: =B14/$A$5
A15: Conflicting implementations | B15: =COUNTIF('Feature Register'!$S$2:$S$634,A15) | C15: =B15/$A$5
A16: Scaffold only | B16: =COUNTIF('Feature Register'!$S$2:$S$634,A16) | C16: =B16/$A$5
A17: Not found | B17: =COUNTIF('Feature Register'!$S$2:$S$634,A17) | C17: =B17/$A$5
A18: Unknown | B18: =COUNTIF('Feature Register'!$S$2:$S$634,A18) | C18: =B18/$A$5
A21: Functional completeness
A22: Status | B22: Count | C22: % of 633
A23: Complete against stated requirement | B23: =COUNTIF('Feature Register'!$AG$2:$AG$634,A23) | C23: =B23/$A$5
A24: Incomplete | B24: =COUNTIF('Feature Register'!$AG$2:$AG$634,A24) | C24: =B24/$A$5
A25: Not started | B25: =COUNTIF('Feature Register'!$AG$2:$AG$634,A25) | C25: =B25/$A$5
A26: Not assessable | B26: =COUNTIF('Feature Register'!$AG$2:$AG$634,A26) | C26: =B26/$A$5
A27: Unknown | B27: =COUNTIF('Feature Register'!$AG$2:$AG$634,A27) | C27: =B27/$A$5
A30: Verification
A31: Status | B31: Count | C31: % of 633
A32: Physical device observed | B32: =COUNTIF('Feature Register'!$AJ$2:$AJ$634,A32) | C32: =B32/$A$5
A33: Conflicting evidence | B33: =COUNTIF('Feature Register'!$AJ$2:$AJ$634,A33) | C33: =B33/$A$5
A34: Source traced | B34: =COUNTIF('Feature Register'!$AJ$2:$AJ$634,A34) | C34: =B34/$A$5
A35: Build verified | B35: =COUNTIF('Feature Register'!$AJ$2:$AJ$634,A35) | C35: =B35/$A$5
A36: Automated test passed | B36: =COUNTIF('Feature Register'!$AJ$2:$AJ$634,A36) | C36: =B36/$A$5
A37: Not verified | B37: =COUNTIF('Feature Register'!$AJ$2:$AJ$634,A37) | C37: =B37/$A$5
A38: Unknown | B38: =COUNTIF('Feature Register'!$AJ$2:$AJ$634,A38) | C38: =B38/$A$5
A41: Production conclusion
A42: Status | B42: Count | C42: % of 633
A43: Production ready | B43: =COUNTIF('Feature Register'!$BE$2:$BE$634,A43) | C43: =B43/$A$5
A44: Ready for production validation | B44: =COUNTIF('Feature Register'!$BE$2:$BE$634,A44) | C44: =B44/$A$5
A45: Blocked | B45: =COUNTIF('Feature Register'!$BE$2:$BE$634,A45) | C45: =B45/$A$5
A46: Development required | B46: =COUNTIF('Feature Register'!$BE$2:$BE$634,A46) | C46: =B46/$A$5
A47: Not assessed | B47: =COUNTIF('Feature Register'!$BE$2:$BE$634,A47) | C47: =B47/$A$5
A48: Unknown | B48: =COUNTIF('Feature Register'!$BE$2:$BE$634,A48) | C48: =B48/$A$5
A49: Not applicable | B49: =COUNTIF('Feature Register'!$BE$2:$BE$634,A49) | C49: =B49/$A$5
A64: Product-area coverage
A65: Product area | B65: Records | C65: Implemented | D65: Complete | E65: Observed | F65: Blocked | G65: Development required | H65: Ready for validation | I65: Not assessed | J65: Production ready
A66: BLYP Bar and AI-assisted posting | B66: =COUNTIF('Feature Register'!$C$2:$C$634,A66) | C66: =COUNTIFS('Feature Register'!$C$2:$C$634,A66,'Feature Register'!$S$2:$S$634,"Scaffold only")+COUNTIFS('Feature Register'!$C$2:$C$634,A66,'Feature Register'!$S$2:$S$634,"UI only")+COUNTIFS('Feature Register'!$C$2:$C$634,A66,'Feature Register'!$S$2:$S$634,"Backend only")+COUNTIFS('Feature Register'!$C$2:$C$634,A66,'Feature Register'!$S$2:$S$634,"Partial")+COUNTIFS('Feature Register'!$C$2:$C$634,A66,'Feature Register'!$S$2:$S$634,"End-to-end present")+COUNTIFS('Feature Register'!$C$2:$C$634,A66,'Feature Register'!$S$2:$S$634,"Conflicting implementations") | D66: =COUNTIFS('Feature Register'!$C$2:$C$634,A66,'Feature Register'!$AG$2:$AG$634,"Complete against stated requirement") | E66: =COUNTIFS('Feature Register'!$C$2:$C$634,A66,'Feature Register'!$AJ$2:$AJ$634,"Physical device observed") | F66: =COUNTIFS('Feature Register'!$C$2:$C$634,A66,'Feature Register'!$BE$2:$BE$634,"Blocked") | G66: =COUNTIFS('Feature Register'!$C$2:$C$634,A66,'Feature Register'!$BE$2:$BE$634,"Development required") | H66: =COUNTIFS('Feature Register'!$C$2:$C$634,A66,'Feature Register'!$BE$2:$BE$634,"Ready for production validation") | I66: =COUNTIFS('Feature Register'!$C$2:$C$634,A66,'Feature Register'!$BE$2:$BE$634,"Not assessed") | J66: =COUNTIFS('Feature Register'!$C$2:$C$634,A66,'Feature Register'!$BE$2:$BE$634,"Production ready")
A67: Team applications | B67: =COUNTIF('Feature Register'!$C$2:$C$634,A67) | C67: =COUNTIFS('Feature Register'!$C$2:$C$634,A67,'Feature Register'!$S$2:$S$634,"Scaffold only")+COUNTIFS('Feature Register'!$C$2:$C$634,A67,'Feature Register'!$S$2:$S$634,"UI only")+COUNTIFS('Feature Register'!$C$2:$C$634,A67,'Feature Register'!$S$2:$S$634,"Backend only")+COUNTIFS('Feature Register'!$C$2:$C$634,A67,'Feature Register'!$S$2:$S$634,"Partial")+COUNTIFS('Feature Register'!$C$2:$C$634,A67,'Feature Register'!$S$2:$S$634,"End-to-end present")+COUNTIFS('Feature Register'!$C$2:$C$634,A67,'Feature Register'!$S$2:$S$634,"Conflicting implementations") | D67: =COUNTIFS('Feature Register'!$C$2:$C$634,A67,'Feature Register'!$AG$2:$AG$634,"Complete against stated requirement") | E67: =COUNTIFS('Feature Register'!$C$2:$C$634,A67,'Feature Register'!$AJ$2:$AJ$634,"Physical device observed") | F67: =COUNTIFS('Feature Register'!$C$2:$C$634,A67,'Feature Register'!$BE$2:$BE$634,"Blocked") | G67: =COUNTIFS('Feature Register'!$C$2:$C$634,A67,'Feature Register'!$BE$2:$BE$634,"Development required") | H67: =COUNTIFS('Feature Register'!$C$2:$C$634,A67,'Feature Register'!$BE$2:$BE$634,"Ready for production validation") | I67: =COUNTIFS('Feature Register'!$C$2:$C$634,A67,'Feature Register'!$BE$2:$BE$634,"Not assessed") | J67: =COUNTIFS('Feature Register'!$C$2:$C$634,A67,'Feature Register'!$BE$2:$BE$634,"Production ready")
A68: Interest hubs | B68: =COUNTIF('Feature Register'!$C$2:$C$634,A68) | C68: =COUNTIFS('Feature Register'!$C$2:$C$634,A68,'Feature Register'!$S$2:$S$634,"Scaffold only")+COUNTIFS('Feature Register'!$C$2:$C$634,A68,'Feature Register'!$S$2:$S$634,"UI only")+COUNTIFS('Feature Register'!$C$2:$C$634,A68,'Feature Register'!$S$2:$S$634,"Backend only")+COUNTIFS('Feature Register'!$C$2:$C$634,A68,'Feature Register'!$S$2:$S$634,"Partial")+COUNTIFS('Feature Register'!$C$2:$C$634,A68,'Feature Register'!$S$2:$S$634,"End-to-end present")+COUNTIFS('Feature Register'!$C$2:$C$634,A68,'Feature Register'!$S$2:$S$634,"Conflicting implementations") | D68: =COUNTIFS('Feature Register'!$C$2:$C$634,A68,'Feature Register'!$AG$2:$AG$634,"Complete against stated requirement") | E68: =COUNTIFS('Feature Register'!$C$2:$C$634,A68,'Feature Register'!$AJ$2:$AJ$634,"Physical device observed") | F68: =COUNTIFS('Feature Register'!$C$2:$C$634,A68,'Feature Register'!$BE$2:$BE$634,"Blocked") | G68: =COUNTIFS('Feature Register'!$C$2:$C$634,A68,'Feature Register'!$BE$2:$BE$634,"Development required") | H68: =COUNTIFS('Feature Register'!$C$2:$C$634,A68,'Feature Register'!$BE$2:$BE$634,"Ready for production validation") | I68: =COUNTIFS('Feature Register'!$C$2:$C$634,A68,'Feature Register'!$BE$2:$BE$634,"Not assessed") | J68: =COUNTIFS('Feature Register'!$C$2:$C$634,A68,'Feature Register'!$BE$2:$BE$634,"Production ready")
A69: Always-on communal topic live rooms | B69: =COUNTIF('Feature Register'!$C$2:$C$634,A69) | C69: =COUNTIFS('Feature Register'!$C$2:$C$634,A69,'Feature Register'!$S$2:$S$634,"Scaffold only")+COUNTIFS('Feature Register'!$C$2:$C$634,A69,'Feature Register'!$S$2:$S$634,"UI only")+COUNTIFS('Feature Register'!$C$2:$C$634,A69,'Feature Register'!$S$2:$S$634,"Backend only")+COUNTIFS('Feature Register'!$C$2:$C$634,A69,'Feature Register'!$S$2:$S$634,"Partial")+COUNTIFS('Feature Register'!$C$2:$C$634,A69,'Feature Register'!$S$2:$S$634,"End-to-end present")+COUNTIFS('Feature Register'!$C$2:$C$634,A69,'Feature Register'!$S$2:$S$634,"Conflicting implementations") | D69: =COUNTIFS('Feature Register'!$C$2:$C$634,A69,'Feature Register'!$AG$2:$AG$634,"Complete against stated requirement") | E69: =COUNTIFS('Feature Register'!$C$2:$C$634,A69,'Feature Register'!$AJ$2:$AJ$634,"Physical device observed") | F69: =COUNTIFS('Feature Register'!$C$2:$C$634,A69,'Feature Register'!$BE$2:$BE$634,"Blocked") | G69: =COUNTIFS('Feature Register'!$C$2:$C$634,A69,'Feature Register'!$BE$2:$BE$634,"Development required") | H69: =COUNTIFS('Feature Register'!$C$2:$C$634,A69,'Feature Register'!$BE$2:$BE$634,"Ready for production validation") | I69: =COUNTIFS('Feature Register'!$C$2:$C$634,A69,'Feature Register'!$BE$2:$BE$634,"Not assessed") | J69: =COUNTIFS('Feature Register'!$C$2:$C$634,A69,'Feature Register'!$BE$2:$BE$634,"Production ready")
A70: Role-based Team Board | B70: =COUNTIF('Feature Register'!$C$2:$C$634,A70) | C70: =COUNTIFS('Feature Register'!$C$2:$C$634,A70,'Feature Register'!$S$2:$S$634,"Scaffold only")+COUNTIFS('Feature Register'!$C$2:$C$634,A70,'Feature Register'!$S$2:$S$634,"UI only")+COUNTIFS('Feature Register'!$C$2:$C$634,A70,'Feature Register'!$S$2:$S$634,"Backend only")+COUNTIFS('Feature Register'!$C$2:$C$634,A70,'Feature Register'!$S$2:$S$634,"Partial")+COUNTIFS('Feature Register'!$C$2:$C$634,A70,'Feature Register'!$S$2:$S$634,"End-to-end present")+COUNTIFS('Feature Register'!$C$2:$C$634,A70,'Feature Register'!$S$2:$S$634,"Conflicting implementations") | D70: =COUNTIFS('Feature Register'!$C$2:$C$634,A70,'Feature Register'!$AG$2:$AG$634,"Complete against stated requirement") | E70: =COUNTIFS('Feature Register'!$C$2:$C$634,A70,'Feature Register'!$AJ$2:$AJ$634,"Physical device observed") | F70: =COUNTIFS('Feature Register'!$C$2:$C$634,A70,'Feature Register'!$BE$2:$BE$634,"Blocked") | G70: =COUNTIFS('Feature Register'!$C$2:$C$634,A70,'Feature Register'!$BE$2:$BE$634,"Development required") | H70: =COUNTIFS('Feature Register'!$C$2:$C$634,A70,'Feature Register'!$BE$2:$BE$634,"Ready for production validation") | I70: =COUNTIFS('Feature Register'!$C$2:$C$634,A70,'Feature Register'!$BE$2:$BE$634,"Not assessed") | J70: =COUNTIFS('Feature Register'!$C$2:$C$634,A70,'Feature Register'!$BE$2:$BE$634,"Production ready")
A71: Homepage feeds and header | B71: =COUNTIF('Feature Register'!$C$2:$C$634,A71) | C71: =COUNTIFS('Feature Register'!$C$2:$C$634,A71,'Feature Register'!$S$2:$S$634,"Scaffold only")+COUNTIFS('Feature Register'!$C$2:$C$634,A71,'Feature Register'!$S$2:$S$634,"UI only")+COUNTIFS('Feature Register'!$C$2:$C$634,A71,'Feature Register'!$S$2:$S$634,"Backend only")+COUNTIFS('Feature Register'!$C$2:$C$634,A71,'Feature Register'!$S$2:$S$634,"Partial")+COUNTIFS('Feature Register'!$C$2:$C$634,A71,'Feature Register'!$S$2:$S$634,"End-to-end present")+COUNTIFS('Feature Register'!$C$2:$C$634,A71,'Feature Register'!$S$2:$S$634,"Conflicting implementations") | D71: =COUNTIFS('Feature Register'!$C$2:$C$634,A71,'Feature Register'!$AG$2:$AG$634,"Complete against stated requirement") | E71: =COUNTIFS('Feature Register'!$C$2:$C$634,A71,'Feature Register'!$AJ$2:$AJ$634,"Physical device observed") | F71: =COUNTIFS('Feature Register'!$C$2:$C$634,A71,'Feature Register'!$BE$2:$BE$634,"Blocked") | G71: =COUNTIFS('Feature Register'!$C$2:$C$634,A71,'Feature Register'!$BE$2:$BE$634,"Development required") | H71: =COUNTIFS('Feature Register'!$C$2:$C$634,A71,'Feature Register'!$BE$2:$BE$634,"Ready for production validation") | I71: =COUNTIFS('Feature Register'!$C$2:$C$634,A71,'Feature Register'!$BE$2:$BE$634,"Not assessed") | J71: =COUNTIFS('Feature Register'!$C$2:$C$634,A71,'Feature Register'!$BE$2:$BE$634,"Production ready")
A72: Live, Battles, Your BLYP, Teams, and games header | B72: =COUNTIF('Feature Register'!$C$2:$C$634,A72) | C72: =COUNTIFS('Feature Register'!$C$2:$C$634,A72,'Feature Register'!$S$2:$S$634,"Scaffold only")+COUNTIFS('Feature Register'!$C$2:$C$634,A72,'Feature Register'!$S$2:$S$634,"UI only")+COUNTIFS('Feature Register'!$C$2:$C$634,A72,'Feature Register'!$S$2:$S$634,"Backend only")+COUNTIFS('Feature Register'!$C$2:$C$634,A72,'Feature Register'!$S$2:$S$634,"Partial")+COUNTIFS('Feature Register'!$C$2:$C$634,A72,'Feature Register'!$S$2:$S$634,"End-to-end present")+COUNTIFS('Feature Register'!$C$2:$C$634,A72,'Feature Register'!$S$2:$S$634,"Conflicting implementations") | D72: =COUNTIFS('Feature Register'!$C$2:$C$634,A72,'Feature Register'!$AG$2:$AG$634,"Complete against stated requirement") | E72: =COUNTIFS('Feature Register'!$C$2:$C$634,A72,'Feature Register'!$AJ$2:$AJ$634,"Physical device observed") | F72: =COUNTIFS('Feature Register'!$C$2:$C$634,A72,'Feature Register'!$BE$2:$BE$634,"Blocked") | G72: =COUNTIFS('Feature Register'!$C$2:$C$634,A72,'Feature Register'!$BE$2:$BE$634,"Development required") | H72: =COUNTIFS('Feature Register'!$C$2:$C$634,A72,'Feature Register'!$BE$2:$BE$634,"Ready for production validation") | I72: =COUNTIFS('Feature Register'!$C$2:$C$634,A72,'Feature Register'!$BE$2:$BE$634,"Not assessed") | J72: =COUNTIFS('Feature Register'!$C$2:$C$634,A72,'Feature Register'!$BE$2:$BE$634,"Production ready")
A73: Subscriber-only Dating destination | B73: =COUNTIF('Feature Register'!$C$2:$C$634,A73) | C73: =COUNTIFS('Feature Register'!$C$2:$C$634,A73,'Feature Register'!$S$2:$S$634,"Scaffold only")+COUNTIFS('Feature Register'!$C$2:$C$634,A73,'Feature Register'!$S$2:$S$634,"UI only")+COUNTIFS('Feature Register'!$C$2:$C$634,A73,'Feature Register'!$S$2:$S$634,"Backend only")+COUNTIFS('Feature Register'!$C$2:$C$634,A73,'Feature Register'!$S$2:$S$634,"Partial")+COUNTIFS('Feature Register'!$C$2:$C$634,A73,'Feature Register'!$S$2:$S$634,"End-to-end present")+COUNTIFS('Feature Register'!$C$2:$C$634,A73,'Feature Register'!$S$2:$S$634,"Conflicting implementations") | D73: =COUNTIFS('Feature Register'!$C$2:$C$634,A73,'Feature Register'!$AG$2:$AG$634,"Complete against stated requirement") | E73: =COUNTIFS('Feature Register'!$C$2:$C$634,A73,'Feature Register'!$AJ$2:$AJ$634,"Physical device observed") | F73: =COUNTIFS('Feature Register'!$C$2:$C$634,A73,'Feature Register'!$BE$2:$BE$634,"Blocked") | G73: =COUNTIFS('Feature Register'!$C$2:$C$634,A73,'Feature Register'!$BE$2:$BE$634,"Development required") | H73: =COUNTIFS('Feature Register'!$C$2:$C$634,A73,'Feature Register'!$BE$2:$BE$634,"Ready for production validation") | I73: =COUNTIFS('Feature Register'!$C$2:$C$634,A73,'Feature Register'!$BE$2:$BE$634,"Not assessed") | J73: =COUNTIFS('Feature Register'!$C$2:$C$634,A73,'Feature Register'!$BE$2:$BE$634,"Production ready")
A74: Free and £4.99 membership | B74: =COUNTIF('Feature Register'!$C$2:$C$634,A74) | C74: =COUNTIFS('Feature Register'!$C$2:$C$634,A74,'Feature Register'!$S$2:$S$634,"Scaffold only")+COUNTIFS('Feature Register'!$C$2:$C$634,A74,'Feature Register'!$S$2:$S$634,"UI only")+COUNTIFS('Feature Register'!$C$2:$C$634,A74,'Feature Register'!$S$2:$S$634,"Backend only")+COUNTIFS('Feature Register'!$C$2:$C$634,A74,'Feature Register'!$S$2:$S$634,"Partial")+COUNTIFS('Feature Register'!$C$2:$C$634,A74,'Feature Register'!$S$2:$S$634,"End-to-end present")+COUNTIFS('Feature Register'!$C$2:$C$634,A74,'Feature Register'!$S$2:$S$634,"Conflicting implementations") | D74: =COUNTIFS('Feature Register'!$C$2:$C$634,A74,'Feature Register'!$AG$2:$AG$634,"Complete against stated requirement") | E74: =COUNTIFS('Feature Register'!$C$2:$C$634,A74,'Feature Register'!$AJ$2:$AJ$634,"Physical device observed") | F74: =COUNTIFS('Feature Register'!$C$2:$C$634,A74,'Feature Register'!$BE$2:$BE$634,"Blocked") | G74: =COUNTIFS('Feature Register'!$C$2:$C$634,A74,'Feature Register'!$BE$2:$BE$634,"Development required") | H74: =COUNTIFS('Feature Register'!$C$2:$C$634,A74,'Feature Register'!$BE$2:$BE$634,"Ready for production validation") | I74: =COUNTIFS('Feature Register'!$C$2:$C$634,A74,'Feature Register'!$BE$2:$BE$634,"Not assessed") | J74: =COUNTIFS('Feature Register'!$C$2:$C$634,A74,'Feature Register'!$BE$2:$BE$634,"Production ready")
A75: Trust, safety, and moderation | B75: =COUNTIF('Feature Register'!$C$2:$C$634,A75) | C75: =COUNTIFS('Feature Register'!$C$2:$C$634,A75,'Feature Register'!$S$2:$S$634,"Scaffold only")+COUNTIFS('Feature Register'!$C$2:$C$634,A75,'Feature Register'!$S$2:$S$634,"UI only")+COUNTIFS('Feature Register'!$C$2:$C$634,A75,'Feature Register'!$S$2:$S$634,"Backend only")+COUNTIFS('Feature Register'!$C$2:$C$634,A75,'Feature Register'!$S$2:$S$634,"Partial")+COUNTIFS('Feature Register'!$C$2:$C$634,A75,'Feature Register'!$S$2:$S$634,"End-to-end present")+COUNTIFS('Feature Register'!$C$2:$C$634,A75,'Feature Register'!$S$2:$S$634,"Conflicting implementations") | D75: =COUNTIFS('Feature Register'!$C$2:$C$634,A75,'Feature Register'!$AG$2:$AG$634,"Complete against stated requirement") | E75: =COUNTIFS('Feature Register'!$C$2:$C$634,A75,'Feature Register'!$AJ$2:$AJ$634,"Physical device observed") | F75: =COUNTIFS('Feature Register'!$C$2:$C$634,A75,'Feature Register'!$BE$2:$BE$634,"Blocked") | G75: =COUNTIFS('Feature Register'!$C$2:$C$634,A75,'Feature Register'!$BE$2:$BE$634,"Development required") | H75: =COUNTIFS('Feature Register'!$C$2:$C$634,A75,'Feature Register'!$BE$2:$BE$634,"Ready for production validation") | I75: =COUNTIFS('Feature Register'!$C$2:$C$634,A75,'Feature Register'!$BE$2:$BE$634,"Not assessed") | J75: =COUNTIFS('Feature Register'!$C$2:$C$634,A75,'Feature Register'!$BE$2:$BE$634,"Production ready")
A76: First-time onboarding and personalisation | B76: =COUNTIF('Feature Register'!$C$2:$C$634,A76) | C76: =COUNTIFS('Feature Register'!$C$2:$C$634,A76,'Feature Register'!$S$2:$S$634,"Scaffold only")+COUNTIFS('Feature Register'!$C$2:$C$634,A76,'Feature Register'!$S$2:$S$634,"UI only")+COUNTIFS('Feature Register'!$C$2:$C$634,A76,'Feature Register'!$S$2:$S$634,"Backend only")+COUNTIFS('Feature Register'!$C$2:$C$634,A76,'Feature Register'!$S$2:$S$634,"Partial")+COUNTIFS('Feature Register'!$C$2:$C$634,A76,'Feature Register'!$S$2:$S$634,"End-to-end present")+COUNTIFS('Feature Register'!$C$2:$C$634,A76,'Feature Register'!$S$2:$S$634,"Conflicting implementations") | D76: =COUNTIFS('Feature Register'!$C$2:$C$634,A76,'Feature Register'!$AG$2:$AG$634,"Complete against stated requirement") | E76: =COUNTIFS('Feature Register'!$C$2:$C$634,A76,'Feature Register'!$AJ$2:$AJ$634,"Physical device observed") | F76: =COUNTIFS('Feature Register'!$C$2:$C$634,A76,'Feature Register'!$BE$2:$BE$634,"Blocked") | G76: =COUNTIFS('Feature Register'!$C$2:$C$634,A76,'Feature Register'!$BE$2:$BE$634,"Development required") | H76: =COUNTIFS('Feature Register'!$C$2:$C$634,A76,'Feature Register'!$BE$2:$BE$634,"Ready for production validation") | I76: =COUNTIFS('Feature Register'!$C$2:$C$634,A76,'Feature Register'!$BE$2:$BE$634,"Not assessed") | J76: =COUNTIFS('Feature Register'!$C$2:$C$634,A76,'Feature Register'!$BE$2:$BE$634,"Production ready")
A77: Notifications and reminders | B77: =COUNTIF('Feature Register'!$C$2:$C$634,A77) | C77: =COUNTIFS('Feature Register'!$C$2:$C$634,A77,'Feature Register'!$S$2:$S$634,"Scaffold only")+COUNTIFS('Feature Register'!$C$2:$C$634,A77,'Feature Register'!$S$2:$S$634,"UI only")+COUNTIFS('Feature Register'!$C$2:$C$634,A77,'Feature Register'!$S$2:$S$634,"Backend only")+COUNTIFS('Feature Register'!$C$2:$C$634,A77,'Feature Register'!$S$2:$S$634,"Partial")+COUNTIFS('Feature Register'!$C$2:$C$634,A77,'Feature Register'!$S$2:$S$634,"End-to-end present")+COUNTIFS('Feature Register'!$C$2:$C$634,A77,'Feature Register'!$S$2:$S$634,"Conflicting implementations") | D77: =COUNTIFS('Feature Register'!$C$2:$C$634,A77,'Feature Register'!$AG$2:$AG$634,"Complete against stated requirement") | E77: =COUNTIFS('Feature Register'!$C$2:$C$634,A77,'Feature Register'!$AJ$2:$AJ$634,"Physical device observed") | F77: =COUNTIFS('Feature Register'!$C$2:$C$634,A77,'Feature Register'!$BE$2:$BE$634,"Blocked") | G77: =COUNTIFS('Feature Register'!$C$2:$C$634,A77,'Feature Register'!$BE$2:$BE$634,"Development required") | H77: =COUNTIFS('Feature Register'!$C$2:$C$634,A77,'Feature Register'!$BE$2:$BE$634,"Ready for production validation") | I77: =COUNTIFS('Feature Register'!$C$2:$C$634,A77,'Feature Register'!$BE$2:$BE$634,"Not assessed") | J77: =COUNTIFS('Feature Register'!$C$2:$C$634,A77,'Feature Register'!$BE$2:$BE$634,"Production ready")
... A95: Quality assurance and release readiness | B95: =COUNTIF('Feature Register'!$C$2:$C$634,A95) | C95: =COUNTIFS('Feature Register'!$C$2:$C$634,A95,'Feature Register'!$S$2:$S$634,"Scaffold only")+COUNTIFS('Feature Register'!$C$2:$C$634,A95,'Feature Register'!$S$2:$S$634,"UI only")+COUNTIFS('Feature Register'!$C$2:$C$634,A95,'Feature Register'!$S$2:$S$634,"Backend only")+COUNTIFS('Feature Register'!$C$2:$C$634,A95,'Feature Register'!$S$2:$S$634,"Partial")+COUNTIFS('Feature Register'!$C$2:$C$634,A95,'Feature Register'!$S$2:$S$634,"End-to-end present")+COUNTIFS('Feature Register'!$C$2:$C$634,A95,'Feature Register'!$S$2:$S$634,"Conflicting implementations") | D95: =COUNTIFS('Feature Register'!$C$2:$C$634,A95,'Feature Register'!$AG$2:$AG$634,"Complete against stated requirement") | E95: =COUNTIFS('Feature Register'!$C$2:$C$634,A95,'Feature Register'!$AJ$2:$AJ$634,"Physical device observed") | F95: =COUNTIFS('Feature Register'!$C$2:$C$634,A95,'Feature Register'!$BE$2:$BE$634,"Blocked") | G95: =COUNTIFS('Feature Register'!$C$2:$C$634,A95,'Feature Register'!$BE$2:$BE$634,"Development required") | H95: =COUNTIFS('Feature Register'!$C$2:$C$634,A95,'Feature Register'!$BE$2:$BE$634,"Ready for production validation") | I95: =COUNTIFS('Feature Register'!$C$2:$C$634,A95,'Feature Register'!$BE$2:$BE$634,"Not assessed") | J95: =COUNTIFS('Feature Register'!$C$2:$C$634,A95,'Feature Register'!$BE$2:$BE$634,"Production ready")

Sheet Feature Register
A1: Feature ID | B1: Parent Feature ID | C1: Product Area | D1: Area Number | E1: Area Sequence | F1: Record Type | G1: Feature Name | H1: Source Requirement | I1: Source Location | J1: Normalization Location | K1: Intended Scope | L1: Intended Actor | M1: Intended Surface | N1: Intended Outcome | O1: Acceptance Criteria | P1: Dependencies | Q1: Prior Audit Label | R1: Prior Audit Note | S1: Implementation State | T1: Client Entry and Navigation | U1: UI Components and Screens | V1: Client State and Services | W1: Server Routes and Handlers | X1: Data Stores | Y1: Workers and Async Paths | Z1: External Services | AA1: Configuration and Permissions | AB1: Deployable Runtime | AC1: Runtime Path ID | AD1: Runtime Path Narrative | AE1: Reachability | AF1: Reachability Detail | AG1: Functional Completeness | AH1: Complete Against Requirement? | AI1: Known Gaps | AJ1: Verification State | AK1: Source Evidence IDs | AL1: Test Evidence IDs | AM1: Observed Evidence IDs | AN1: Last Verified At | AO1: Verified Revision or Build | AP1: Evidence Confidence | AQ1: Gate — Scope and Acceptance | AR1: Gate — Architecture and Authority | AS1: Gate — Functional Behaviour | AT1: Gate — Identity and Permissions | AU1: Gate — Data Integrity | AV1: Gate — Privacy and Consent | AW1: Gate — Safety and Abuse | AX1: Gate — Commerce and Entitlement | AY1: Gate — Security | AZ1: Gate — Reliability and Scale | BA1: Gate — Observability and Operations | BB1: Gate — Accessibility and Device Coverage | BC1: Gate — Legal and Policy | BD1: Gate — Release-candidate Verification | BE1: Production Conclusion | BF1: Production Blockers | BG1: Required Next Evidence | BH1: Owner | BI1: Approved By | BJ1: Approved At | BK1: Review Notes | BL1: Last Updated
A2: BLYP-01-001 | C2: BLYP Bar and AI-assisted posting | D2: 1 | E2: 1 | F2: Feature | G2: BLYP Bar conversational interface | H2: BLYP Bar conversational interface | I2: /home/ubuntu/blyp_product_requirements.md :: Section 1 — BLYP Bar and AI-assisted posting | J2: /home/ubuntu/BLYP_COMPLETE_FEATURE_LIST.md:16 | K2: Required | L2: Applicable BLYP member | M2: BLYP mobile application and supporting production services | N2: BLYP Bar conversational interface | O2: Not explicitly defined in the product source; requires accountable product approval before production sign-off. | Q2: Yes | R2: a bounded BLYP Bar dispatcher exists. | S2: Not found | T2: Not found | U2: Not found | V2: Not found | W2: Not found | X2: Unknown | Y2: Not found | Z2: Not found | AA2: Not found | AB2: Unknown | AE2: Unknown | AG2: Not started | AH2: No | AI2: Searched all non-node_modules source files for 'BLYP Bar', 'BlypBar', 'blypBar', 'blyp-bar', 'blyp_bar'. No component, screen, service, route, or data model matching a BLYP Bar conversational interface was found. The feature may exist under a different identifier not covered by this search. | AJ2: Not verified | AK2: EV-01-0001 | AO2: 8bc0dcb2a1da1b21368c5536aaeef829d587f316 | AP2: Low | AQ2: Not assessed | AR2: Not assessed | AS2: Fail | AT2: Not assessed | AU2: Not assessed | AV2: Not assessed | AW2: Not assessed | AX2: Not assessed | AY2: Not assessed | AZ2: Not assessed | BA2: Not assessed | BB2: Not assessed | BC2: Not assessed | BD2: Not assessed | BE2: Development required | BF2: Physical implementation is not complete against the stated requirement.; Searched all non-node_modules source files for 'BLYP Bar', 'BlypBar', 'blypBar', 'blyp-bar', 'blyp_bar'. No component, screen, service, route, or data model matching a BLYP Bar conversational interface was found. The feature may exist under a different identifier not covered by this search. | BG2: Identify the actual file/component name for the BLYP Bar dispatcher; search for it; confirm wiring in navigation stack. | BK2: Evidence reconciled against the reviewed source revision. No production approval is inferred from implementation or file presence. | BL2: 2026-08-02
A3: BLYP-01-002 | C3: BLYP Bar and AI-assisted posting | D3: 1 | E3: 2 | F3: Feature | G3: Battle-request interpretation | H3: Battle-request interpretation | I3: /home/ubuntu/blyp_product_requirements.md :: Section 1 — BLYP Bar and AI-assisted posting | J3: /home/ubuntu/BLYP_COMPLETE_FEATURE_LIST.md:17 | K3: Required | L3: Applicable BLYP member | M3: BLYP mobile application and supporting production services | N3: Battle-request interpretation | O3: Not explicitly defined in the product source; requires accountable product approval before production sign-off. | Q3: Yes | S3: Not found | T3: Not found | U3: Not found | V3: Not found | W3: Not found | X3: Unknown | Y3: Not found | Z3: Not found | AA3: Not found | AB3: Unknown | AE3: Unknown | AG3: Not started | AH3: No | AI3: No client-side battle-request parsing or interpretation layer found. Backend economy route POST /promote/battle exists but is a coin-spend feature unrelated to BLYP Bar dispatch. Searched for 'battle' in client AI/dispatch context. | AJ3: Not verified | AK3: EV-01-0002;EV-01-0003 | AO3: 8bc0dcb2a1da1b21368c5536aaeef829d587f316 | AP3: Low | AQ3: Not assessed | AR3: Not assessed | AS3: Fail | AT3: Not assessed | AU3: Not assessed | AV3: Not assessed | AW3: Not assessed | AX3: Not assessed | AY3: Not assessed | AZ3: Not assessed | BA3: Not assessed | BB3: Not assessed | BC3: Not assessed | BD3: Not assessed | BE3: Development required | BF3: Physical implementation is not complete against the stated requirement.; No client-side battle-request parsing or interpretation layer found. Backend economy route POST /promote/battle exists but is a coin-spend feature unrelated to BLYP Bar dispatch. Searched for 'battle' in client AI/dispatch context. | BG3: Identify BLYP Bar dispatcher code; search for battle-request parsing logic within it. | BK3: Evidence reconciled against the reviewed source revision. No production approval is inferred from implementation or file presence. | BL3: 2026-08-02
A4: BLYP-01-003 | C4: BLYP Bar and AI-assisted posting | D4: 1 | E4: 3 | F4: Feature | G4: Opponent resolution for a Battle request | H4: Opponent resolution for a Battle request | I4: /home/ubuntu/blyp_product_requirements.md :: Section 1 — BLYP Bar and AI-assisted posting | J4: /home/ubuntu/BLYP_COMPLETE_FEATURE_LIST.md:18 | K4: Required | L4: Applicable BLYP member | M4: BLYP mobile application and supporting production services | N4: Opponent resolution for a Battle request | O4: Not explicitly defined in the product source; requires accountable product approval before production sign-off. | Q4: Yes | S4: Not found | T4: Not found | U4: Not found | V4: Not found | W4: Not found | X4: Unknown | Y4: Not found | Z4: Not found | AA4: Not found | AB4: Unknown | AE4: Unknown | AG4: Not started | AH4: No | AI4: No opponent resolution logic found in client source. Searched for 'opponent', 'resolution', 'battle' in client AI/dispatch context. No user lookup or matching service for battle opponents found. | AJ4: Not verified | AK4: EV-01-0002;EV-01-0003 | AO4: 8bc0dcb2a1da1b21368c5536aaeef829d587f316 | AP4: Low | AQ4: Not assessed | AR4: Not assessed | AS4: Fail | AT4: Not assessed | AU4: Not assessed | AV4: Not assessed | AW4: Not assessed | AX4: Not assessed | AY4: Not assessed | AZ4: Not assessed | BA4: Not assessed | BB4: Not assessed | BC4: Not assessed | BD4: Not assessed | BE4: Development required | BF4: Physical implementation is not complete against the stated requirement.; No opponent resolution logic found in client source. Searched for 'opponent', 'resolution', 'battle' in client AI/dispatch context. No user lookup or matching service for battle opponents found. | BG4: Identify BLYP Bar dispatcher; search for opponent resolution/lookup logic. | BK4: Evidence reconciled against the reviewed source revision. No production approval is inferred from implementation or file presence. | BL4: 2026-08-02
A5: BLYP-01-004 | C5: BLYP Bar and AI-assisted posting | D5: 1 | E5: 4 | F5: Feature | G5: Prefilled Battle creation flow | H5: Prefilled Battle creation flow | I5: /home/ubuntu/blyp_product_requirements.md :: Section 1 — BLYP Bar and AI-assisted posting | J5: /home/ubuntu/BLYP_COMPLETE_FEATURE_LIST.md:19 | K5: Required | L5: Applicable BLYP member | M5: BLYP mobile application and supporting production services | N5: Prefilled Battle creation flow | O5: Not explicitly defined in the product source; requires accountable product approval before production sign-off. | Q5: Yes | S5: Not found | T5: Not found | U5: Not found | V5: Not found | W5: Not found | X5: Unknown | Y5: Not found | Z5: Not found | AA5: Not found | AB5: Unknown | AE5: Unknown | AG5: Not started | AH5: No | AI5: No prefilled battle creation flow found. Searched for 'prefill', 'Prefill', 'battle' in client navigation/creation context. No navigation to a battle creation screen with pre-populated fields was found. | AJ5: Not verified | AK5: EV-01-0002;EV-01-0003 | AO5: 8bc0dcb2a1da1b21368c5536aaeef829d587f316 | AP5: Low | AQ5: Not assessed | AR5: Not assessed | AS5: Fail | AT5: Not assessed | AU5: Not assessed | AV5: Not assessed | AW5: Not assessed | AX5: Not assessed | AY5: Not assessed | AZ5: Not assessed | BA5: Not assessed | BB5: Not assessed | BC5: Not assessed | BD5: Not assessed | BE5: Development required | BF5: Physical implementation is not complete against the stated requirement.; No prefilled battle creation flow found. Searched for 'prefill', 'Prefill', 'battle' in client navigation/creation context. No navigation to a battle creation screen with pre-populated fields was found. | BG5: Identify BLYP Bar dispatcher; search for prefilled battle creation navigation. | BK5: Evidence reconciled against the reviewed source revision. No production approval is inferred from implementation or file presence. | BL5: 2026-08-02
A6: BLYP-01-005 | C6: BLYP Bar and AI-assisted posting | D6: 1 | E6: 5 | F6: Feature | G6: Event watches | H6: Event watches | I6: /home/ubuntu/blyp_product_requirements.md :: Section 1 — BLYP Bar and AI-assisted posting | J6: /home/ubuntu/BLYP_COMPLETE_FEATURE_LIST.md:20 | K6: Required | L6: Authenticated or eligible viewer | M6: BLYP mobile application and supporting production services | N6: Event watches | O6: Not explicitly defined in the product source; requires accountable product approval before production sign-off. | Q6: Yes | S6: Not found | T6: Not found | U6: Not found | V6: Not found | W6: Not found | X6: Unknown | Y6: Not found | Z6: Not found | AA6: Not found | AB6: Unknown | AE6: Unknown | AG6: Not started | AH6: No | AI6: No event-watch subscription feature found. Searched for 'watch', 'Watch' in event/creator context. Only found totalWatchTime analytics and 'watching' viewer count labels. No event watch data model, service, or UI found. | AJ6: Not verified | AK6: EV-01-0004 | AO6: 8bc0dcb2a1da1b21368c5536aaeef829d587f316 | AP6: Low | AQ6: Not assessed | AR6: Not assessed | AS6: Fail | AT6: Not assessed | AU6: Not assessed | AV6: Not assessed | AW6: Not assessed | AX6: Not assessed | AY6: Not assessed | AZ6: Not assessed | BA6: Not assessed | BB6: Not assessed | BC6: Not assessed | BD6: Not assessed | BE6: Development required | BF6: Physical implementation is not complete against the stated requirement.; No event-watch subscription feature found. Searched for 'watch', 'Watch' in event/creator context. Only found totalWatchTime analytics and 'watching' viewer count labels. No event watch data model, service, or UI found. | BG6: Search for event subscription/watch feature under alternate identifiers; check Firestore collections for watch/subscription documents. | BK6: Evidence reconciled against the reviewed source revision. No production approval is inferred from implementation or file presence. | BL6: 2026-08-02
A7: BLYP-01-006 | C7: BLYP Bar and AI-assisted posting | D7: 1 | E7: 6 | F7: Feature | G7: Creator/user watches | H7: Creator/user watches | I7: /home/ubuntu/blyp_product_requirements.md :: Section 1 — BLYP Bar and AI-assisted posting | J7: /home/ubuntu/BLYP_COMPLETE_FEATURE_LIST.md:21 | K7: Required | L7: Authenticated creator or host | M7: BLYP mobile application and supporting production services | N7: Creator/user watches | O7: Not explicitly defined in the product source; requires accountable product approval before production sign-off. | Q7: Yes | S7: Not found | T7: Not found | U7: Not found | V7: Not found | W7: Not found | X7: Unknown | Y7: Not found | Z7: Not found | AA7: Not found | AB7: Unknown | AE7: Unknown | AG7: Not started | AH7: No | AI7: No creator/user watch subscription feature found. Searched for 'watch', 'Watch', 'creator', 'follow', 'subscribe' in relevant context. No creator-watch data model, service, or UI found. | AJ7: Not verified | AK7: EV-01-0004 | AO7: 8bc0dcb2a1da1b21368c5536aaeef829d587f316 | AP7: Low | AQ7: Not assessed | AR7: Not assessed | AS7: Fail | AT7: Not assessed | AU7: Not assessed | AV7: Not assessed | AW7: Not assessed | AX7: Not assessed | AY7: Not assessed | AZ7: Not assessed | BA7: Not assessed | BB7: Not assessed | BC7: Not assessed | BD7: Not assessed | BE7: Development required | BF7: Physical implementation is not complete against the stated requirement.; No creator/user watch subscription feature found. Searched for 'watch', 'Watch', 'creator', 'follow', 'subscribe' in relevant context. No creator-watch data model, service, or UI found. | BG7: Search for creator/user subscription feature under alternate identifiers; check Firestore collections. | BK7: Evidence reconciled against the reviewed source revision. No production approval is inferred from implementation or file presence. | BL7: 2026-08-02
A8: BLYP-01-007 | C8: BLYP Bar and AI-assisted posting | D8: 1 | E8: 7 | F8: Feature | G8: Notification when a watched creator next goes live | H8: Notification when a watched creator next goes live | I8: /home/ubuntu/blyp_product_requirements.md :: Section 1 — BLYP Bar and AI-assisted posting | J8: /home/ubuntu/BLYP_COMPLETE_FEATURE_LIST.md:22 | K8: Required | L8: Authenticated creator or host | M8: BLYP mobile application and supporting production services | N8: Notification when a watched creator next goes live | O8: Not explicitly defined in the product source; requires accountable product approval before production sign-off. | Q8: Partial | R8: watch persistence exists; the complete notification journey needs verification. | S8: Not found | T8: Not found | U8: Not found | V8: Not found | W8: Not found | X8: Unknown | Y8: Not found | Z8: Not found | AA8: Not found | AB8: Unknown | AE8: Unknown | AG8: Not started | AH8: No | AI8: No notification-when-watched-creator-goes-live feature found. Searched for 'reminder', 'Reminder', 'notification', 'Notification', 'live', 'watch' in relevant context. No push notification trigger for watched creator going live was found. | AJ8: Not verified | AK8: EV-01-0004;EV-01-0005 | AO8: 8bc0dcb2a1da1b21368c5536aaeef829d587f316 | AP8: Low | AQ8: Not assessed | AR8: Not assessed | AS8: Fail | AT8: Not assessed | AU8: Not assessed | AV8: Not assessed | AW8: Not assessed | AX8: Not assessed | AY8: Not assessed | AZ8: Not assessed | BA8: Not assessed | BB8: Not assessed | BC8: Not assessed | BD8: Not assessed | BE8: Development required | BF8: Physical implementation is not complete against the stated requirement.; No notification-when-watched-creator-goes-live feature found. Searched for 'reminder', 'Reminder', 'notification', 'Notification', 'live', 'watch' in relevant context. No push notification trigger for watched creator going live was found. | BG8: Search for push notification service and live-start trigger; check Firebase Functions for notification dispatch. | BK8: Evidence reconciled against the reviewed source revision. No production approval is inferred from implementation or file presence. | BL8: 2026-08-02
A9: BLYP-01-008 | C9: BLYP Bar and AI-assisted posting | D9: 1 | E9: 8 | F9: Feature | G9: Single-reminder creation | H9: Single-reminder creation | I9: /home/ubuntu/blyp_product_requirements.md :: Section 1 — BLYP Bar and AI-assisted posting | J9: /home/ubuntu/BLYP_COMPLETE_FEATURE_LIST.md:23 | K9: Required | L9: Applicable BLYP member | M9: BLYP mobile application and supporting production services | N9: Single-reminder creation | O9: Not explicitly defined in the product source; requires accountable product approval before production sign-off. | Q9: Yes | S9: Not found | T9: Not found | U9: Not found | V9: Not found | W9: Not found | X9: Unknown | Y9: Not found | Z9: Not found | AA9: Not found | AB9: Unknown | AE9: Unknown | AG9: Not started | AH9: No | AI9: No single-reminder creation feature found. Searched for 'reminder', 'Reminder' across all source files - zero results. | AJ9: Not verified | AK9: EV-01-0005 | AO9: 8bc0dcb2a1da1b21368c5536aaeef829d587f316 | AP9: Low | AQ9: Not assessed | AR9: Not assessed | AS9: Fail | AT9: Not assessed | AU9: Not assessed | AV9: Not assessed | AW9: Not assessed | AX9: Not assessed | AY9: Not assessed | AZ9: Not assessed | BA9: Not assessed | BB9: Not assessed | BC9: Not assessed | BD9: Not assessed | BE9: Development required | BF9: Physical implementation is not complete against the stated requirement.; No single-reminder creation feature found. Searched for 'reminder', 'Reminder' across all source files - zero results. | BG9: Search for reminder/scheduling feature under alternate identifiers; check Firebase Functions for scheduled notifications. | BK9: Evidence reconciled against the reviewed source revision. No production approval is inferred from implementation or file presence. | BL9: 2026-08-02
A10: BLYP-01-009 | C10: BLYP Bar and AI-assisted posting | D10: 1 | E10: 9 | F10: Feature | G10: Multi-event reminder planning | H10: Multi-event reminder planning | I10: /home/ubuntu/blyp_product_requirements.md :: Section 1 — BLYP Bar and AI-assisted posting | J10: /home/ubuntu/BLYP_COMPLETE_FEATURE_LIST.md:24 | K10: Required | L10: Applicable BLYP member | M10: BLYP mobile application and supporting production services | N10: Multi-event reminder planning | O10: Not explicitly defined in the product source; requires accountable product approval before production sign-off. | Q10: Yes | S10: Not found | T10: Not found | U10: Not found | V10: Not found | W10: Not found | X10: Unknown | Y10: Not found | Z10: Not found | AA10: Not found | AB10: Unknown | AE10: Unknown | AG10: Not started | AH10: No | AI10: No multi-event reminder planning feature found. Searched for 'reminder', 'Reminder', 'multi', 'planning' across all source files - zero results for reminder. | AJ10: Not verified | AK10: EV-01-0005 | AO10: 8bc0dcb2a1da1b21368c5536aaeef829d587f316 | AP10: Low | AQ10: Not assessed | AR10: Not assessed | AS10: Fail | AT10: Not assessed | AU10: Not assessed | AV10: Not assessed | AW10: Not assessed | AX10: Not assessed | AY10: Not assessed | AZ10: Not assessed | BA10: Not assessed | BB10: Not assessed | BC10: Not assessed | BD10: Not assessed | BE10: Development required | BF10: Physical implementation is not complete against the stated requirement.; No multi-event reminder planning feature found. Searched for 'reminder', 'Reminder', 'multi', 'planning' across all source files - zero results for reminder. | BG10: Search for multi-event scheduling/reminder feature under alternate identifiers. | BK10: Evidence reconciled against the reviewed source revision. No production approval is inferred from implementation or file presence. | BL10: 2026-08-02
A11: BLYP-01-010 | C11: BLYP Bar and AI-assisted posting | D11: 1 | E11: 10 | F11: Feature | G11: In-app content search from the BLYP Bar | H11: In-app content search from the BLYP Bar | I11: /home/ubuntu/blyp_product_requirements.md :: Section 1 — BLYP Bar and AI-assisted posting | J11: /home/ubuntu/BLYP_COMPLETE_FEATURE_LIST.md:25 | K11: Required | L11: Applicable BLYP member | M11: BLYP mobile application and supporting production services | N11: In-app content search from the BLYP Bar | O11: Not explicitly defined in the product source; requires accountable product approval before production sign-off. | P11: Firestore (imported but mock data used); Firestore (imported but mock data used for posts); hardcoded suggestedUsers; Firebase config (src/config/firebase.js) | Q11: Yes | S11: Partial | T11: App.js Stack.Screen name='Search' (line 199); SearchScreen.js | U11: SearchScreen.js; SearchResultsScreen.js | V11: searchService.globalSearch / searchUsers / searchPosts / searchHashtags / searchLocations | W11: Not found (client-side only; Firestore queries not fully wired) | X11: Firestore (imported but mock data used for posts); hardcoded suggestedUsers | Y11: Not found | Z11: Firestore (imported but mock data used) | AA11: Firebase config (src/config/firebase.js) | AB11: Expo mobile client | AC11: RP-002 | AD11: User navigates to Search tab; SearchScreen calls searchService.globalSearch; searchService returns mock posts and filtered hardcoded users; no BLYP Bar integration found. | AE11: User reachable | AF11: App.js Stack.Screen name='Search' (line 199); SearchScreen.js; User navigates to Search tab; SearchScreen calls searchService.globalSearch; searchService returns mock posts and filtered hardcoded users; no BLYP Bar integration found. | AG11: Incomplete | AH11: No | AI11: searchPosts returns mock data (searchService.js:101-102). No BLYP Bar integration found. Search is not AI-powered. Firestore-backed live search not confirmed. No BLYP Bar entry point found. | AJ11: Source traced | AK11: EV-01-0006;EV-01-0007;EV-01-0037 | AO11: 8bc0dcb2a1da1b21368c5536aaeef829d587f316 | AP11: Medium | AQ11: Not assessed | AR11: Not assessed | AS11: Fail | AT11: Not assessed | AU11: Not assessed | AV11: Not assessed | AW11: Not assessed | AX11: Not assessed | AY11: Not assessed | AZ11: Not assessed | BA11: Not assessed | BB11: Not assessed | BC11: Not assessed | BD11: Not assessed | BE11: Development required | BF11: Physical implementation is not complete against the stated requirement.; searchPosts returns mock data (searchService.js:101-102). No BLYP Bar integration found. Search is not AI-powered. Firestore-backed live search not confirmed. No BLYP Bar entry point found. | BG11: Confirm live Firestore search queries; confirm BLYP Bar integration if required; test on device. | BK11: Evidence reconciled against the reviewed source revision. No production approval is inferred from implementation or file presence. | BL11: 2026-08-02
A12: BLYP-01-011 | C12: BLYP Bar and AI-assisted posting | D12: 1 | E12: 11 | F12: Feature | G12: Plus-gated Gemini answers | H12: Plus-gated Gemini answers | I12: /home/ubuntu/blyp_product_requirements.md :: Section 1 — BLYP Bar and AI-assisted posting | J12: /home/ubuntu/BLYP_COMPLETE_FEATURE_LIST.md:26 | K12: Required | L12: Applicable BLYP member | M12: BLYP mobile application and supporting production services | N12: Plus-gated Gemini answers | O12: Not explicitly defined in the product source; requires accountable product approval before production sign-off. | Q12: Yes | S12: Not found | T12: Not found | U12: Not found | V12: Not found | W12: Not found | X12: Unknown | Y12: Not found | Z12: Not found | AA12: Not found | AB12: Unknown | AE12: Unknown | AG12: Not started | AH12: No | AI12: No Plus-gated Gemini answers feature found. Searched for 'plus', 'Plus', 'premium', 'subscription', 'entitlement', 'gated' across all source files - zero results. No subscription tier or entitlement check for Gemini was found. | AJ12: Not verified | AK12: EV-01-0008 | AO12: 8bc0dcb2a1da1b21368c5536aaeef829d587f316 | AP12: Low | AQ12: Not assessed | AR12: Not assessed | AS12: Fail | AT12: Not assessed | AU12: Not assessed | AV12: Not assessed | AW12: Not assessed | AX12: Not assessed | AY12: Not assessed | AZ12: Not assessed | BA12: Not assessed | BB12: Not assessed | BC12: Not assessed | BD12: Not assessed | BE12: Development required | BF12: Physical implementation is not complete against the stated requirement.; No Plus-gated Gemini answers feature found. Searched for 'plus', 'Plus', 'premium', 'subscription', 'entitlement', 'gated' across all source files - zero results. No subscription tier or entitlement check for Gemini was found. | BG12: Search for subscription/entitlement service; check backend routes for Plus tier; check Firestore for user subscription documents. | BK12: Evidence reconciled against the reviewed source revision. No production approval is inferred from implementation or file presence. | BL12: 2026-08-02
A13: BLYP-01-012 | C13: BLYP Bar and AI-assisted posting | D13: 1 | E13: 12 | F13: Feature | G13: Generic autonomous action execution | H13: Generic autonomous action execution | I13: /home/ubuntu/blyp_product_requirements.md :: Section 1 — BLYP Bar and AI-assisted posting | J13: /home/ubuntu/BLYP_COMPLETE_FEATURE_LIST.md:27 | K13: Required | L13: Applicable BLYP member | M13: BLYP mobile application and supporting production services | N13: Generic autonomous action execution | O13: Not explicitly defined in the product source; requires accountable product approval before production sign-off. | Q13: No evidence | S13: Not found | T13: Not found | U13: Not found | V13: Not found | W13: Not found | X13: Unknown | Y13: Not found | Z13: Not found | AA13: Not found | AB13: Unknown | AE13: Unknown | AG13: Not started | AH13: No | AI13: No generic autonomous action execution framework found. Searched for 'autonomous', 'Autonomous', 'action execution', 'generic action' across all source files - zero results. | AJ13: Not verified | AK13: EV-01-0009 | AO13: 8bc0dcb2a1da1b21368c5536aaeef829d587f316 | AP13: Low | AQ13: Not assessed | AR13: Not assessed | AS13: Fail | AT13: Not assessed | AU13: Not assessed | AV13: Not assessed | AW13: Not assessed | AX13: Not assessed | AY13: Not assessed | AZ13: Not assessed | BA13: Not assessed | BB13: Not assessed | BC13: Not assessed | BD13: Not assessed | BE13: Development required | BF13: Physical implementation is not complete against the stated requirement.; No generic autonomous action execution framework found. Searched for 'autonomous', 'Autonomous', 'action execution', 'generic action' across all source files - zero results. | BG13: Identify BLYP Bar dispatcher; search for action-execution framework within it. | BK13: Evidence reconciled against the reviewed source revision. No production approval is inferred from implementation or file presence. | BL13: 2026-08-02
A14: BLYP-01-013 | C14: BLYP Bar and AI-assisted posting | D14: 1 | E14: 13 | F14: Feature | G14: AI assistant integrated into the post composer | H14: AI assistant integrated into the post composer | I14: /home/ubuntu/blyp_product_requirements.md :: Section 1 — BLYP Bar and AI-assisted posting | J14: /home/ubuntu/BLYP_COMPLETE_FEATURE_LIST.md:28 | K14: Required | L14: Applicable BLYP member | M14: BLYP mobile application and supporting production services | N14: AI assistant integrated into the post composer | O14: Not explicitly defined in the product source; requires accountable product approval before production sign-off. | P14: Gemini API (generativelanguage.googleapis.com) via client-side key; Firestore posts collection (post creation); Firebase Storage (media upload); EXPO_PUBLIC_GEMINI_API_KEY (app.config.js:8-19); camera/microphone permissions (app.config.js:44-62) | Q14: Yes | S14: Partial | T14: App.js Stack.Screen name='Review' (line 214); CameraScreen navigates to Review; VoiceMemoScreen navigates to Review | U14: ReviewScreen.js | V14: aiService; speechToTextService; geminiSpeechService; mediaDescriptionService; isGeneratingContent; aiSuggestions; aiCaption state | W14: Not found (direct client-to-Gemini API calls) | X14: Firestore posts collection (post creation); Firebase Storage (media upload) | Y14: Not found | Z14: Gemini API (generativelanguage.googleapis.com) via client-side key | AA14: EXPO_PUBLIC_GEMINI_API_KEY (app.config.js:8-19); camera/microphone permissions (app.config.js:44-62) | AB14: Expo mobile client | AC14: RP-002 | AD14: User navigates to Camera/VoiceMemo, captures media, lands on ReviewScreen. ReviewScreen provides AI-assisted caption generation via Gemini API. No separate composer screen found; ReviewScreen IS the composer. | AE14: User reachable | AF14: App.js Stack.Screen name='Review' (line 214); CameraScreen navigates to Review; VoiceMemoScreen navigates to Review; User navigates to Camera/VoiceMemo, captures media, lands on ReviewScreen. ReviewScreen provides AI-assisted caption generation via Gemini API. No separate composer screen found; ReviewScreen IS the composer. | AG14: Incomplete | AH14: No | AI14: No dedicated 'composer' screen separate from ReviewScreen. AI calls go directly to Gemini API from client (not server-proxied). No BLYP Bar integration found. No Plus/entitlement gating. Three distinct caption choices not implemented. | AJ14: Source traced | AK14: EV-01-0010;EV-01-0033 | AO14: 8bc0dcb2a1da1b21368c5536aaeef829d587f316 | AP14: Medium | AQ14: Not assessed | AR14: Not assessed | AS14: Fail | AT14: Not assessed | AU14: Not assessed | AV14: Not assessed | AW14: Not assessed | AX14: Not assessed | AY14: Not assessed | AZ14: Not assessed | BA14: Not assessed | BB14: Not assessed | BC14: Not assessed | BD14: Not assessed | BE14: Development required | BF14: Physical implementation is not complete against the stated requirement.; No dedicated 'composer' screen separate from ReviewScreen. AI calls go directly to Gemini API from client (not server-proxied). No BLYP Bar integration found. No Plus/entitlement gating. Three distinct caption choices not implemented. | BG14: Confirm Gemini API key availability in production build; test AI generation on device; confirm BLYP Bar integration if required. | BK14: Evidence reconciled against the reviewed source revision. No production approval is inferred from implementation or file presence. | BL14: 2026-08-02
A15: BLYP-01-014 | C15: BLYP Bar and AI-assisted posting | D15: 1 | E15: 14 | F15: Feature | G15: Photo capture | H15: Photo capture | I15: /home/ubuntu/blyp_product_requirements.md :: Section 1 — BLYP Bar and AI-assisted posting | J15: /home/ubuntu/BLYP_COMPLETE_FEATURE_LIST.md:29 | K15: Required | L15: Applicable BLYP member | M15: BLYP mobile application and supporting production services | N15: Photo capture | O15: Not explicitly defined in the product source; requires accountable product approval before production sign-off. | P15: Device media library (save); Firebase Storage (upload via ReviewScreen); NSCameraUsageDescription; android.permission.CAMERA (app.config.js:44, 56) | Q15: Yes | S15: Partial | T15: App.js Stack.Screen name='Camera' (line 209); CameraScreen.js | U15: CameraScreen.js; CameraView (expo-camera) | V15: capturedPhotos; CameraView.takePictureAsync; MediaLibrary.saveToLibraryAsync | W15: Not found | X15: Device media library (save); Firebase Storage (upload via ReviewScreen) | Y15: Not found | Z15: Not found | AA15: NSCameraUsageDescription; android.permission.CAMERA (app.config.js:44, 56) | AB15: Expo mobile client | AC15: RP-002 | AD15: User opens Camera screen, takes photo, photo is added to capturedPhotos array, navigates to Review screen with photos. | AE15: User reachable | AF15: App.js Stack.Screen name='Camera' (line 209); CameraScreen.js; User opens Camera screen, takes photo, photo is added to capturedPhotos array, navigates to Review screen with photos. | AG15: Incomplete | AH15: No | AI15: Physical device camera not verified. Emulator detection present (CameraScreen.js:45-55). Production build not verified. | AJ15: Source traced | AK15: EV-01-0011;EV-01-0034;EV-01-0039 | AO15: 8bc0dcb2a1da1b21368c5536aaeef829d587f316 | AP15: Medium | AQ15: Not assessed | AR15: Not assessed | AS15: Fail | AT15: Not assessed | AU15: Not assessed | AV15: Not assessed | AW15: Not assessed | AX15: Not assessed | AY15: Not assessed | AZ15: Not assessed | BA15: Not assessed | BB15: Not assessed | BC15: Not assessed | BD15: Not assessed | BE15: Development required | BF15: Physical implementation is not complete against the stated requirement.; Physical device camera not verified. Emulator detection present (CameraScreen.js:45-55). Production build not verified. | BG15: Test photo capture on physical device; verify production build. | BK15: Evidence reconciled against the reviewed source revision. No production approval is inferred from implementation or file presence. | BL15: 2026-08-02
A16: BLYP-01-015 | C16: BLYP Bar and AI-assisted posting | D16: 1 | E16: 15 | F16: Feature | G16: Video recording | H16: Video recording | I16: /home/ubuntu/blyp_product_requirements.md :: Section 1 — BLYP Bar and AI-assisted posting | J16: /home/ubuntu/BLYP_COMPLETE_FEATURE_LIST.md:30 | K16: Required | L16: Applicable BLYP member | M16: BLYP mobile application and supporting production services | N16: Video recording | O16: Not explicitly defined in the product source; requires accountable product approval before production sign-off. | P16: Device media library (save); Firebase Storage (upload via ReviewScreen); NSMicrophoneUsageDescription; android.permission.RECORD_AUDIO; android.permission.CAMERA (app.config.js:45, 57-58) | Q16: Yes | S16: Partial | T16: App.js Stack.Screen name='Camera' (line 209); CameraScreen.js | U16: CameraScreen.js; CameraView (expo-camera) | V16: isRecording; CameraView.recordAsync; ImagePicker.launchImageLibraryAsync (video) | W16: Not found | X16: Device media library (save); Firebase Storage (upload via ReviewScreen) | Y16: Not found | Z16: Not found | AA16: NSMicrophoneUsageDescription; android.permission.RECORD_AUDIO; android.permission.CAMERA (app.config.js:45, 57-58) | AB16: Expo mobile client | AC16: RP-002 | AD16: User opens Camera screen, records video via CameraView.recordAsync or system video picker, navigates to Review screen with video. | AE16: User reachable | AF16: App.js Stack.Screen name='Camera' (line 209); CameraScreen.js; User opens Camera screen, records video via CameraView.recordAsync or system video picker, navigates to Review screen with video. | AG16: Incomplete | AH16: No | AI16: Video recording noted as unreliable on emulator (CameraScreen.js:51). Physical device not verified. Production build not verified. | AJ16: Source traced | AK16: EV-01-0012;EV-01-0034;EV-01-0039 | AO16: 8bc0dcb2a1da1b21368c5536aaeef829d587f316 | AP16: Medium | AQ16: Not assessed | AR16: Not assessed | AS16: Fail | AT16: Not assessed | AU16: Not assessed | AV16: Not assessed | AW16: Not assessed | AX16: Not assessed | AY16: Not assessed | AZ16: Not assessed | BA16: Not assessed | BB16: Not assessed | BC16: Not assessed | BD16: Not assessed | BE16: Development required | BF16: Physical implementation is not complete against the stated requirement.; Video recording noted as unreliable on emulator (CameraScreen.js:51). Physical device not verified. Production build not verified. | BG16: Test video recording on physical device; verify production build. | BK16: Evidence reconciled against the reviewed source revision. No production approval is inferred from implementation or file presence. | BL16: 2026-08-02
A17: BLYP-01-016 | C17: BLYP Bar and AI-assisted posting | D17: 1 | E17: 16 | F17: Feature | G17: Phone-gallery media selection | H17: Phone-gallery media selection | I17: /home/ubuntu/blyp_product_requirements.md :: Section 1 — BLYP Bar and AI-assisted posting | J17: /home/ubuntu/BLYP_COMPLETE_FEATURE_LIST.md:31 | K17: Required | L17: Applicable BLYP member | M17: BLYP mobile application and supporting production services | N17: Phone-gallery media selection | O17: Not explicitly defined in the product source; requires accountable product approval before production sign-off. | P17: Device photo library; Firebase Storage (upload via ReviewScreen); NSPhotoLibraryUsageDescription; expo-media-library plugin (app.config.js:46, 79) | Q17: Yes | S17: Partial | T17: App.js Stack.Screen name='Camera' (line 209); CameraScreen.js openGallery() | U17: CameraScreen.js; galleryButton (line 581-585); ImagePicker | V17: ImagePicker.launchImageLibraryAsync; allowsMultipleSelection:true; selectionLimit:10 | W17: Not found | X17: Device photo library; Firebase Storage (upload via ReviewScreen) | Y17: Not found | Z17: Not found | AA17: NSPhotoLibraryUsageDescription; expo-media-library plugin (app.config.js:46, 79) | AB17: Expo mobile client | AC17: RP-002 | AD17: User taps gallery button in CameraScreen, ImagePicker opens phone gallery, selected photos navigate to ReviewScreen with source='gallery'. | AE17: User reachable | AF17: App.js Stack.Screen name='Camera' (line 209); CameraScreen.js openGallery(); User taps gallery button in CameraScreen, ImagePicker opens phone gallery, selected photos navigate to ReviewScreen with source='gallery'. | AG17: Incomplete | AH17: No | AI17: Physical device gallery access not verified. Production build not verified. | AJ17: Source traced | AK17: EV-01-0013;EV-01-0034;EV-01-0039 | AO17: 8bc0dcb2a1da1b21368c5536aaeef829d587f316 | AP17: Medium | AQ17: Not assessed | AR17: Not assessed | AS17: Fail | AT17: Not assessed | AU17: Not assessed | AV17: Not assessed | AW17: Not assessed | AX17: Not assessed | AY17: Not assessed | AZ17: Not assessed | BA17: Not assessed | BB17: Not assessed | BC17: Not assessed | BD17: Not assessed | BE17: Development required | BF17: Physical implementation is not complete against the stated requirement.; Physical device gallery access not verified. Production build not verified. | BG17: Test gallery selection on physical device; verify production build. | BK17: Evidence reconciled against the reviewed source revision. No production approval is inferred from implementation or file presence. | BL17: 2026-08-02
A18: BLYP-01-017 | C18: BLYP Bar and AI-assisted posting | D18: 1 | E18: 17 | F18: Feature | G18: Audio/voice-memo capture | H18: Audio/voice-memo capture | I18: /home/ubuntu/blyp_product_requirements.md :: Section 1 — BLYP Bar and AI-assisted posting | J18: /home/ubuntu/BLYP_COMPLETE_FEATURE_LIST.md:32 | K18: Required | L18: Applicable BLYP member | M18: BLYP mobile application and supporting production services | N18: Audio/voice-memo capture | O18: Not explicitly defined in the product source; requires accountable product approval before production sign-off. | P18: Local file system (audio URI); Firebase Storage (upload via ReviewScreen); NSMicrophoneUsageDescription; expo-av plugin; android.permission.RECORD_AUDIO (app.config.js:45, 75, 89) | Q18: Yes | S18: Partial | T18: App.js Stack.Screen name='VoiceMemo' (line 222); VoiceMemoScreen.js; ReviewScreen.js (Audio import) | U18: VoiceMemoScreen.js; ReviewScreen.js (voice recording UI) | V18: Audio.Recording.createAsync (expo-av); speechToTextService.startRecording; voiceMemo state | W18: Not found | X18: Local file system (audio URI); Firebase Storage (upload via ReviewScreen) | Y18: Not found | Z18: Not found | AA18: NSMicrophoneUsageDescription; expo-av plugin; android.permission.RECORD_AUDIO (app.config.js:45, 75, 89) | AB18: Expo mobile client | AC18: RP-002 | AD18: User opens VoiceMemoScreen or uses ReviewScreen voice button, records audio via expo-av, navigates to Review with audio URI. | AE18: User reachable | AF18: App.js Stack.Screen name='VoiceMemo' (line 222); VoiceMemoScreen.js; ReviewScreen.js (Audio import); User opens VoiceMemoScreen or uses ReviewScreen voice button, records audio via expo-av, navigates to Review with audio URI. | AG18: Incomplete | AH18: No | AI18: Physical device microphone not verified. Production build not verified. | AJ18: Source traced | AK18: EV-01-0014;EV-01-0035;EV-01-0036;EV-01-0039 | AO18: 8bc0dcb2a1da1b21368c5536aaeef829d587f316 | AP18: Medium | AQ18: Not assessed | AR18: Not assessed | AS18: Fail | AT18: Not assessed | AU18: Not assessed | AV18: Not assessed | AW18: Not assessed | AX18: Not assessed | AY18: Not assessed | AZ18: Not assessed | BA18: Not assessed | BB18: Not assessed | BC18: Not assessed | BD18: Not assessed | BE18: Development required | BF18: Physical implementation is not complete against the stated requirement.; Physical device microphone not verified. Production build not verified. | BG18: Test audio recording on physical device; verify production build. | BK18: Evidence reconciled against the reviewed source revision. No production approval is inferred from implementation or file presence. | BL18: 2026-08-02
A19: BLYP-01-018 | C19: BLYP Bar and AI-assisted posting | D19: 1 | E19: 18 | F19: Feature | G19: Manual post description and caption entry | H19: Manual post description and caption entry | I19: /home/ubuntu/blyp_product_requirements.md :: Section 1 — BLYP Bar and AI-assisted posting | J19: /home/ubuntu/BLYP_COMPLETE_FEATURE_LIST.md:33 | K19: Required | L19: Applicable BLYP member | M19: BLYP mobile application and supporting production services | N19: Manual post description and caption entry | O19: Not explicitly defined in the product source; requires accountable product approval before production sign-off. | P19: Firestore posts collection (caption field, line 1966) | Q19: Yes | S19: End-to-end present | T19: App.js Stack.Screen name='Review' (line 214); ReviewScreen.js | U19: ReviewScreen.js; aiCaptionInput TextInput (line 2582); manualDescription TextInput | V19: caption state; manualDescription state; setCaption; setManualDescription | W19: Not found (caption stored in Firestore post document) | X19: Firestore posts collection (caption field, line 1966) | Y19: Not found | Z19: Not found | AA19: Not found | AB19: Expo mobile client | AC19: RP-002 | AD19: User types description/caption in ReviewScreen TextInput; caption is stored in Firestore post document on submission. | AE19: User reachable | AF19: App.js Stack.Screen name='Review' (line 214); ReviewScreen.js; User types description/caption in ReviewScreen TextInput; caption is stored in Firestore post document on submission. | AG19: Complete against stated requirement | AH19: Yes | AI19: Production build and Firestore write not verified on device. | AJ19: Source traced | AK19: EV-01-0015;EV-01-0033 | AO19: 8bc0dcb2a1da1b21368c5536aaeef829d587f316 | AP19: Medium | AQ19: Not assessed | AR19: Not assessed | AS19: Not assessed | AT19: Not assessed | AU19: Not assessed | AV19: Not assessed | AW19: Not assessed | AX19: Not assessed | AY19: Not assessed | AZ19: Not assessed | BA19: Not assessed | BB19: Not assessed | BC19: Not assessed | BD19: Not assessed | BE19: Ready for production validation | BF19: Applicable production gates and acceptance checks have not been completed on an approved release candidate. | BG19: Test manual caption entry and post creation on device; verify Firestore write. | BK19: Evidence reconciled against the reviewed source revision. No production approval is inferred from implementation or file presence. | BL19: 2026-08-02
A20: BLYP-01-019 | C20: BLYP Bar and AI-assisted posting | D20: 1 | E20: 19 | F20: Feature | G20: Push-to-talk description | H20: Push-to-talk description | I20: /home/ubuntu/blyp_product_requirements.md :: Section 1 — BLYP Bar and AI-assisted posting | J20: /home/ubuntu/BLYP_COMPLETE_FEATURE_LIST.md:34 | K20: Required | L20: Applicable BLYP member | M20: BLYP mobile application and supporting production services | N20: Push-to-talk description | O20: Not explicitly defined in the product source; requires accountable product approval before production sign-off. | P20: Gemini API (for transcription after recording); Local file system (audio URI); NSMicrophoneUsageDescription; expo-av plugin; android.permission.RECORD_AUDIO | Q20: Yes | S20: Partial | T20: ReviewScreen.js; handleVoiceButtonPressIn/PressOut (lines 1001-1015); handleVoiceDescriptionPressIn/PressOut (lines 1494-1513) | U20: ReviewScreen.js; voiceButton (line 2389-2396); description overlay voice button (line 3111-3118) | V20: speechToTextService.startRecording/stopRecording; isRecording state; isTranscribing state | W20: Not found | X20: Local file system (audio URI) | Y20: Not found | Z20: Gemini API (for transcription after recording) | AA20: NSMicrophoneUsageDescription; expo-av plugin; android.permission.RECORD_AUDIO | AB20: Expo mobile client | AC20: RP-002 | AD20: User holds voice button in ReviewScreen (onPressIn/onPressOut), audio is recorded via speechToTextService, transcribed via Gemini, and used as caption input. | AE20: User reachable | AF20: ReviewScreen.js; handleVoiceButtonPressIn/PressOut (lines 1001-1015); handleVoiceDescriptionPressIn/PressOut (lines 1494-1513); User holds voice button in ReviewScreen (onPressIn/onPressOut), audio is recorded via speechToTextService, transcribed via Gemini, and used as caption input. | AG20: Incomplete | AH20: No | AI20: Physical device microphone not verified. Transcription depends on Gemini API key availability. Production build not verified. | AJ20: Source traced | AK20: EV-01-0016;EV-01-0036 | AO20: 8bc0dcb2a1da1b21368c5536aaeef829d587f316 | AP20: Medium | AQ20: Not assessed | AR20: Not assessed | AS20: Fail | AT20: Not assessed | AU20: Not assessed | AV20: Not assessed | AW20: Not assessed | AX20: Not assessed | AY20: Not assessed | AZ20: Not assessed | BA20: Not assessed | BB20: Not assessed | BC20: Not assessed | BD20: Not assessed | BE20: Development required | BF20: Physical implementation is not complete against the stated requirement.; Physical device microphone not verified. Transcription depends on Gemini API key availability. Production build not verified. | BG20: Test push-to-talk on physical device; verify Gemini transcription with production API key. | BK20: Evidence reconciled against the reviewed source revision. No production approval is inferred from implementation or file presence. | BL20: 2026-08-02
A21: BLYP-01-020 | C21: BLYP Bar and AI-assisted posting | D21: 1 | E21: 20 | F21: Feature | G21: Voice-to-text transcription | H21: Voice-to-text transcription | I21: /home/ubuntu/blyp_product_requirements.md :: Section 1 — BLYP Bar and AI-assisted posting | J21: /home/ubuntu/BLYP_COMPLETE_FEATURE_LIST.md:35 | K21: Required | L21: Applicable BLYP member | M21: BLYP mobile application and supporting production services | N21: Voice-to-text transcription | O21: Not explicitly defined in the product source; requires accountable product approval before production sign-off. | P21: Gemini API (generativelanguage.googleapis.com/v1beta/models/gemini-2.5-flash-preview-05-20); Local file system (audio URI); caption/voiceTranscript state; EXPO_PUBLIC_GEMINI_API_KEY; NSMicrophoneUsageDescription | Q21: Yes | S21: Partial | T21: ReviewScreen.js; stopVoiceDescription (line 503-530); VoiceMemoScreen.js | U21: ReviewScreen.js; VoiceMemoScreen.js | V21: geminiSpeechService.transcribeAudio; speechToTextService.transcribeAudio; isTranscribing state; voiceTranscript state | W21: Not found (direct client-to-Gemini API) | X21: Local file system (audio URI); caption/voiceTranscript state | Y21: Not found | Z21: Gemini API (generativelanguage.googleapis.com/v1beta/models/gemini-2.5-flash-preview-05-20) | AA21: EXPO_PUBLIC_GEMINI_API_KEY; NSMicrophoneUsageDescription | AB21: Expo mobile client | AC21: RP-002 | AD21: After recording, ReviewScreen calls geminiSpeechService.transcribeAudio(audioUri) which sends audio to Gemini API for transcription. Transcript is set as caption. | AE21: User reachable | AF21: ReviewScreen.js; stopVoiceDescription (line 503-530); VoiceMemoScreen.js; After recording, ReviewScreen calls geminiSpeechService.transcribeAudio(audioUri) which sends audio to Gemini API for transcription. Transcript is set as caption. | AG21: Incomplete | AH21: No | AI21: speechToTextService.transcribeAudio in demo mode returns placeholder string (line 339). Gemini API key must be present in production build. Physical device not verified. Direct client-to-API call (not server-proxied). | AJ21: Source traced | AK21: EV-01-0017;EV-01-0036 | AO21: 8bc0dcb2a1da1b21368c5536aaeef829d587f316 | AP21: Medium | AQ21: Not assessed | AR21: Not assessed | AS21: Fail | AT21: Not assessed | AU21: Not assessed | AV21: Not assessed | AW21: Not assessed | AX21: Not assessed | AY21: Not assessed | AZ21: Not assessed | BA21: Not assessed | BB21: Not assessed | BC21: Not assessed | BD21: Not assessed | BE21: Development required | BF21: Physical implementation is not complete against the stated requirement.; speechToTextService.transcribeAudio in demo mode returns placeholder string (line 339). Gemini API key must be present in production build. Physical device not verified. Direct client-to-API call (not server-proxied). | BG21: Verify Gemini API key in production build; test transcription on physical device. | BK21: Evidence reconciled against the reviewed source revision. No production approval is inferred from implementation or file presence. | BL21: 2026-08-02
A22: BLYP-01-021 | C22: BLYP Bar and AI-assisted posting | D22: 1 | E22: 21 | F22: Feature | G22: Creative-direction input for AI captions | H22: Creative-direction input for AI captions | I22: /home/ubuntu/blyp_product_requirements.md :: Section 1 — BLYP Bar and AI-assisted posting | J22: /home/ubuntu/BLYP_COMPLETE_FEATURE_LIST.md:36 | K22: Required | L22: Applicable BLYP member | M22: BLYP mobile application and supporting production services | N22: Creative-direction input for AI captions | O22: Not explicitly defined in the product source; requires accountable product approval before production sign-off. | P22: Gemini API (receives creative direction as part of context prompt); EXPO_PUBLIC_GEMINI_API_KEY | Q22: Partial | S22: Partial | T22: ReviewScreen.js; manualDescription TextInput; descriptionText state | U22: ReviewScreen.js; description method overlay; manualDescription input | V22: manualDescription state; descriptionText state; allContextualData.manualText | W22: Not found | X22: Not found | Y22: Not found | Z22: Gemini API (receives creative direction as part of context prompt) | AA22: EXPO_PUBLIC_GEMINI_API_KEY | AB22: Expo mobile client | AC22: RP-002 | AD22: User types creative direction in manualDescription TextInput; text is included in AI context prompt as 'Extra user context' in generateComprehensiveAIContent. | AE22: User reachable | AF22: ReviewScreen.js; manualDescription TextInput; descriptionText state; User types creative direction in manualDescription TextInput; text is included in AI context prompt as 'Extra user context' in generateComprehensiveAIContent. | AG22: Incomplete | AH22: No | AI22: No dedicated 'creative direction' UI label found. The feature is implemented as a general text input that feeds into AI context. No distinct UX flow for creative direction vs. plain caption entry. Production build not verified. | AJ22: Source traced | AK22: EV-01-0018 | AO22: 8bc0dcb2a1da1b21368c5536aaeef829d587f316 | AP22: Low | AQ22: Not assessed | AR22: Not assessed | AS22: Fail | AT22: Not assessed | AU22: Not assessed | AV22: Not assessed | AW22: Not assessed | AX22: Not assessed | AY22: Not assessed | AZ22: Not assessed | BA22: Not assessed | BB22: Not assessed | BC22: Not assessed | BD22: Not assessed | BE22: Development required | BF22: Physical implementation is not complete against the stated requirement.; No dedicated 'creative direction' UI label found. The feature is implemented as a general text input that feeds into AI context. No distinct UX flow for creative direction vs. plain caption entry. Production build not verified. | BG22: Confirm dedicated creative-direction UI; test on device with Gemini API key. | BK22: Evidence reconciled against the reviewed source revision. No production approval is inferred from implementation or file presence. | BL22: 2026-08-02
A23: BLYP-01-022 | C23: BLYP Bar and AI-assisted posting | D23: 1 | E23: 22 | F23: Feature | G23: Context-aware caption generation | H23: Context-aware caption generation | I23: /home/ubuntu/blyp_product_requirements.md :: Section 1 — BLYP Bar and AI-assisted posting | J23: /home/ubuntu/BLYP_COMPLETE_FEATURE_LIST.md:37 | K23: Required | L23: Applicable BLYP member | M23: BLYP mobile application and supporting production services | N23: Context-aware caption generation | O23: Not explicitly defined in the product source; requires accountable product approval before production sign-off. | P23: Gemini API (generativelanguage.googleapis.com/v1beta/models/gemini-2.5-flash-preview-05-20); EXPO_PUBLIC_GEMINI_API_KEY | Q23: Yes | S23: Partial | T23: ReviewScreen.js; handleGenerateAIPost; generateComprehensiveAIContent | U23: ReviewScreen.js; AI Enhanced toggle; aiCaptionInput | V23: mediaDescriptionService.generateFullPostData/generateFullPostDataWithContext; aiCaption state; generatedContent state | W23: Not found (direct client-to-Gemini API) | X23: Not found | Y23: Not found | Z23: Gemini API (generativelanguage.googleapis.com/v1beta/models/gemini-2.5-flash-preview-05-20) | AA23: EXPO_PUBLIC_GEMINI_API_KEY | AB23: Expo mobile client | AC23: RP-002 | AD23: ReviewScreen calls mediaDescriptionService.generateFullPostDataWithContext with media URI and context prompt; Gemini returns description/caption. | AE23: User reachable | AF23: ReviewScreen.js; handleGenerateAIPost; generateComprehensiveAIContent; ReviewScreen calls mediaDescriptionService.generateFullPostDataWithContext with media URI and context prompt; Gemini returns description/caption. | AG23: Incomplete | AH23: No | AI23: Only one caption generated per call (not three distinct choices). Gemini API key must be present. Direct client-to-API call. Production build not verified. | AJ23: Source traced | AK23: EV-01-0019;EV-01-0032 | AO23: 8bc0dcb2a1da1b21368c5536aaeef829d587f316 | AP23: Medium | AQ23: Not assessed | AR23: Not assessed | AS23: Fail | AT23: Not assessed | AU23: Not assessed | AV23: Not assessed | AW23: Not assessed | AX23: Not assessed | AY23: Not assessed | AZ23: Not assessed | BA23: Not assessed | BB23: Not assessed | BC23: Not assessed | BD23: Not assessed | BE23: Development required | BF23: Physical implementation is not complete against the stated requirement.; Only one caption generated per call (not three distinct choices). Gemini API key must be present. Direct client-to-API call. Production build not verified. | BG23: Verify Gemini API key in production build; test caption generation on device. | BK23: Evidence reconciled against the reviewed source revision. No production approval is inferred from implementation or file presence. | BL23: 2026-08-02
A24: BLYP-01-023 | C24: BLYP Bar and AI-assisted posting | D24: 1 | E24: 23 | F24: Feature | G24: Three distinct caption choices per generation | H24: Three distinct caption choices per generation | I24: /home/ubuntu/blyp_product_requirements.md :: Section 1 — BLYP Bar and AI-assisted posting | J24: /home/ubuntu/BLYP_COMPLETE_FEATURE_LIST.md:38 | K24: Required | L24: Applicable BLYP member | M24: BLYP mobile application and supporting production services | N24: Three distinct caption choices per generation | O24: Not explicitly defined in the product source; requires accountable product approval before production sign-off. | Q24: Needs verification | R24: variant support exists, but the exact three-choice behaviour is disputed in the audit material. | S24: Not found | T24: Not found | U24: Not found | V24: Not found | W24: Not found | X24: Unknown | Y24: Not found | Z24: Not found | AA24: Not found | AB24: Unknown | AE24: Unknown | AG24: Not started | AH24: No | AI24: No three-distinct-caption-choices feature found. AI generates one description per call. Searched for 'three', 'choice', 'choices', 'distinct', 'option', 'options' in AI service files and ReviewScreen - no match. | AJ24: Not verified | AK24: EV-01-0020 | AO24: 8bc0dcb2a1da1b21368c5536aaeef829d587f316 | AP24: Low | AQ24: Not assessed | AR24: Not assessed | AS24: Fail | AT24: Not assessed | AU24: Not assessed | AV24: Not assessed | AW24: Not assessed | AX24: Not assessed | AY24: Not assessed | AZ24: Not assessed | BA24: Not assessed | BB24: Not assessed | BC24: Not assessed | BD24: Not assessed | BE24: Development required | BF24: Physical implementation is not complete against the stated requirement.; No three-distinct-caption-choices feature found. AI generates one description per call. Searched for 'three', 'choice', 'choices', 'distinct', 'option', 'options' in AI service files and ReviewScreen - no match. | BG24: Confirm whether requirement is to generate 3 choices per call; if so, implement and verify. | BK24: Evidence reconciled against the reviewed source revision. No production approval is inferred from implementation or file presence. | BL24: 2026-08-02
A25: BLYP-01-024 | C25: BLYP Bar and AI-assisted posting | D25: 1 | E25: 24 | F25: Feature | G25: Context-aware hashtag generation | H25: Context-aware hashtag generation | I25: /home/ubuntu/blyp_product_requirements.md :: Section 1 — BLYP Bar and AI-assisted posting | J25: /home/ubuntu/BLYP_COMPLETE_FEATURE_LIST.md:39 | K25: Required | L25: Applicable BLYP member | M25: BLYP mobile application and supporting production services | N25: Context-aware hashtag generation | O25: Not explicitly defined in the product source; requires accountable product approval before production sign-off. | P25: Gemini API; EXPO_PUBLIC_GEMINI_API_KEY | Q25: Yes | S25: Partial | T25: ReviewScreen.js; aiService.generateHashtags (line 2659); generatedHashtags state | U25: ReviewScreen.js; hashtag display section | V25: aiService.generateHashtags; generatedHashtags state; aiService.generateSmartContent | W25: Not found (direct client-to-Gemini API) | X25: Not found | Y25: Not found | Z25: Gemini API | AA25: EXPO_PUBLIC_GEMINI_API_KEY | AB25: Expo mobile client | AC25: RP-002 | AD25: ReviewScreen calls aiService.generateHashtags(caption, media) which calls generateSmartContent and returns hashtags array from Gemini API. | AE25: User reachable | AF25: ReviewScreen.js; aiService.generateHashtags (line 2659); generatedHashtags state; ReviewScreen calls aiService.generateHashtags(caption, media) which calls generateSmartContent and returns hashtags array from Gemini API. | AG25: Incomplete | AH25: No | AI25: Gemini API key must be present. Direct client-to-API call. Production build not verified. | AJ25: Source traced | AK25: EV-01-0021 | AO25: 8bc0dcb2a1da1b21368c5536aaeef829d587f316 | AP25: Medium | AQ25: Not assessed | AR25: Not assessed | AS25: Fail | AT25: Not assessed | AU25: Not assessed | AV25: Not assessed | AW25: Not assessed | AX25: Not assessed | AY25: Not assessed | AZ25: Not assessed | BA25: Not assessed | BB25: Not assessed | BC25: Not assessed | BD25: Not assessed | BE25: Development required | BF25: Physical implementation is not complete against the stated requirement.; Gemini API key must be present. Direct client-to-API call. Production build not verified. | BG25: Verify Gemini API key in production build; test hashtag generation on device. | BK25: Evidence reconciled against the reviewed source revision. No production approval is inferred from implementation or file presence. | BL25: 2026-08-02
A26: BLYP-01-025 | C26: BLYP Bar and AI-assisted posting | D26: 1 | E26: 25 | F26: Feature | G26: Select an AI suggestion | H26: Select an AI suggestion | I26: /home/ubuntu/blyp_product_requirements.md :: Section 1 — BLYP Bar and AI-assisted posting | J26: /home/ubuntu/BLYP_COMPLETE_FEATURE_LIST.md:40 | K26: Required | L26: Applicable BLYP member | M26: BLYP mobile application and supporting production services | N26: Select an AI suggestion | O26: Not explicitly defined in the product source; requires accountable product approval before production sign-off. | Q26: Yes | S26: Partial | T26: ReviewScreen.js; AI Enhanced toggle button (line 2506-2511) | U26: ReviewScreen.js; contentView toggle; aiCaptionInput | V26: contentView state; setCaption(aiCaption); aiSuggestions state | W26: Not found | X26: Not found | Y26: Not found | Z26: Not found | AA26: Not found | AB26: Expo mobile client | AC26: RP-002 | AD26: User taps 'AI Enhanced' toggle in ReviewScreen; contentView switches to 'ai'; caption is set to aiCaption. | AE26: User reachable | AF26: ReviewScreen.js; AI Enhanced toggle button (line 2506-2511); User taps 'AI Enhanced' toggle in ReviewScreen; contentView switches to 'ai'; caption is set to aiCaption. | AG26: Incomplete | AH26: No | AI26: Only one AI suggestion available (no multi-choice selection UI). Production build not verified. | AJ26: Source traced | AK26: EV-01-0022 | AO26: 8bc0dcb2a1da1b21368c5536aaeef829d587f316 | AP26: Medium | AQ26: Not assessed | AR26: Not assessed | AS26: Fail | AT26: Not assessed | AU26: Not assessed | AV26: Not assessed | AW26: Not assessed | AX26: Not assessed | AY26: Not assessed | AZ26: Not assessed | BA26: Not assessed | BB26: Not assessed | BC26: Not assessed | BD26: Not assessed | BE26: Development required | BF26: Physical implementation is not complete against the stated requirement.; Only one AI suggestion available (no multi-choice selection UI). Production build not verified. | BG26: Test AI suggestion selection on device; confirm multi-choice UX if required. | BK26: Evidence reconciled against the reviewed source revision. No production approval is inferred from implementation or file presence. | BL26: 2026-08-02
A27: BLYP-01-026 | C27: BLYP Bar and AI-assisted posting | D27: 1 | E27: 26 | F27: Feature | G27: Edit an AI suggestion | H27: Edit an AI suggestion | I27: /home/ubuntu/blyp_product_requirements.md :: Section 1 — BLYP Bar and AI-assisted posting | J27: /home/ubuntu/BLYP_COMPLETE_FEATURE_LIST.md:41 | K27: Required | L27: Applicable BLYP member | M27: BLYP mobile application and supporting production services | N27: Edit an AI suggestion | O27: Not explicitly defined in the product source; requires accountable product approval before production sign-off. | Q27: Yes | S27: End-to-end present | T27: ReviewScreen.js; aiCaptionInput TextInput (line 2581-2593) | U27: ReviewScreen.js; aiCaptionInput | V27: caption state; aiCaption state; setCaption; setAiCaption | W27: Not found | X27: Not found | Y27: Not found | Z27: Not found | AA27: Not found | AB27: Expo mobile client | AC27: RP-002 | AD27: User edits AI-generated caption in aiCaptionInput TextInput; onChangeText updates both caption and aiCaption state. | AE27: User reachable | AF27: ReviewScreen.js; aiCaptionInput TextInput (line 2581-2593); User edits AI-generated caption in aiCaptionInput TextInput; onChangeText updates both caption and aiCaption state. | AG27: Complete against stated requirement | AH27: Yes | AI27: Production build not verified. | AJ27: Source traced | AK27: EV-01-0023 | AO27: 8bc0dcb2a1da1b21368c5536aaeef829d587f316 | AP27: Medium | AQ27: Not assessed | AR27: Not assessed | AS27: Not assessed | AT27: Not assessed | AU27: Not assessed | AV27: Not assessed | AW27: Not assessed | AX27: Not assessed | AY27: Not assessed | AZ27: Not assessed | BA27: Not assessed | BB27: Not assessed | BC27: Not assessed | BD27: Not assessed | BE27: Ready for production validation | BF27: Applicable production gates and acceptance checks have not been completed on an approved release candidate. | BG27: Test AI suggestion editing on device. | BK27: Evidence reconciled against the reviewed source revision. No production approval is inferred from implementation or file presence. | BL27: 2026-08-02
A28: BLYP-01-027 | C28: BLYP Bar and AI-assisted posting | D28: 1 | E28: 27 | F28: Feature | G28: Combine manual, voice, and AI wording | H28: Combine manual, voice, and AI wording | I28: /home/ubuntu/blyp_product_requirements.md :: Section 1 — BLYP Bar and AI-assisted posting | J28: /home/ubuntu/BLYP_COMPLETE_FEATURE_LIST.md:42 | K28: Required | L28: Applicable BLYP member | M28: BLYP mobile application and supporting production services | N28: Combine manual, voice, and AI wording | O28: Not explicitly defined in the product source; requires accountable product approval before production sign-off. | P28: Gemini API; EXPO_PUBLIC_GEMINI_API_KEY | Q28: Yes | S28: Partial | T28: ReviewScreen.js; manualDescription + accumulatedVoiceInputs + allContextualData | U28: ReviewScreen.js; manualDescription TextInput; voice input | V28: manualDescription state; accumulatedVoiceInputs state; allContextualData state; generateComprehensiveAIContent | W28: Not found | X28: Not found | Y28: Not found | Z28: Gemini API | AA28: EXPO_PUBLIC_GEMINI_API_KEY | AB28: Expo mobile client | AC28: RP-002 | AD28: ReviewScreen accumulates manual text and voice inputs in allContextualData; generateComprehensiveAIContent combines both in the AI prompt. | AE28: User reachable | AF28: ReviewScreen.js; manualDescription + accumulatedVoiceInputs + allContextualData; ReviewScreen accumulates manual text and voice inputs in allContextualData; generateComprehensiveAIContent combines both in the AI prompt. | AG28: Incomplete | AH28: No | AI28: No dedicated 'combine' UI action found. The combination happens implicitly in the AI prompt. Production build not verified. | AJ28: Source traced | AK28: EV-01-0024 | AO28: 8bc0dcb2a1da1b21368c5536aaeef829d587f316 | AP28: Low | AQ28: Not assessed | AR28: Not assessed | AS28: Fail | AT28: Not assessed | AU28: Not assessed | AV28: Not assessed | AW28: Not assessed | AX28: Not assessed | AY28: Not assessed | AZ28: Not assessed | BA28: Not assessed | BB28: Not assessed | BC28: Not assessed | BD28: Not assessed | BE28: Development required | BF28: Physical implementation is not complete against the stated requirement.; No dedicated 'combine' UI action found. The combination happens implicitly in the AI prompt. Production build not verified. | BG28: Test combined manual+AI caption flow on device; confirm dedicated UX for combining. | BK28: Evidence reconciled against the reviewed source revision. No production approval is inferred from implementation or file presence. | BL28: 2026-08-02
A29: BLYP-01-028 | C29: BLYP Bar and AI-assisted posting | D29: 1 | E29: 28 | F29: Feature | G29: Replace or regenerate a suggestion | H29: Replace or regenerate a suggestion | I29: /home/ubuntu/blyp_product_requirements.md :: Section 1 — BLYP Bar and AI-assisted posting | J29: /home/ubuntu/BLYP_COMPLETE_FEATURE_LIST.md:43 | K29: Required | L29: Applicable BLYP member | M29: BLYP mobile application and supporting production services | N29: Replace or regenerate a suggestion | O29: Not explicitly defined in the product source; requires accountable product approval before production sign-off. | P29: Gemini API; EXPO_PUBLIC_GEMINI_API_KEY | Q29: Partial | S29: Partial | T29: ReviewScreen.js; handleGenerateAIPost (line 1425); generateComprehensiveAIContent (line 2003) | U29: ReviewScreen.js; Generate AI Post button (line 3049); generateAIButton | V29: generatedContent state; aiCaption state; isGeneratingContent state | W29: Not found | X29: Not found | Y29: Not found | Z29: Gemini API | AA29: EXPO_PUBLIC_GEMINI_API_KEY | AB29: Expo mobile client | AC29: RP-002 | AD29: User taps 'Generate AI Post' button; handleGenerateAIPost calls mediaDescriptionService.generateFullPostDataWithContext; new content overwrites aiCaption. | AE29: User reachable | AF29: ReviewScreen.js; handleGenerateAIPost (line 1425); generateComprehensiveAIContent (line 2003); User taps 'Generate AI Post' button; handleGenerateAIPost calls mediaDescriptionService.generateFullPostDataWithContext; new content overwrites aiCaption. | AG29: Incomplete | AH29: No | AI29: No dedicated 'regenerate' button label found. Regeneration happens by re-triggering AI generation. Production build not verified. | AJ29: Source traced | AK29: EV-01-0025 | AO29: 8bc0dcb2a1da1b21368c5536aaeef829d587f316 | AP29: Medium | AQ29: Not assessed | AR29: Not assessed | AS29: Fail | AT29: Not assessed | AU29: Not assessed | AV29: Not assessed | AW29: Not assessed | AX29: Not assessed | AY29: Not assessed | AZ29: Not assessed | BA29: Not assessed | BB29: Not assessed | BC29: Not assessed | BD29: Not assessed | BE29: Development required | BF29: Physical implementation is not complete against the stated requirement.; No dedicated 'regenerate' button label found. Regeneration happens by re-triggering AI generation. Production build not verified. | BG29: Test regeneration on device; confirm dedicated regenerate UX if required. | BK29: Evidence reconciled against the reviewed source revision. No production approval is inferred from implementation or file presence. | BL29: 2026-08-02
A30: BLYP-01-029 | C30: BLYP Bar and AI-assisted posting | D30: 1 | E30: 29 | F30: Feature | G30: Ignore AI and post manually | H30: Ignore AI and post manually | I30: /home/ubuntu/blyp_product_requirements.md :: Section 1 — BLYP Bar and AI-assisted posting | J30: /home/ubuntu/BLYP_COMPLETE_FEATURE_LIST.md:44 | K30: Required | L30: Applicable BLYP member | M30: BLYP mobile application and supporting production services | N30: Ignore AI and post manually | O30: Not explicitly defined in the product source; requires accountable product approval before production sign-off. | P30: Firebase (Firestore, Storage); Firestore posts collection; Firebase Storage (media); Firebase config | Q30: Yes | S30: End-to-end present | T30: ReviewScreen.js; handlePostPress (line 1737); handlePost (line 1836) | U30: ReviewScreen.js; Post button (line 2699-2708); Original toggle (line 2514-2522) | V30: caption state; contentView state; isUploading state | W30: Not found (Firestore write) | X30: Firestore posts collection; Firebase Storage (media) | Y30: Not found | Z30: Firebase (Firestore, Storage) | AA30: Firebase config | AB30: Expo mobile client | AC30: RP-002 | AD30: User can post with original caption without using AI by staying in 'original' contentView and tapping Post button. | AE30: User reachable | AF30: ReviewScreen.js; handlePostPress (line 1737); handlePost (line 1836); User can post with original caption without using AI by staying in 'original' contentView and tapping Post button. | AG30: Complete against stated requirement | AH30: Yes | AI30: Production build and Firestore write not verified on device. | AJ30: Source traced | AK30: EV-01-0026;EV-01-0033 | AO30: 8bc0dcb2a1da1b21368c5536aaeef829d587f316 | AP30: Medium | AQ30: Not assessed | AR30: Not assessed | AS30: Not assessed | AT30: Not assessed | AU30: Not assessed | AV30: Not assessed | AW30: Not assessed | AX30: Not assessed | AY30: Not assessed | AZ30: Not assessed | BA30: Not assessed | BB30: Not assessed | BC30: Not assessed | BD30: Not assessed | BE30: Ready for production validation | BF30: Applicable production gates and acceptance checks have not been completed on an approved release candidate. | BG30: Test manual post creation on device; verify Firestore write. | BK30: Evidence reconciled against the reviewed source revision. No production approval is inferred from implementation or file presence. | BL30: 2026-08-02
A31: BLYP-01-030 | C31: BLYP Bar and AI-assisted posting | D31: 1 | E31: 30 | F31: Feature | G31: Server-held AI provider secret and authenticated proxy | H31: Server-held AI provider secret and authenticated proxy | I31: /home/ubuntu/blyp_product_requirements.md :: Section 1 — BLYP Bar and AI-assisted posting | J31: /home/ubuntu/BLYP_COMPLETE_FEATURE_LIST.md:45 | K31: Required | L31: Applicable BLYP member | M31: BLYP mobile application and supporting production services | N31: Server-held AI provider secret and authenticated proxy | O31: Not explicitly defined in the product source; requires accountable product approval before production sign-off. | P31: Gemini API (direct client call); EXPO_PUBLIC_GEMINI_API_KEY (app.config.js:8-19; firebase.js:318-341) | Q31: Yes | S31: Conflicting implementations | T31: src/config/firebase.js (geminiApiKey export); src/services/aiService.js; src/services/geminiSpeechService.js; src/services/mediaDescriptionService.js | U31: Not found (no proxy UI) | V31: geminiApiKey; geminiApiUrl; AIService.apiKey; AIService.apiUrl | W31: Not found (no server-side AI proxy route) | X31: Not found | Y31: Not found | Z31: Gemini API (direct client call) | AA31: EXPO_PUBLIC_GEMINI_API_KEY (app.config.js:8-19; firebase.js:318-341) | AB31: Expo mobile client | AC31: RP-002 | AD31: Gemini API key is injected as EXPO_PUBLIC_GEMINI_API_KEY env var into the Expo bundle. All AI services call Gemini API directly from the client. No server-side proxy or authenticated backend route for AI calls exists. | AE31: User reachable | AF31: src/config/firebase.js (geminiApiKey export); src/services/aiService.js; src/services/geminiSpeechService.js; src/services/mediaDescriptionService.js; Gemini API key is injected as EXPO_PUBLIC_GEMINI_API_KEY env var into the Expo bundle. All AI services call Gemini API directly from the client. No server-side proxy or authenticated backend route for AI calls exists. | AG31: Incomplete | AH31: No | AI31: Requirement specifies server-held secret and authenticated proxy. Implementation uses client-side env var key with direct API calls. This is a security gap: the key is embedded in the client bundle. No server-side proxy route found in backend/blyp-live-service. | AJ31: Source traced | AK31: EV-01-0027;EV-01-0030;EV-01-0031;EV-01-0032;EV-01-0038 | AO31: 8bc0dcb2a1da1b21368c5536aaeef829d587f316 | AP31: High | AQ31: Not assessed | AR31: Fail | AS31: Fail | AT31: Not assessed | AU31: Not assessed | AV31: Not assessed | AW31: Not assessed | AX31: Not assessed | AY31: Not assessed | AZ31: Not assessed | BA31: Not assessed | BB31: Not assessed | BC31: Not assessed | BD31: Not assessed | BE31: Development required | BF31: Gemini API key is client-side (EXPO_PUBLIC_GEMINI_API_KEY in Expo bundle), not server-held. No authenticated server proxy route found. This contradicts the stated security requirement.; Physical implementation is not complete against the stated requirement.; Requirement specifies server-held secret and authenticated proxy. Implementation uses client-side env var key with direct API calls. This is a security gap: the key is embedded in the client bundle. No server-side proxy route found in backend/blyp-live-service. | BG31: Implement server-side AI proxy route; move Gemini key to server environment; verify server-side authentication of AI requests. | BK31: Evidence reconciled against the reviewed source revision. No production approval is inferred from implementation or file presence. | BL31: 2026-08-02
A32: BLYP-01-031 | C32: BLYP Bar and AI-assisted posting | D32: 1 | E32: 31 | F32: Feature | G32: Consistent AI entitlement enforcement | H32: Consistent AI entitlement enforcement | I32: /home/ubuntu/blyp_product_requirements.md :: Section 1 — BLYP Bar and AI-assisted posting | J32: /home/ubuntu/BLYP_COMPLETE_FEATURE_LIST.md:46 | K32: Required | L32: Applicable BLYP member | M32: BLYP mobile application and supporting production services | N32: Consistent AI entitlement enforcement | O32: Not explicitly defined in the product source; requires accountable product approval before production sign-off. | Q32: Partial | S32: Not found | T32: Not found | U32: Not found | V32: Not found | W32: Not found | X32: Unknown | Y32: Not found | Z32: Not found | AA32: Not found | AB32: Unknown | AE32: Unknown | AG32: Not started | AH32: No | AI32: No AI entitlement enforcement found. Searched for 'entitlement', 'plus', 'premium', 'subscription', 'gated' across all source files - zero results. AI features are available to all users without any entitlement check. | AJ32: Not verified | AK32: EV-01-0008;EV-01-0028;EV-01-0038 | AO32: 8bc0dcb2a1da1b21368c5536aaeef829d587f316 | AP32: Medium | AQ32: Not assessed | AR32: Not assessed | AS32: Fail | AT32: Not assessed | AU32: Not assessed | AV32: Not assessed | AW32: Not assessed | AX32: Not assessed | AY32: Not assessed | AZ32: Not assessed | BA32: Not assessed | BB32: Not assessed | BC32: Not assessed | BD32: Not assessed | BE32: Development required | BF32: Physical implementation is not complete against the stated requirement.; No AI entitlement enforcement found. Searched for 'entitlement', 'plus', 'premium', 'subscription', 'gated' across all source files - zero results. AI features are available to all users without any entitlement check. | BG32: Implement entitlement enforcement; verify server-side entitlement check for AI features. | BK32: Evidence reconciled against the reviewed source revision. No production approval is inferred from implementation or file presence. | BL32: 2026-08-02
A33: BLYP-01-032 | C33: BLYP Bar and AI-assisted posting | D33: 1 | E33: 32 | F33: Feature | G33: Metered free and paid AI allowances | H33: Metered free and paid AI allowances | I33: /home/ubuntu/blyp_product_requirements.md :: Section 1 — BLYP Bar and AI-assisted posting | J33: /home/ubuntu/BLYP_COMPLETE_FEATURE_LIST.md:47 | K33: Required | L33: Applicable BLYP member | M33: BLYP mobile application and supporting production services | N33: Metered free and paid AI allowances | O33: Not explicitly defined in the product source; requires accountable product approval before production sign-off. | Q33: No evidence | S33: Not found | T33: Not found | U33: Not found | V33: Not found | W33: Not found | X33: Unknown | Y33: Not found | Z33: Not found | AA33: Not found | AB33: Unknown | AE33: Unknown | AG33: Not started | AH33: No | AI33: No AI usage metering, free-tier quota, or paid-tier allowance found. Searched for 'allowance', 'meter', 'quota', 'free', 'paid', 'limit' in AI context - zero results. AI features are unmetered. | AJ33: Not verified | AK33: EV-01-0029;EV-01-0038 | AO33: 8bc0dcb2a1da1b21368c5536aaeef829d587f316 | AP33: Medium | AQ33: Not assessed | AR33: Not assessed | AS33: Fail | AT33: Not assessed | AU33: Not assessed | AV33: Not assessed | AW33: Not assessed | AX33: Not assessed | AY33: Not assessed | AZ33: Not assessed | BA33: Not assessed | BB33: Not assessed | BC33: Not assessed | BD33: Not assessed | BE33: Development required | BF33: Physical implementation is not complete against the stated requirement.; No AI usage metering, free-tier quota, or paid-tier allowance found. Searched for 'allowance', 'meter', 'quota', 'free', 'paid', 'limit' in AI context - zero results. AI features are unmetered. | BG33: Implement metered AI allowances; verify server-side usage tracking. | BK33: Evidence reconciled against the reviewed source revision. No production approval is inferred from implementation or file presence. | BL33: 2026-08-02
A34: BLYP-02-001 | C34: Team applications | D34: 2 | E34: 1 | F34: Feature | G34: Teams section and Team-related screens | H34: Teams section and Team-related screens | I34: /home/ubuntu/blyp_product_requirements.md :: Section 2 — Team applications | J34: /home/ubuntu/BLYP_COMPLETE_FEATURE_LIST.md:53 | K34: Required | L34: Applicable BLYP member | M34: BLYP mobile application and supporting production services | N34: Teams section and Team-related screens | O34: Not explicitly defined in the product source; requires accountable product approval before production sign-off. | Q34: Scaffold only | S34: Not found | T34: Not found | U34: Not found | V34: Not found | W34: Not found | X34: Not found | Y34: Not found | Z34: Not found | AA34: Not found | AB34: Not found | AD34: Not found | AE34: Unknown | AG34: Unknown | AH34: Unknown | AI34: Searched for 'Team', 'application', 'apply' in source code, no relevant implementation found. | AJ34: Not verified | AO34: 8bc0dcb2a1da1b21368c5536aaeef829d587f316 | AP34: Low | AQ34: Not assessed | AR34: Not assessed | AS34: Not assessed | AT34: Not assessed | AU34: Not assessed | AV34: Not assessed | AW34: Not assessed | AX34: Not assessed | AY34: Not assessed | AZ34: Not assessed | BA34: Not assessed | BB34: Not assessed | BC34: Not assessed | BD34: Not assessed | BE34: Development required | BF34: Not assessed; Physical implementation is not complete against the stated requirement.; Searched for 'Team', 'application', 'apply' in source code, no relevant implementation found. | BG34: Not assessed | BK34: Evidence reconciled against the reviewed source revision. No production approval is inferred from implementation or file presence. | BL34: 2026-08-02
A35: BLYP-02-002 | C35: Team applications | D35: 2 | E35: 2 | F35: Feature | G35: View another Team | H35: View another Team | I35: /home/ubuntu/blyp_product_requirements.md :: Section 2 — Team applications | J35: /home/ubuntu/BLYP_COMPLETE_FEATURE_LIST.md:54 | K35: Required | L35: Applicable BLYP member | M35: BLYP mobile application and supporting production services | N35: View another Team | O35: Not explicitly defined in the product source; requires accountable product approval before production sign-off. | Q35: Partial | S35: Not found | T35: Not found | U35: Not found | V35: Not found | W35: Not found | X35: Not found | Y35: Not found | Z35: Not found | AA35: Not found | AB35: Not found | AD35: Not found | AE35: Unknown | AG35: Unknown | AH35: Unknown | AI35: Searched for 'Team', 'application', 'apply' in source code, no relevant implementation found. | AJ35: Not verified | AO35: 8bc0dcb2a1da1b21368c5536aaeef829d587f316 | AP35: Low | AQ35: Not assessed | AR35: Not assessed | AS35: Not assessed | AT35: Not assessed | AU35: Not assessed | AV35: Not assessed | AW35: Not assessed | AX35: Not assessed | AY35: Not assessed | AZ35: Not assessed | BA35: Not assessed | BB35: Not assessed | BC35: Not assessed | BD35: Not assessed | BE35: Development required | BF35: Not assessed; Physical implementation is not complete against the stated requirement.; Searched for 'Team', 'application', 'apply' in source code, no relevant implementation found. | BG35: Not assessed | BK35: Evidence reconciled against the reviewed source revision. No production approval is inferred from implementation or file presence. | BL35: 2026-08-02
A36: BLYP-02-003 | C36: Team applications | D36: 2 | E36: 3 | F36: Feature | G36: Send Application action | H36: Send Application action | I36: /home/ubuntu/blyp_product_requirements.md :: Section 2 — Team applications | J36: /home/ubuntu/BLYP_COMPLETE_FEATURE_LIST.md:55 | K36: Required | L36: Applicable BLYP member | M36: BLYP mobile application and supporting production services | N36: Send Application action | O36: Not explicitly defined in the product source; requires accountable product approval before production sign-off. | Q36: Partial | R36: the flow exists but has produced a “Missing user” failure. | S36: Not found | T36: Not found | U36: Not found | V36: Not found | W36: Not found | X36: Not found | Y36: Not found | Z36: Not found | AA36: Not found | AB36: Not found | AD36: Not found | AE36: Unknown | AG36: Unknown | AH36: Unknown | AI36: Searched for 'Team', 'application', 'apply' in source code, no relevant implementation found. | AJ36: Not verified | AO36: 8bc0dcb2a1da1b21368c5536aaeef829d587f316 | AP36: Low | AQ36: Not assessed | AR36: Not assessed | AS36: Not assessed | AT36: Not assessed | AU36: Not assessed | AV36: Not assessed | AW36: Not assessed | AX36: Not assessed | AY36: Not assessed | AZ36: Not assessed | BA36: Not assessed | BB36: Not assessed | BC36: Not assessed | BD36: Not assessed | BE36: Development required | BF36: Not assessed; Physical implementation is not complete against the stated requirement.; Searched for 'Team', 'application', 'apply' in source code, no relevant implementation found. | BG36: Not assessed | BK36: Evidence reconciled against the reviewed source revision. No production approval is inferred from implementation or file presence. | BL36: 2026-08-02
A37: BLYP-02-004 | C37: Team applications | D37: 2 | E37: 4 | F37: Feature | G37: Associate an application with the authenticated member | H37: Associate an application with the authenticated member | I37: /home/ubuntu/blyp_product_requirements.md :: Section 2 — Team applications | J37: /home/ubuntu/BLYP_COMPLETE_FEATURE_LIST.md:56 | K37: Required | L37: Applicable BLYP member | M37: BLYP mobile application and supporting production services | N37: Associate an application with the authenticated member | O37: Not explicitly defined in the product source; requires accountable product approval before production sign-off. | Q37: No evidence | S37: Not found | T37: Not found | U37: Not found | V37: Not found | W37: Not found | X37: Not found | Y37: Not found | Z37: Not found | AA37: Not found | AB37: Not found | AD37: Not found | AE37: Unknown | AG37: Unknown | AH37: Unknown | AI37: Searched for 'Team', 'application', 'apply' in source code, no relevant implementation found. | AJ37: Not verified | AO37: 8bc0dcb2a1da1b21368c5536aaeef829d587f316 | AP37: Low | AQ37: Not assessed | AR37: Not assessed | AS37: Not assessed | AT37: Not assessed | AU37: Not assessed | AV37: Not assessed | AW37: Not assessed | AX37: Not assessed | AY37: Not assessed | AZ37: Not assessed | BA37: Not assessed | BB37: Not assessed | BC37: Not assessed | BD37: Not assessed | BE37: Development required | BF37: Not assessed; Physical implementation is not complete against the stated requirement.; Searched for 'Team', 'application', 'apply' in source code, no relevant implementation found. | BG37: Not assessed | BK37: Evidence reconciled against the reviewed source revision. No production approval is inferred from implementation or file presence. | BL37: 2026-08-02
A38: BLYP-02-005 | C38: Team applications | D38: 2 | E38: 5 | F38: Feature | G38: Send the application to the selected Team | H38: Send the application to the selected Team | I38: /home/ubuntu/blyp_product_requirements.md :: Section 2 — Team applications | J38: /home/ubuntu/BLYP_COMPLETE_FEATURE_LIST.md:57 | K38: Required | L38: Applicable BLYP member | M38: BLYP mobile application and supporting production services | N38: Send the application to the selected Team | O38: Not explicitly defined in the product source; requires accountable product approval before production sign-off. | Q38: Partial | S38: Not found | T38: Not found | U38: Not found | V38: Not found | W38: Not found | X38: Not found | Y38: Not found | Z38: Not found | AA38: Not found | AB38: Not found | AD38: Not found | AE38: Unknown | AG38: Unknown | AH38: Unknown | AI38: Searched for 'Team', 'application', 'apply' in source code, no relevant implementation found. | AJ38: Not verified | AO38: 8bc0dcb2a1da1b21368c5536aaeef829d587f316 | AP38: Low | AQ38: Not assessed | AR38: Not assessed | AS38: Not assessed | AT38: Not assessed | AU38: Not assessed | AV38: Not assessed | AW38: Not assessed | AX38: Not assessed | AY38: Not assessed | AZ38: Not assessed | BA38: Not assessed | BB38: Not assessed | BC38: Not assessed | BD38: Not assessed | BE38: Development required | BF38: Not assessed; Physical implementation is not complete against the stated requirement.; Searched for 'Team', 'application', 'apply' in source code, no relevant implementation found. | BG38: Not assessed | BK38: Evidence reconciled against the reviewed source revision. No production approval is inferred from implementation or file presence. | BL38: 2026-08-02
A39: BLYP-02-006 | C39: Team applications | D39: 2 | E39: 6 | F39: Rule | G39: Prevent duplicate Team applications | H39: Prevent duplicate Team applications | I39: /home/ubuntu/blyp_product_requirements.md :: Section 2 — Team applications | J39: /home/ubuntu/BLYP_COMPLETE_FEATURE_LIST.md:58 | K39: Required | L39: Applicable BLYP member | M39: BLYP mobile application and supporting production services | N39: Prevent duplicate Team applications | O39: Not explicitly defined in the product source; requires accountable product approval before production sign-off. | Q39: No evidence | S39: Not found | T39: Not found | U39: Not found | V39: Not found | W39: Not found | X39: Not found | Y39: Not found | Z39: Not found | AA39: Not found | AB39: Not found | AD39: Not found | AE39: Unknown | AG39: Unknown | AH39: Unknown | AI39: Searched for 'Team', 'application', 'apply' in source code, no relevant implementation found. | AJ39: Not verified | AO39: 8bc0dcb2a1da1b21368c5536aaeef829d587f316 | AP39: Low | AQ39: Not assessed | AR39: Not assessed | AS39: Not assessed | AT39: Not assessed | AU39: Not assessed | AV39: Not assessed | AW39: Not assessed | AX39: Not assessed | AY39: Not assessed | AZ39: Not assessed | BA39: Not assessed | BB39: Not assessed | BC39: Not assessed | BD39: Not assessed | BE39: Development required | BF39: Not assessed; Physical implementation is not complete against the stated requirement.; Searched for 'Team', 'application', 'apply' in source code, no relevant implementation found. | BG39: Not assessed | BK39: Evidence reconciled against the reviewed source revision. No production approval is inferred from implementation or file presence. | BL39: 2026-08-02
A40: BLYP-02-007 | C40: Team applications | D40: 2 | E40: 7 | F40: Feature | G40: Clear application success state | H40: Clear application success state | I40: /home/ubuntu/blyp_product_requirements.md :: Section 2 — Team applications | J40: /home/ubuntu/BLYP_COMPLETE_FEATURE_LIST.md:59 | K40: Required | L40: Applicable BLYP member | M40: BLYP mobile application and supporting production services | N40: Clear application success state | O40: Not explicitly defined in the product source; requires accountable product approval before production sign-off. | Q40: No evidence | S40: Not found | T40: Not found | U40: Not found | V40: Not found | W40: Not found | X40: Not found | Y40: Not found | Z40: Not found | AA40: Not found | AB40: Not found | AD40: Not found | AE40: Unknown | AG40: Unknown | AH40: Unknown | AI40: Searched for 'Team', 'application', 'apply' in source code, no relevant implementation found. | AJ40: Not verified | AO40: 8bc0dcb2a1da1b21368c5536aaeef829d587f316 | AP40: Low | AQ40: Not assessed | AR40: Not assessed | AS40: Not assessed | AT40: Not assessed | AU40: Not assessed | AV40: Not assessed | AW40: Not assessed | AX40: Not assessed | AY40: Not assessed | AZ40: Not assessed | BA40: Not assessed | BB40: Not assessed | BC40: Not assessed | BD40: Not assessed | BE40: Development required | BF40: Not assessed; Physical implementation is not complete against the stated requirement.; Searched for 'Team', 'application', 'apply' in source code, no relevant implementation found. | BG40: Not assessed | BK40: Evidence reconciled against the reviewed source revision. No production approval is inferred from implementation or file presence. | BL40: 2026-08-02
A41: BLYP-02-008 | C41: Team applications | D41: 2 | E41: 8 | F41: Feature | G41: Actionable application error messages | H41: Actionable application error messages | I41: /home/ubuntu/blyp_product_requirements.md :: Section 2 — Team applications | J41: /home/ubuntu/BLYP_COMPLETE_FEATURE_LIST.md:60 | K41: Required | L41: Applicable BLYP member | M41: BLYP mobile application and supporting production services | N41: Actionable application error messages | O41: Not explicitly defined in the product source; requires accountable product approval before production sign-off. | Q41: Partial | S41: Not found | T41: Not found | U41: Not found | V41: Not found | W41: Not found | X41: Not found | Y41: Not found | Z41: Not found | AA41: Not found | AB41: Not found | AD41: Not found | AE41: Unknown | AG41: Unknown | AH41: Unknown | AI41: Searched for 'Team', 'application', 'apply' in source code, no relevant implementation found. | AJ41: Not verified | AO41: 8bc0dcb2a1da1b21368c5536aaeef829d587f316 | AP41: Low | AQ41: Not assessed | AR41: Not assessed | AS41: Not assessed | AT41: Not assessed | AU41: Not assessed | AV41: Not assessed | AW41: Not assessed | AX41: Not assessed | AY41: Not assessed | AZ41: Not assessed | BA41: Not assessed | BB41: Not assessed | BC41: Not assessed | BD41: Not assessed | BE41: Development required | BF41: Not assessed; Physical implementation is not complete against the stated requirement.; Searched for 'Team', 'application', 'apply' in source code, no relevant implementation found. | BG41: Not assessed | BK41: Evidence reconciled against the reviewed source revision. No production approval is inferred from implementation or file presence. | BL41: 2026-08-02
A42: BLYP-02-009 | C42: Team applications | D42: 2 | E42: 9 | F42: Feature | G42: Team-application decision state | H42: Team-application decision state | I42: /home/ubuntu/blyp_product_requirements.md :: Section 2 — Team applications | J42: /home/ubuntu/BLYP_COMPLETE_FEATURE_LIST.md:61 | K42: Required | L42: Applicable BLYP member | M42: BLYP mobile application and supporting production services | N42: Team-application decision state | O42: Not explicitly defined in the product source; requires accountable product approval before production sign-off. | Q42: Scaffold only | S42: Not found | T42: Not found | U42: Not found | V42: Not found | W42: Not found | X42: Not found | Y42: Not found | Z42: Not found | AA42: Not found | AB42: Not found | AD42: Not found | AE42: Unknown | AG42: Unknown | AH42: Unknown | AI42: Searched for 'Team', 'application', 'apply' in source code, no relevant implementation found. | AJ42: Not verified | AO42: 8bc0dcb2a1da1b21368c5536aaeef829d587f316 | AP42: Low | AQ42: Not assessed | AR42: Not assessed | AS42: Not assessed | AT42: Not assessed | AU42: Not assessed | AV42: Not assessed | AW42: Not assessed | AX42: Not assessed | AY42: Not assessed | AZ42: Not assessed | BA42: Not assessed | BB42: Not assessed | BC42: Not assessed | BD42: Not assessed | BE42: Development required | BF42: Not assessed; Physical implementation is not complete against the stated requirement.; Searched for 'Team', 'application', 'apply' in source code, no relevant implementation found. | BG42: Not assessed | BK42: Evidence reconciled against the reviewed source revision. No production approval is inferred from implementation or file presence. | BL42: 2026-08-02
A43: BLYP-03-001 | C43: Interest hubs | D43: 3 | E43: 1 | F43: Feature | G43: Broad Interest catalogue | H43: Broad Interest catalogue | I43: /home/ubuntu/blyp_product_requirements.md :: Section 3 — Interest hubs | J43: /home/ubuntu/BLYP_COMPLETE_FEATURE_LIST.md:67 | K43: Required | L43: Applicable BLYP member | M43: BLYP mobile application and supporting production services | N43: Broad Interest catalogue | O43: Not explicitly defined in the product source; requires accountable product approval before production sign-off. | Q43: Partial | S43: Not found | AE43: Unknown | AG43: Unknown | AH43: Unknown | AI43: Searched for hub, interest, category, hashtag, football, formula 1, fixtures, empty state, invite, bot, fake. No concrete implementation found. | AJ43: Not verified | AO43: 8bc0dcb2a1da1b21368c5536aaeef829d587f316 | AP43: Low | AQ43: Not assessed | AR43: Not assessed | AS43: Not assessed | AT43: Not assessed | AU43: Not assessed | AV43: Not assessed | AW43: Not assessed | AX43: Not assessed | AY43: Not assessed | AZ43: Not assessed | BA43: Not assessed | BB43: Not assessed | BC43: Not assessed | BD43: Not assessed | BE43: Development required | BF43: Physical implementation is not complete against the stated requirement.; Searched for hub, interest, category, hashtag, football, formula 1, fixtures, empty state, invite, bot, fake. No concrete implementation found. | BK43: Evidence reconciled against the reviewed source revision. No production approval is inferred from implementation or file presence. | BL43: 2026-08-02
A44: BLYP-03-002 | C44: Interest hubs | D44: 3 | E44: 2 | F44: Feature | G44: Categories/Interest browsing surface | H44: Categories/Interest browsing surface | I44: /home/ubuntu/blyp_product_requirements.md :: Section 3 — Interest hubs | J44: /home/ubuntu/BLYP_COMPLETE_FEATURE_LIST.md:68 | K44: Required | L44: Applicable BLYP member | M44: BLYP mobile application and supporting production services | N44: Categories/Interest browsing surface | O44: Not explicitly defined in the product source; requires accountable product approval before production sign-off. | Q44: Yes | S44: Not found | AE44: Unknown | AG44: Unknown | AH44: Unknown | AI44: Searched for hub, interest, category, hashtag, football, formula 1, fixtures, empty state, invite, bot, fake. No concrete implementation found. | AJ44: Not verified | AO44: 8bc0dcb2a1da1b21368c5536aaeef829d587f316 | AP44: Low | AQ44: Not assessed | AR44: Not assessed | AS44: Not assessed | AT44: Not assessed | AU44: Not assessed | AV44: Not assessed | AW44: Not assessed | AX44: Not assessed | AY44: Not assessed | AZ44: Not assessed | BA44: Not assessed | BB44: Not assessed | BC44: Not assessed | BD44: Not assessed | BE44: Development required | BF44: Physical implementation is not complete against the stated requirement.; Searched for hub, interest, category, hashtag, football, formula 1, fixtures, empty state, invite, bot, fake. No concrete implementation found. | BK44: Evidence reconciled against the reviewed source revision. No production approval is inferred from implementation or file presence. | BL44: 2026-08-02
A45: BLYP-03-003 | C45: Interest hubs | D45: 3 | E45: 3 | F45: Feature | G45: Hashtag/topic browsing | H45: Hashtag/topic browsing | I45: /home/ubuntu/blyp_product_requirements.md :: Section 3 — Interest hubs | J45: /home/ubuntu/BLYP_COMPLETE_FEATURE_LIST.md:69 | K45: Required | L45: Applicable BLYP member | M45: BLYP mobile application and supporting production services | N45: Hashtag/topic browsing | O45: Not explicitly defined in the product source; requires accountable product approval before production sign-off. | Q45: Yes | S45: Unknown | AE45: Unknown | AF45: No exact feature-level physical path was resolved from the reviewed evidence. | AG45: Unknown | AH45: Unknown | AI45: Found smartListGenerator.js and searchService.js but no dedicated UI components for browsing.; A prior area review labelled this 'Partial', but did not supply a feature-level physical mapping; the authoritative state is therefore Unknown. | AJ45: Unknown | AK45: EV-03-0001 | AO45: 8bc0dcb2a1da1b21368c5536aaeef829d587f316 | AP45: Low | AQ45: Not assessed | AR45: Not assessed | AS45: Not assessed | AT45: Not assessed | AU45: Not assessed | AV45: Not assessed | AW45: Not assessed | AX45: Not assessed | AY45: Not assessed | AZ45: Not assessed | BA45: Not assessed | BB45: Not assessed | BC45: Not assessed | BD45: Not assessed | BE45: Not assessed | BF45: Production readiness cannot be assessed until the exact physical implementation and runtime path are traced. | BG45: Map the feature to exact client, server, data, worker and configuration locations, then verify its runtime path. | BK45: Evidence reconciled against the reviewed source revision. No production approval is inferred from implementation or file presence. | BL45: 2026-08-02
A46: BLYP-03-004 | C46: Interest hubs | D46: 3 | E46: 4 | F46: Feature | G46: Dedicated Interest hub pages | H46: Dedicated Interest hub pages | I46: /home/ubuntu/blyp_product_requirements.md :: Section 3 — Interest hubs | J46: /home/ubuntu/BLYP_COMPLETE_FEATURE_LIST.md:70 | K46: Required | L46: Applicable BLYP member | M46: BLYP mobile application and supporting production services | N46: Dedicated Interest hub pages | O46: Not explicitly defined in the product source; requires accountable product approval before production sign-off. | Q46: Partial | S46: Not found | AE46: Unknown | AG46: Unknown | AH46: Unknown | AI46: Searched for hub, interest, category, hashtag, football, formula 1, fixtures, empty state, invite, bot, fake. No concrete implementation found. | AJ46: Not verified | AO46: 8bc0dcb2a1da1b21368c5536aaeef829d587f316 | AP46: Low | AQ46: Not assessed | AR46: Not assessed | AS46: Not assessed | AT46: Not assessed | AU46: Not assessed | AV46: Not assessed | AW46: Not assessed | AX46: Not assessed | AY46: Not assessed | AZ46: Not assessed | BA46: Not assessed | BB46: Not assessed | BC46: Not assessed | BD46: Not assessed | BE46: Development required | BF46: Physical implementation is not complete against the stated requirement.; Searched for hub, interest, category, hashtag, football, formula 1, fixtures, empty state, invite, bot, fake. No concrete implementation found. | BK46: Evidence reconciled against the reviewed source revision. No production approval is inferred from implementation or file presence. | BL46: 2026-08-02
A47: BLYP-03-005 | C47: Interest hubs | D47: 3 | E47: 5 | F47: Feature | G47: Football hub | H47: Football hub | I47: /home/ubuntu/blyp_product_requirements.md :: Section 3 — Interest hubs | J47: /home/ubuntu/BLYP_COMPLETE_FEATURE_LIST.md:71 | K47: Required | L47: Applicable BLYP member | M47: BLYP mobile application and supporting production services | N47: Football hub | O47: Not explicitly defined in the product source; requires accountable product approval before production sign-off. | Q47: Needs verification | S47: Not found | AE47: Unknown | AG47: Unknown | AH47: Unknown | AI47: Searched for hub, interest, category, hashtag, football, formula 1, fixtures, empty state, invite, bot, fake. No concrete implementation found. | AJ47: Not verified | AO47: 8bc0dcb2a1da1b21368c5536aaeef829d587f316 | AP47: Low | AQ47: Not assessed | AR47: Not assessed | AS47: Not assessed | AT47: Not assessed | AU47: Not assessed | AV47: Not assessed | AW47: Not assessed | AX47: Not assessed | AY47: Not assessed | AZ47: Not assessed | BA47: Not assessed | BB47: Not assessed | BC47: Not assessed | BD47: Not assessed | BE47: Development required | BF47: Physical implementation is not complete against the stated requirement.; Searched for hub, interest, category, hashtag, football, formula 1, fixtures, empty state, invite, bot, fake. No concrete implementation found. | BK47: Evidence reconciled against the reviewed source revision. No production approval is inferred from implementation or file presence. | BL47: 2026-08-02
A48: BLYP-03-006 | C48: Interest hubs | D48: 3 | E48: 6 | F48: Feature | G48: Formula 1 hub | H48: Formula 1 hub | I48: /home/ubuntu/blyp_product_requirements.md :: Section 3 — Interest hubs | J48: /home/ubuntu/BLYP_COMPLETE_FEATURE_LIST.md:72 | K48: Required | L48: Applicable BLYP member | M48: BLYP mobile application and supporting production services | N48: Formula 1 hub | O48: Not explicitly defined in the product source; requires accountable product approval before production sign-off. | Q48: Needs verification | S48: Not found | AE48: Unknown | AG48: Unknown | AH48: Unknown | AI48: Searched for hub, interest, category, hashtag, football, formula 1, fixtures, empty state, invite, bot, fake. No concrete implementation found. | AJ48: Not verified | AO48: 8bc0dcb2a1da1b21368c5536aaeef829d587f316 | AP48: Low | AQ48: Not assessed | AR48: Not assessed | AS48: Not assessed | AT48: Not assessed | AU48: Not assessed | AV48: Not assessed | AW48: Not assessed | AX48: Not assessed | AY48: Not assessed | AZ48: Not assessed | BA48: Not assessed | BB48: Not assessed | BC48: Not assessed | BD48: Not assessed | BE48: Development required | BF48: Physical implementation is not complete against the stated requirement.; Searched for hub, interest, category, hashtag, football, formula 1, fixtures, empty state, invite, bot, fake. No concrete implementation found. | BK48: Evidence reconciled against the reviewed source revision. No production approval is inferred from implementation or file presence. | BL48: 2026-08-02
A49: BLYP-03-007 | C49: Interest hubs | D49: 3 | E49: 7 | F49: Feature | G49: Relevant posts inside an Interest | H49: Relevant posts inside an Interest | I49: /home/ubuntu/blyp_product_requirements.md :: Section 3 — Interest hubs | J49: /home/ubuntu/BLYP_COMPLETE_FEATURE_LIST.md:73 | K49: Required | L49: Applicable BLYP member | M49: BLYP mobile application and supporting production services | N49: Relevant posts inside an Interest | O49: Not explicitly defined in the product source; requires accountable product approval before production sign-off. | Q49: Partial | S49: Not found | AE49: Unknown | AG49: Unknown | AH49: Unknown | AI49: Searched for hub, interest, category, hashtag, football, formula 1, fixtures, empty state, invite, bot, fake. No concrete implementation found. | AJ49: Not verified | AO49: 8bc0dcb2a1da1b21368c5536aaeef829d587f316 | AP49: Low | AQ49: Not assessed | AR49: Not assessed | AS49: Not assessed | AT49: Not assessed | AU49: Not assessed | AV49: Not assessed | AW49: Not assessed | AX49: Not assessed | AY49: Not assessed | AZ49: Not assessed | BA49: Not assessed | BB49: Not assessed | BC49: Not assessed | BD49: Not assessed | BE49: Development required | BF49: Physical implementation is not complete against the stated requirement.; Searched for hub, interest, category, hashtag, football, formula 1, fixtures, empty state, invite, bot, fake. No concrete implementation found. | BK49: Evidence reconciled against the reviewed source revision. No production approval is inferred from implementation or file presence. | BL49: 2026-08-02
A50: BLYP-03-008 | C50: Interest hubs | D50: 3 | E50: 8 | F50: Feature | G50: Relevant videos inside an Interest | H50: Relevant videos inside an Interest | I50: /home/ubuntu/blyp_product_requirements.md :: Section 3 — Interest hubs | J50: /home/ubuntu/BLYP_COMPLETE_FEATURE_LIST.md:74 | K50: Required | L50: Applicable BLYP member | M50: BLYP mobile application and supporting production services | N50: Relevant videos inside an Interest | O50: Not explicitly defined in the product source; requires accountable product approval before production sign-off. | Q50: Partial | S50: Not found | AE50: Unknown | AG50: Unknown | AH50: Unknown | AI50: Searched for hub, interest, category, hashtag, football, formula 1, fixtures, empty state, invite, bot, fake. No concrete implementation found. | AJ50: Not verified | AO50: 8bc0dcb2a1da1b21368c5536aaeef829d587f316 | AP50: Low | AQ50: Not assessed | AR50: Not assessed | AS50: Not assessed | AT50: Not assessed | AU50: Not assessed | AV50: Not assessed | AW50: Not assessed | AX50: Not assessed | AY50: Not assessed | AZ50: Not assessed | BA50: Not assessed | BB50: Not assessed | BC50: Not assessed | BD50: Not assessed | BE50: Development required | BF50: Physical implementation is not complete against the stated requirement.; Searched for hub, interest, category, hashtag, football, formula 1, fixtures, empty state, invite, bot, fake. No concrete implementation found. | BK50: Evidence reconciled against the reviewed source revision. No production approval is inferred from implementation or file presence. | BL50: 2026-08-02
A51: BLYP-03-009 | C51: Interest hubs | D51: 3 | E51: 9 | F51: Feature | G51: Relevant creators inside an Interest | H51: Relevant creators inside an Interest | I51: /home/ubuntu/blyp_product_requirements.md :: Section 3 — Interest hubs | J51: /home/ubuntu/BLYP_COMPLETE_FEATURE_LIST.md:75 | K51: Required | L51: Authenticated creator or host | M51: BLYP mobile application and supporting production services | N51: Relevant creators inside an Interest | O51: Not explicitly defined in the product source; requires accountable product approval before production sign-off. | Q51: Partial | S51: Not found | AE51: Unknown | AG51: Unknown | AH51: Unknown | AI51: Searched for hub, interest, category, hashtag, football, formula 1, fixtures, empty state, invite, bot, fake. No concrete implementation found. | AJ51: Not verified | AO51: 8bc0dcb2a1da1b21368c5536aaeef829d587f316 | AP51: Low | AQ51: Not assessed | AR51: Not assessed | AS51: Not assessed | AT51: Not assessed | AU51: Not assessed | AV51: Not assessed | AW51: Not assessed | AX51: Not assessed | AY51: Not assessed | AZ51: Not assessed | BA51: Not assessed | BB51: Not assessed | BC51: Not assessed | BD51: Not assessed | BE51: Development required | BF51: Physical implementation is not complete against the stated requirement.; Searched for hub, interest, category, hashtag, football, formula 1, fixtures, empty state, invite, bot, fake. No concrete implementation found. | BK51: Evidence reconciled against the reviewed source revision. No production approval is inferred from implementation or file presence. | BL51: 2026-08-02
A52: BLYP-03-010 | C52: Interest hubs | D52: 3 | E52: 10 | F52: Feature | G52: Relevant live streams inside an Interest | H52: Relevant live streams inside an Interest | I52: /home/ubuntu/blyp_product_requirements.md :: Section 3 — Interest hubs | J52: /home/ubuntu/BLYP_COMPLETE_FEATURE_LIST.md:76 | K52: Required | L52: Applicable BLYP member | M52: BLYP mobile application and supporting production services | N52: Relevant live streams inside an Interest | O52: Not explicitly defined in the product source; requires accountable product approval before production sign-off. | Q52: Partial | S52: Not found | AE52: Unknown | AG52: Unknown | AH52: Unknown | AI52: Searched for hub, interest, category, hashtag, football, formula 1, fixtures, empty state, invite, bot, fake. No concrete implementation found. | AJ52: Not verified | AO52: 8bc0dcb2a1da1b21368c5536aaeef829d587f316 | AP52: Low | AQ52: Not assessed | AR52: Not assessed | AS52: Not assessed | AT52: Not assessed | AU52: Not assessed | AV52: Not assessed | AW52: Not assessed | AX52: Not assessed | AY52: Not assessed | AZ52: Not assessed | BA52: Not assessed | BB52: Not assessed | BC52: Not assessed | BD52: Not assessed | BE52: Development required | BF52: Physical implementation is not complete against the stated requirement.; Searched for hub, interest, category, hashtag, football, formula 1, fixtures, empty state, invite, bot, fake. No concrete implementation found. | BK52: Evidence reconciled against the reviewed source revision. No production approval is inferred from implementation or file presence. | BL52: 2026-08-02
A53: BLYP-03-011 | C53: Interest hubs | D53: 3 | E53: 11 | F53: Feature | G53: Communal live rooms inside an Interest | H53: Communal live rooms inside an Interest | I53: /home/ubuntu/blyp_product_requirements.md :: Section 3 — Interest hubs | J53: /home/ubuntu/BLYP_COMPLETE_FEATURE_LIST.md:77 | K53: Required | L53: Applicable BLYP member | M53: BLYP mobile application and supporting production services | N53: Communal live rooms inside an Interest | O53: Not explicitly defined in the product source; requires accountable product approval before production sign-off. | Q53: No evidence | S53: Not found | AE53: Unknown | AG53: Unknown | AH53: Unknown | AI53: Searched for hub, interest, category, hashtag, football, formula 1, fixtures, empty state, invite, bot, fake. No concrete implementation found. | AJ53: Not verified | AO53: 8bc0dcb2a1da1b21368c5536aaeef829d587f316 | AP53: Low | AQ53: Not assessed | AR53: Not assessed | AS53: Not assessed | AT53: Not assessed | AU53: Not assessed | AV53: Not assessed | AW53: Not assessed | AX53: Not assessed | AY53: Not assessed | AZ53: Not assessed | BA53: Not assessed | BB53: Not assessed | BC53: Not assessed | BD53: Not assessed | BE53: Development required | BF53: Physical implementation is not complete against the stated requirement.; Searched for hub, interest, category, hashtag, football, formula 1, fixtures, empty state, invite, bot, fake. No concrete implementation found. | BK53: Evidence reconciled against the reviewed source revision. No production approval is inferred from implementation or file presence. | BL53: 2026-08-02
A54: BLYP-03-012 | C54: Interest hubs | D54: 3 | E54: 12 | F54: Feature | G54: Persistent topic conversation | H54: Persistent topic conversation | I54: /home/ubuntu/blyp_product_requirements.md :: Section 3 — Interest hubs | J54: /home/ubuntu/BLYP_COMPLETE_FEATURE_LIST.md:78 | K54: Required | L54: Applicable BLYP member | M54: BLYP mobile application and supporting production services | N54: Persistent topic conversation | O54: Not explicitly defined in the product source; requires accountable product approval before production sign-off. | Q54: Yes | R54: text chat-room foundations exist. | S54: Not found | AE54: Unknown | AG54: Unknown | AH54: Unknown | AI54: Searched for hub, interest, category, hashtag, football, formula 1, fixtures, empty state, invite, bot, fake. No concrete implementation found. | AJ54: Not verified | AO54: 8bc0dcb2a1da1b21368c5536aaeef829d587f316 | AP54: Low | AQ54: Not assessed | AR54: Not assessed | AS54: Not assessed | AT54: Not assessed | AU54: Not assessed | AV54: Not assessed | AW54: Not assessed | AX54: Not assessed | AY54: Not assessed | AZ54: Not assessed | BA54: Not assessed | BB54: Not assessed | BC54: Not assessed | BD54: Not assessed | BE54: Development required | BF54: Physical implementation is not complete against the stated requirement.; Searched for hub, interest, category, hashtag, football, formula 1, fixtures, empty state, invite, bot, fake. No concrete implementation found. | BK54: Evidence reconciled against the reviewed source revision. No production approval is inferred from implementation or file presence. | BL54: 2026-08-02
A55: BLYP-03-013 | C55: Interest hubs | D55: 3 | E55: 13 | F55: Feature | G55: Follow an Interest | H55: Follow an Interest | I55: /home/ubuntu/blyp_product_requirements.md :: Section 3 — Interest hubs | J55: /home/ubuntu/BLYP_COMPLETE_FEATURE_LIST.md:79 | K55: Required | L55: Applicable BLYP member | M55: BLYP mobile application and supporting production services | N55: Follow an Interest | O55: Not explicitly defined in the product source; requires accountable product approval before production sign-off. | Q55: Partial | S55: Not found | AE55: Unknown | AG55: Unknown | AH55: Unknown | AI55: Searched for hub, interest, category, hashtag, football, formula 1, fixtures, empty state, invite, bot, fake. No concrete implementation found. | AJ55: Not verified | AO55: 8bc0dcb2a1da1b21368c5536aaeef829d587f316 | AP55: Low | AQ55: Not assessed | AR55: Not assessed | AS55: Not assessed | AT55: Not assessed | AU55: Not assessed | AV55: Not assessed | AW55: Not assessed | AX55: Not assessed | AY55: Not assessed | AZ55: Not assessed | BA55: Not assessed | BB55: Not assessed | BC55: Not assessed | BD55: Not assessed | BE55: Development required | BF55: Physical implementation is not complete against the stated requirement.; Searched for hub, interest, category, hashtag, football, formula 1, fixtures, empty state, invite, bot, fake. No concrete implementation found. | BK55: Evidence reconciled against the reviewed source revision. No production approval is inferred from implementation or file presence. | BL55: 2026-08-02
A56: BLYP-03-014 | C56: Interest hubs | D56: 3 | E56: 14 | F56: Feature | G56: Interest notifications | H56: Interest notifications | I56: /home/ubuntu/blyp_product_requirements.md :: Section 3 — Interest hubs | J56: /home/ubuntu/BLYP_COMPLETE_FEATURE_LIST.md:80 | K56: Required | L56: Applicable BLYP member | M56: BLYP mobile application and supporting production services | N56: Interest notifications | O56: Not explicitly defined in the product source; requires accountable product approval before production sign-off. | Q56: Partial | S56: Not found | AE56: Unknown | AG56: Unknown | AH56: Unknown | AI56: Searched for hub, interest, category, hashtag, football, formula 1, fixtures, empty state, invite, bot, fake. No concrete implementation found. | AJ56: Not verified | AO56: 8bc0dcb2a1da1b21368c5536aaeef829d587f316 | AP56: Low | AQ56: Not assessed | AR56: Not assessed | AS56: Not assessed | AT56: Not assessed | AU56: Not assessed | AV56: Not assessed | AW56: Not assessed | AX56: Not assessed | AY56: Not assessed | AZ56: Not assessed | BA56: Not assessed | BB56: Not assessed | BC56: Not assessed | BD56: Not assessed | BE56: Development required | BF56: Physical implementation is not complete against the stated requirement.; Searched for hub, interest, category, hashtag, football, formula 1, fixtures, empty state, invite, bot, fake. No concrete implementation found. | BK56: Evidence reconciled against the reviewed source revision. No production approval is inferred from implementation or file presence. | BL56: 2026-08-02
A57: BLYP-03-015 | C57: Interest hubs | D57: 3 | E57: 15 | F57: Feature | G57: Fixtures, schedules, results, or attributed factual information | H57: Fixtures, schedules, results, or attributed factual information | I57: /home/ubuntu/blyp_product_requirements.md :: Section 3 — Interest hubs | J57: /home/ubuntu/BLYP_COMPLETE_FEATURE_LIST.md:81 | K57: Required | L57: Applicable BLYP member | M57: BLYP mobile application and supporting production services | N57: Fixtures, schedules, results, or attributed factual information | O57: Not explicitly defined in the product source; requires accountable product approval before production sign-off. | Q57: No evidence | S57: Not found | AE57: Unknown | AG57: Unknown | AH57: Unknown | AI57: Searched for hub, interest, category, hashtag, football, formula 1, fixtures, empty state, invite, bot, fake. No concrete implementation found. | AJ57: Not verified | AO57: 8bc0dcb2a1da1b21368c5536aaeef829d587f316 | AP57: Low | AQ57: Not assessed | AR57: Not assessed | AS57: Not assessed | AT57: Not assessed | AU57: Not assessed | AV57: Not assessed | AW57: Not assessed | AX57: Not assessed | AY57: Not assessed | AZ57: Not assessed | BA57: Not assessed | BB57: Not assessed | BC57: Not assessed | BD57: Not assessed | BE57: Development required | BF57: Physical implementation is not complete against the stated requirement.; Searched for hub, interest, category, hashtag, football, formula 1, fixtures, empty state, invite, bot, fake. No concrete implementation found. | BK57: Evidence reconciled against the reviewed source revision. No production approval is inferred from implementation or file presence. | BL57: 2026-08-02
A58: BLYP-03-016 | C58: Interest hubs | D58: 3 | E58: 16 | F58: Feature | G58: Honest empty-state message for a quiet Interest | H58: Honest empty-state message for a quiet Interest | I58: /home/ubuntu/blyp_product_requirements.md :: Section 3 — Interest hubs | J58: /home/ubuntu/BLYP_COMPLETE_FEATURE_LIST.md:82 | K58: Required | L58: Applicable BLYP member | M58: BLYP mobile application and supporting production services | N58: Honest empty-state message for a quiet Interest | O58: Not explicitly defined in the product source; requires accountable product approval before production sign-off. | Q58: No evidence | S58: Not found | AE58: Unknown | AG58: Unknown | AH58: Unknown | AI58: Searched for hub, interest, category, hashtag, football, formula 1, fixtures, empty state, invite, bot, fake. No concrete implementation found. | AJ58: Not verified | AO58: 8bc0dcb2a1da1b21368c5536aaeef829d587f316 | AP58: Low | AQ58: Not assessed | AR58: Not assessed | AS58: Not assessed | AT58: Not assessed | AU58: Not assessed | AV58: Not assessed | AW58: Not assessed | AX58: Not assessed | AY58: Not assessed | AZ58: Not assessed | BA58: Not assessed | BB58: Not assessed | BC58: Not assessed | BD58: Not assessed | BE58: Development required | BF58: Physical implementation is not complete against the stated requirement.; Searched for hub, interest, category, hashtag, football, formula 1, fixtures, empty state, invite, bot, fake. No concrete implementation found. | BK58: Evidence reconciled against the reviewed source revision. No production approval is inferred from implementation or file presence. | BL58: 2026-08-02
A59: BLYP-03-017 | C59: Interest hubs | D59: 3 | E59: 17 | F59: Feature | G59: Invite real creators to an Interest | H59: Invite real creators to an Interest | I59: /home/ubuntu/blyp_product_requirements.md :: Section 3 — Interest hubs | J59: /home/ubuntu/BLYP_COMPLETE_FEATURE_LIST.md:83 | K59: Required | L59: Authenticated creator or host | M59: BLYP mobile application and supporting production services | N59: Invite real creators to an Interest | O59: Not explicitly defined in the product source; requires accountable product approval before production sign-off. | Q59: No evidence | S59: Not found | AE59: Unknown | AG59: Unknown | AH59: Unknown | AI59: Searched for hub, interest, category, hashtag, football, formula 1, fixtures, empty state, invite, bot, fake. No concrete implementation found. | AJ59: Not verified | AO59: 8bc0dcb2a1da1b21368c5536aaeef829d587f316 | AP59: Low | AQ59: Not assessed | AR59: Not assessed | AS59: Not assessed | AT59: Not assessed | AU59: Not assessed | AV59: Not assessed | AW59: Not assessed | AX59: Not assessed | AY59: Not assessed | AZ59: Not assessed | BA59: Not assessed | BB59: Not assessed | BC59: Not assessed | BD59: Not assessed | BE59: Development required | BF59: Physical implementation is not complete against the stated requirement.; Searched for hub, interest, category, hashtag, football, formula 1, fixtures, empty state, invite, bot, fake. No concrete implementation found. | BK59: Evidence reconciled against the reviewed source revision. No production approval is inferred from implementation or file presence. | BL59: 2026-08-02
A60: BLYP-03-018 | C60: Interest hubs | D60: 3 | E60: 18 | F60: Feature | G60: Create the first content in a quiet Interest | H60: Create the first content in a quiet Interest | I60: /home/ubuntu/blyp_product_requirements.md :: Section 3 — Interest hubs | J60: /home/ubuntu/BLYP_COMPLETE_FEATURE_LIST.md:84 | K60: Required | L60: Applicable BLYP member | M60: BLYP mobile application and supporting production services | N60: Create the first content in a quiet Interest | O60: Not explicitly defined in the product source; requires accountable product approval before production sign-off. | Q60: Partial | R60: general posting exists, but the hub-specific journey is not proven. | S60: Not found | AE60: Unknown | AG60: Unknown | AH60: Unknown | AI60: Searched for hub, interest, category, hashtag, football, formula 1, fixtures, empty state, invite, bot, fake. No concrete implementation found. | AJ60: Not verified | AO60: 8bc0dcb2a1da1b21368c5536aaeef829d587f316 | AP60: Low | AQ60: Not assessed | AR60: Not assessed | AS60: Not assessed | AT60: Not assessed | AU60: Not assessed | AV60: Not assessed | AW60: Not assessed | AX60: Not assessed | AY60: Not assessed | AZ60: Not assessed | BA60: Not assessed | BB60: Not assessed | BC60: Not assessed | BD60: Not assessed | BE60: Development required | BF60: Physical implementation is not complete against the stated requirement.; Searched for hub, interest, category, hashtag, football, formula 1, fixtures, empty state, invite, bot, fake. No concrete implementation found. | BK60: Evidence reconciled against the reviewed source revision. No production approval is inferred from implementation or file presence. | BL60: 2026-08-02
A61: BLYP-03-019 | C61: Interest hubs | D61: 3 | E61: 19 | F61: Rule | G61: No bots, fake accounts, fake posts, fake engagement, or misleading counts | H61: No bots, fake accounts, fake posts, fake engagement, or misleading counts | I61: /home/ubuntu/blyp_product_requirements.md :: Section 3 — Interest hubs | J61: /home/ubuntu/BLYP_COMPLETE_FEATURE_LIST.md:85 | K61: Required | L61: Applicable BLYP member | M61: BLYP mobile application and supporting production services | N61: No bots, fake accounts, fake posts, fake engagement, or misleading counts | O61: Not explicitly defined in the product source; requires accountable product approval before production sign-off. | Q61: No | R61: manufactured fallback content and randomised counts were found. | S61: Not found | AE61: Unknown | AG61: Unknown | AH61: Unknown | AI61: Found manufactured fallback content and randomised counts. | AJ61: Not verified | AK61: EV-03-0002 | AO61: 8bc0dcb2a1da1b21368c5536aaeef829d587f316 | AP61: Low | AQ61: Not assessed | AR61: Not assessed | AS61: Not assessed | AT61: Not assessed | AU61: Not assessed | AV61: Not assessed | AW61: Not assessed | AX61: Not assessed | AY61: Not assessed | AZ61: Not assessed | BA61: Not assessed | BB61: Not assessed | BC61: Not assessed | BD61: Not assessed | BE61: Development required | BF61: Physical implementation is not complete against the stated requirement.; Found manufactured fallback content and randomised counts. | BK61: Evidence reconciled against the reviewed source revision. No production approval is inferred from implementation or file presence. | BL61: 2026-08-02
A62: BLYP-04-001 | C62: Always-on communal topic live rooms | D62: 4 | E62: 1 | F62: Feature | G62: Always-available Interest live room | H62: Always-available Interest live room | I62: /home/ubuntu/blyp_product_requirements.md :: Section 4 — Always-on communal topic live rooms | J62: /home/ubuntu/BLYP_COMPLETE_FEATURE_LIST.md:91 | K62: Required | L62: Applicable BLYP member | M62: BLYP mobile application and supporting production services | N62: Always-available Interest live room | O62: Not explicitly defined in the product source; requires accountable product approval before production sign-off. | Q62: No evidence | S62: Unknown | T62: Unknown | U62: Unknown | V62: Unknown | W62: Unknown | X62: Unknown | Y62: Unknown | Z62: Unknown | AA62: Unknown | AB62: Unknown | AE62: Unknown | AF62: No exact feature-level physical path was resolved from the reviewed evidence. | AG62: Unknown | AH62: Unknown | AI62: Searched src/; A prior area review labelled this 'Partial', but did not supply a feature-level physical mapping; the authoritative state is therefore Unknown. | AJ62: Unknown | AK62: EV-04-0001 | AO62: 8bc0dcb2a1da1b21368c5536aaeef829d587f316 | AP62: Low | AQ62: Not assessed | AR62: Not assessed | AS62: Not assessed | AT62: Not assessed | AU62: Not assessed | AV62: Not assessed | AW62: Not assessed | AX62: Not assessed | AY62: Not assessed | AZ62: Not assessed | BA62: Not assessed | BB62: Not assessed | BC62: Not assessed | BD62: Not assessed | BE62: Not assessed | BF62: Production readiness cannot be assessed until the exact physical implementation and runtime path are traced. | BG62: Map the feature to exact client, server, data, worker and configuration locations, then verify its runtime path. | BK62: Evidence reconciled against the reviewed source revision. No production approval is inferred from implementation or file presence. | BL62: 2026-08-02
A63: BLYP-04-002 | C63: Always-on communal topic live rooms | D63: 4 | E63: 2 | F63: Rule | G63: Community-owned room with no permanent host | H63: Community-owned room with no permanent host | I63: /home/ubuntu/blyp_product_requirements.md :: Section 4 — Always-on communal topic live rooms | J63: /home/ubuntu/BLYP_COMPLETE_FEATURE_LIST.md:92 | K63: Required | L63: Authenticated creator or host | M63: BLYP mobile application and supporting production services | N63: Community-owned room with no permanent host | O63: Not explicitly defined in the product source; requires accountable product approval before production sign-off. | Q63: No evidence | S63: Unknown | T63: Unknown | U63: Unknown | V63: Unknown | W63: Unknown | X63: Unknown | Y63: Unknown | Z63: Unknown | AA63: Unknown | AB63: Unknown | AE63: Unknown | AF63: No exact feature-level physical path was resolved from the reviewed evidence. | AG63: Unknown | AH63: Unknown | AI63: Searched src/; A prior area review labelled this 'Partial', but did not supply a feature-level physical mapping; the authoritative state is therefore Unknown. | AJ63: Unknown | AK63: EV-04-0002 | AO63: 8bc0dcb2a1da1b21368c5536aaeef829d587f316 | AP63: Low | AQ63: Not assessed | AR63: Not assessed | AS63: Not assessed | AT63: Not assessed | AU63: Not assessed | AV63: Not assessed | AW63: Not assessed | AX63: Not assessed | AY63: Not assessed | AZ63: Not assessed | BA63: Not assessed | BB63: Not assessed | BC63: Not assessed | BD63: Not assessed | BE63: Not assessed | BF63: Production readiness cannot be assessed until the exact physical implementation and runtime path are traced. | BG63: Map the feature to exact client, server, data, worker and configuration locations, then verify its runtime path. | BK63: Evidence reconciled against the reviewed source revision. No production approval is inferred from implementation or file presence. | BL63: 2026-08-02
A64: BLYP-04-003 | C64: Always-on communal topic live rooms | D64: 4 | E64: 3 | F64: Feature | G64: Enter first as a viewer | H64: Enter first as a viewer | I64: /home/ubuntu/blyp_product_requirements.md :: Section 4 — Always-on communal topic live rooms | J64: /home/ubuntu/BLYP_COMPLETE_FEATURE_LIST.md:93 | K64: Required | L64: Authenticated or eligible viewer | M64: BLYP mobile application and supporting production services | N64: Enter first as a viewer | O64: Not explicitly defined in the product source; requires accountable product approval before production sign-off. | Q64: Partial | R64: viewer entry exists for host-owned live streams. | S64: Unknown | T64: Unknown | U64: Unknown | V64: Unknown | W64: Unknown | X64: Unknown | Y64: Unknown | Z64: Unknown | AA64: Unknown | AB64: Unknown | AE64: Unknown | AF64: No exact feature-level physical path was resolved from the reviewed evidence. | AG64: Unknown | AH64: Unknown | AI64: Searched src/; A prior area review labelled this 'Partial', but did not supply a feature-level physical mapping; the authoritative state is therefore Unknown. | AJ64: Unknown | AK64: EV-04-0003 | AO64: 8bc0dcb2a1da1b21368c5536aaeef829d587f316 | AP64: Low | AQ64: Not assessed | AR64: Not assessed | AS64: Not assessed | AT64: Not assessed | AU64: Not assessed | AV64: Not assessed | AW64: Not assessed | AX64: Not assessed | AY64: Not assessed | AZ64: Not assessed | BA64: Not assessed | BB64: Not assessed | BC64: Not assessed | BD64: Not assessed | BE64: Not assessed | BF64: Production readiness cannot be assessed until the exact physical implementation and runtime path are traced. | BG64: Map the feature to exact client, server, data, worker and configuration locations, then verify its runtime path. | BK64: Evidence reconciled against the reviewed source revision. No production approval is inferred from implementation or file presence. | BL64: 2026-08-02
A65: BLYP-04-004 | C65: Always-on communal topic live rooms | D65: 4 | E65: 4 | F65: Feature | G65: Request to join the stage | H65: Request to join the stage | I65: /home/ubuntu/blyp_product_requirements.md :: Section 4 — Always-on communal topic live rooms | J65: /home/ubuntu/BLYP_COMPLETE_FEATURE_LIST.md:94 | K65: Required | L65: Applicable BLYP member | M65: BLYP mobile application and supporting production services | N65: Request to join the stage | O65: Not explicitly defined in the product source; requires accountable product approval before production sign-off. | Q65: Partial | R65: approved-guest foundations exist. | S65: Unknown | T65: Unknown | U65: Unknown | V65: Unknown | W65: Unknown | X65: Unknown | Y65: Unknown | Z65: Unknown | AA65: Unknown | AB65: Unknown | AE65: Unknown | AF65: No exact feature-level physical path was resolved from the reviewed evidence. | AG65: Unknown | AH65: Unknown | AI65: Searched src/; A prior area review labelled this 'Partial', but did not supply a feature-level physical mapping; the authoritative state is therefore Unknown. | AJ65: Unknown | AK65: EV-04-0004 | AO65: 8bc0dcb2a1da1b21368c5536aaeef829d587f316 | AP65: Low | AQ65: Not assessed | AR65: Not assessed | AS65: Not assessed | AT65: Not assessed | AU65: Not assessed | AV65: Not assessed | AW65: Not assessed | AX65: Not assessed | AY65: Not assessed | AZ65: Not assessed | BA65: Not assessed | BB65: Not assessed | BC65: Not assessed | BD65: Not assessed | BE65: Not assessed | BF65: Production readiness cannot be assessed until the exact physical implementation and runtime path are traced. | BG65: Map the feature to exact client, server, data, worker and configuration locations, then verify its runtime path. | BK65: Evidence reconciled against the reviewed source revision. No production approval is inferred from implementation or file presence. | BL65: 2026-08-02
A66: BLYP-04-005 | C66: Always-on communal topic live rooms | D66: 4 | E66: 5 | F66: Feature | G66: Final confirmation before joining the stage | H66: Final confirmation before joining the stage | I66: /home/ubuntu/blyp_product_requirements.md :: Section 4 — Always-on communal topic live rooms | J66: /home/ubuntu/BLYP_COMPLETE_FEATURE_LIST.md:95 | K66: Required | L66: Applicable BLYP member | M66: BLYP mobile application and supporting production services | N66: Final confirmation before joining the stage | O66: Not explicitly defined in the product source; requires accountable product approval before production sign-off. | Q66: Needs verification | S66: Unknown | T66: Unknown | U66: Unknown | V66: Unknown | W66: Unknown | X66: Unknown | Y66: Unknown | Z66: Unknown | AA66: Unknown | AB66: Unknown | AE66: Unknown | AF66: No exact feature-level physical path was resolved from the reviewed evidence. | AG66: Unknown | AH66: Unknown | AI66: Searched src/; A prior area review labelled this 'Partial', but did not supply a feature-level physical mapping; the authoritative state is therefore Unknown. | AJ66: Unknown | AK66: EV-04-0005 | AO66: 8bc0dcb2a1da1b21368c5536aaeef829d587f316 | AP66: Low | AQ66: Not assessed | AR66: Not assessed | AS66: Not assessed | AT66: Not assessed | AU66: Not assessed | AV66: Not assessed | AW66: Not assessed | AX66: Not assessed | AY66: Not assessed | AZ66: Not assessed | BA66: Not assessed | BB66: Not assessed | BC66: Not assessed | BD66: Not assessed | BE66: Not assessed | BF66: Production readiness cannot be assessed until the exact physical implementation and runtime path are traced. | BG66: Map the feature to exact client, server, data, worker and configuration locations, then verify its runtime path. | BK66: Evidence reconciled against the reviewed source revision. No production approval is inferred from implementation or file presence. | BL66: 2026-08-02
A67: BLYP-04-006 | C67: Always-on communal topic live rooms | D67: 4 | E67: 6 | F67: Feature | G67: Automatic promotion when a slot is available | H67: Automatic promotion when a slot is available | I67: /home/ubuntu/blyp_product_requirements.md :: Section 4 — Always-on communal topic live rooms | J67: /home/ubuntu/BLYP_COMPLETE_FEATURE_LIST.md:96 | K67: Required | L67: Applicable BLYP member | M67: BLYP mobile application and supporting production services | N67: Automatic promotion when a slot is available | O67: Not explicitly defined in the product source; requires accountable product approval before production sign-off. | Q67: No evidence | S67: Unknown | T67: Unknown | U67: Unknown | V67: Unknown | W67: Unknown | X67: Unknown | Y67: Unknown | Z67: Unknown | AA67: Unknown | AB67: Unknown | AE67: Unknown | AF67: No exact feature-level physical path was resolved from the reviewed evidence. | AG67: Unknown | AH67: Unknown | AI67: Searched src/; A prior area review labelled this 'Partial', but did not supply a feature-level physical mapping; the authoritative state is therefore Unknown. | AJ67: Unknown | AK67: EV-04-0006 | AO67: 8bc0dcb2a1da1b21368c5536aaeef829d587f316 | AP67: Low | AQ67: Not assessed | AR67: Not assessed | AS67: Not assessed | AT67: Not assessed | AU67: Not assessed | AV67: Not assessed | AW67: Not assessed | AX67: Not assessed | AY67: Not assessed | AZ67: Not assessed | BA67: Not assessed | BB67: Not assessed | BC67: Not assessed | BD67: Not assessed | BE67: Not assessed | BF67: Production readiness cannot be assessed until the exact physical implementation and runtime path are traced. | BG67: Map the feature to exact client, server, data, worker and configuration locations, then verify its runtime path. | BK67: Evidence reconciled against the reviewed source revision. No production approval is inferred from implementation or file presence. | BL67: 2026-08-02
A68: BLYP-04-007 | C68: Always-on communal topic live rooms | D68: 4 | E68: 7 | F68: Feature | G68: Visible queue when the stage is full | H68: Visible queue when the stage is full | I68: /home/ubuntu/blyp_product_requirements.md :: Section 4 — Always-on communal topic live rooms | J68: /home/ubuntu/BLYP_COMPLETE_FEATURE_LIST.md:97 | K68: Required | L68: Applicable BLYP member | M68: BLYP mobile application and supporting production services | N68: Visible queue when the stage is full | O68: Not explicitly defined in the product source; requires accountable product approval before production sign-off. | Q68: No evidence | S68: Unknown | T68: Unknown | U68: Unknown | V68: Unknown | W68: Unknown | X68: Unknown | Y68: Unknown | Z68: Unknown | AA68: Unknown | AB68: Unknown | AE68: Unknown | AF68: No exact feature-level physical path was resolved from the reviewed evidence. | AG68: Unknown | AH68: Unknown | AI68: Searched src/; A prior area review labelled this 'Partial', but did not supply a feature-level physical mapping; the authoritative state is therefore Unknown. | AJ68: Unknown | AK68: EV-04-0007 | AO68: 8bc0dcb2a1da1b21368c5536aaeef829d587f316 | AP68: Low | AQ68: Not assessed | AR68: Not assessed | AS68: Not assessed | AT68: Not assessed | AU68: Not assessed | AV68: Not assessed | AW68: Not assessed | AX68: Not assessed | AY68: Not assessed | AZ68: Not assessed | BA68: Not assessed | BB68: Not assessed | BC68: Not assessed | BD68: Not assessed | BE68: Not assessed | BF68: Production readiness cannot be assessed until the exact physical implementation and runtime path are traced. | BG68: Map the feature to exact client, server, data, worker and configuration locations, then verify its runtime path. | BK68: Evidence reconciled against the reviewed source revision. No production approval is inferred from implementation or file presence. | BL68: 2026-08-02
A69: BLYP-04-008 | C69: Always-on communal topic live rooms | D69: 4 | E69: 8 | F69: Feature | G69: Up to 12 simultaneous participant streams | H69: Up to 12 simultaneous participant streams | I69: /home/ubuntu/blyp_product_requirements.md :: Section 4 — Always-on communal topic live rooms | J69: /home/ubuntu/BLYP_COMPLETE_FEATURE_LIST.md:98 | K69: Required | L69: Applicable BLYP member | M69: BLYP mobile application and supporting production services | N69: Up to 12 simultaneous participant streams | O69: Not explicitly defined in the product source; requires accountable product approval before production sign-off. | Q69: Needs verification | R69: capacity foundations exist, but this exact communal-room model is not proven. | S69: Unknown | T69: Unknown | U69: Unknown | V69: Unknown | W69: Unknown | X69: Unknown | Y69: Unknown | Z69: Unknown | AA69: Unknown | AB69: Unknown | AE69: Unknown | AF69: No exact feature-level physical path was resolved from the reviewed evidence. | AG69: Unknown | AH69: Unknown | AI69: Searched src/; A prior area review labelled this 'Partial', but did not supply a feature-level physical mapping; the authoritative state is therefore Unknown. | AJ69: Unknown | AK69: EV-04-0008 | AO69: 8bc0dcb2a1da1b21368c5536aaeef829d587f316 | AP69: Low | AQ69: Not assessed | AR69: Not assessed | AS69: Not assessed | AT69: Not assessed | AU69: Not assessed | AV69: Not assessed | AW69: Not assessed | AX69: Not assessed | AY69: Not assessed | AZ69: Not assessed | BA69: Not assessed | BB69: Not assessed | BC69: Not assessed | BD69: Not assessed | BE69: Not assessed | BF69: Production readiness cannot be assessed until the exact physical implementation and runtime path are traced. | BG69: Map the feature to exact client, server, data, worker and configuration locations, then verify its runtime path. | BK69: Evidence reconciled against the reviewed source revision. No production approval is inferred from implementation or file presence. | BL69: 2026-08-02
A70: BLYP-04-009 | C70: Always-on communal topic live rooms | D70: 4 | E70: 9 | F70: Rule | G70: Camera off by default on promotion | H70: Camera off by default on promotion | I70: /home/ubuntu/blyp_product_requirements.md :: Section 4 — Always-on communal topic live rooms | J70: /home/ubuntu/BLYP_COMPLETE_FEATURE_LIST.md:99 | K70: Required | L70: Applicable BLYP member | M70: BLYP mobile application and supporting production services | N70: Camera off by default on promotion | O70: Not explicitly defined in the product source; requires accountable product approval before production sign-off. | Q70: No evidence | S70: Unknown | T70: Unknown | U70: Unknown | V70: Unknown | W70: Unknown | X70: Unknown | Y70: Unknown | Z70: Unknown | AA70: Unknown | AB70: Unknown | AE70: Unknown | AF70: No exact feature-level physical path was resolved from the reviewed evidence. | AG70: Unknown | AH70: Unknown | AI70: Searched src/; A prior area review labelled this 'Partial', but did not supply a feature-level physical mapping; the authoritative state is therefore Unknown. | AJ70: Unknown | AK70: EV-04-0009 | AO70: 8bc0dcb2a1da1b21368c5536aaeef829d587f316 | AP70: Low | AQ70: Not assessed | AR70: Not assessed | AS70: Not assessed | AT70: Not assessed | AU70: Not assessed | AV70: Not assessed | AW70: Not assessed | AX70: Not assessed | AY70: Not assessed | AZ70: Not assessed | BA70: Not assessed | BB70: Not assessed | BC70: Not assessed | BD70: Not assessed | BE70: Not assessed | BF70: Production readiness cannot be assessed until the exact physical implementation and runtime path are traced. | BG70: Map the feature to exact client, server, data, worker and configuration locations, then verify its runtime path. | BK70: Evidence reconciled against the reviewed source revision. No production approval is inferred from implementation or file presence. | BL70: 2026-08-02
A71: BLYP-04-010 | C71: Always-on communal topic live rooms | D71: 4 | E71: 10 | F71: Rule | G71: Microphone off by default on promotion | H71: Microphone off by default on promotion | I71: /home/ubuntu/blyp_product_requirements.md :: Section 4 — Always-on communal topic live rooms | J71: /home/ubuntu/BLYP_COMPLETE_FEATURE_LIST.md:100 | K71: Required | L71: Applicable BLYP member | M71: BLYP mobile application and supporting production services | N71: Microphone off by default on promotion | O71: Not explicitly defined in the product source; requires accountable product approval before production sign-off. | Q71: No evidence | S71: Unknown | T71: Unknown | U71: Unknown | V71: Unknown | W71: Unknown | X71: Unknown | Y71: Unknown | Z71: Unknown | AA71: Unknown | AB71: Unknown | AE71: Unknown | AF71: No exact feature-level physical path was resolved from the reviewed evidence. | AG71: Unknown | AH71: Unknown | AI71: Searched src/; A prior area review labelled this 'Partial', but did not supply a feature-level physical mapping; the authoritative state is therefore Unknown. | AJ71: Unknown | AK71: EV-04-0010 | AO71: 8bc0dcb2a1da1b21368c5536aaeef829d587f316 | AP71: Low | AQ71: Not assessed | AR71: Not assessed | AS71: Not assessed | AT71: Not assessed | AU71: Not assessed | AV71: Not assessed | AW71: Not assessed | AX71: Not assessed | AY71: Not assessed | AZ71: Not assessed | BA71: Not assessed | BB71: Not assessed | BC71: Not assessed | BD71: Not assessed | BE71: Not assessed | BF71: Production readiness cannot be assessed until the exact physical implementation and runtime path are traced. | BG71: Map the feature to exact client, server, data, worker and configuration locations, then verify its runtime path. | BK71: Evidence reconciled against the reviewed source revision. No production approval is inferred from implementation or file presence. | BL71: 2026-08-02
A72: BLYP-04-011 | C72: Always-on communal topic live rooms | D72: 4 | E72: 11 | F72: Feature | G72: Prominent camera/microphone overlay | H72: Prominent camera/microphone overlay | I72: /home/ubuntu/blyp_product_requirements.md :: Section 4 — Always-on communal topic live rooms | J72: /home/ubuntu/BLYP_COMPLETE_FEATURE_LIST.md:101 | K72: Required | L72: Applicable BLYP member | M72: BLYP mobile application and supporting production services | N72: Prominent camera/microphone overlay | O72: Not explicitly defined in the product source; requires accountable product approval before production sign-off. | Q72: No evidence | S72: Unknown | T72: Unknown | U72: Unknown | V72: Unknown | W72: Unknown | X72: Unknown | Y72: Unknown | Z72: Unknown | AA72: Unknown | AB72: Unknown | AE72: Unknown | AF72: No exact feature-level physical path was resolved from the reviewed evidence. | AG72: Unknown | AH72: Unknown | AI72: Searched src/; A prior area review labelled this 'Partial', but did not supply a feature-level physical mapping; the authoritative state is therefore Unknown. | AJ72: Unknown | AK72: EV-04-0011 | AO72: 8bc0dcb2a1da1b21368c5536aaeef829d587f316 | AP72: Low | AQ72: Not assessed | AR72: Not assessed | AS72: Not assessed | AT72: Not assessed | AU72: Not assessed | AV72: Not assessed | AW72: Not assessed | AX72: Not assessed | AY72: Not assessed | AZ72: Not assessed | BA72: Not assessed | BB72: Not assessed | BC72: Not assessed | BD72: Not assessed | BE72: Not assessed | BF72: Production readiness cannot be assessed until the exact physical implementation and runtime path are traced. | BG72: Map the feature to exact client, server, data, worker and configuration locations, then verify its runtime path. | BK72: Evidence reconciled against the reviewed source revision. No production approval is inferred from implementation or file presence. | BL72: 2026-08-02
A73: BLYP-04-012 | C73: Always-on communal topic live rooms | D73: 4 | E73: 12 | F73: Feature | G73: Independent camera and microphone controls | H73: Independent camera and microphone controls | I73: /home/ubuntu/blyp_product_requirements.md :: Section 4 — Always-on communal topic live rooms | J73: /home/ubuntu/BLYP_COMPLETE_FEATURE_LIST.md:102 | K73: Required | L73: Applicable BLYP member | M73: BLYP mobile application and supporting production services | N73: Independent camera and microphone controls | O73: Not explicitly defined in the product source; requires accountable product approval before production sign-off. | Q73: Partial | R73: live controls exist, but the communal-room implementation is not proven. | S73: Unknown | T73: Unknown | U73: Unknown | V73: Unknown | W73: Unknown | X73: Unknown | Y73: Unknown | Z73: Unknown | AA73: Unknown | AB73: Unknown | AE73: Unknown | AF73: No exact feature-level physical path was resolved from the reviewed evidence. | AG73: Unknown | AH73: Unknown | AI73: Searched src/; A prior area review labelled this 'Partial', but did not supply a feature-level physical mapping; the authoritative state is therefore Unknown. | AJ73: Unknown | AK73: EV-04-0012 | AO73: 8bc0dcb2a1da1b21368c5536aaeef829d587f316 | AP73: Low | AQ73: Not assessed | AR73: Not assessed | AS73: Not assessed | AT73: Not assessed | AU73: Not assessed | AV73: Not assessed | AW73: Not assessed | AX73: Not assessed | AY73: Not assessed | AZ73: Not assessed | BA73: Not assessed | BB73: Not assessed | BC73: Not assessed | BD73: Not assessed | BE73: Not assessed | BF73: Production readiness cannot be assessed until the exact physical implementation and runtime path are traced. | BG73: Map the feature to exact client, server, data, worker and configuration locations, then verify its runtime path. | BK73: Evidence reconciled against the reviewed source revision. No production approval is inferred from implementation or file presence. | BL73: 2026-08-02
A74: BLYP-04-013 | C74: Always-on communal topic live rooms | D74: 4 | E74: 13 | F74: Feature | G74: Responsive dynamic participant tiles | H74: Responsive dynamic participant tiles | I74: /home/ubuntu/blyp_product_requirements.md :: Section 4 — Always-on communal topic live rooms | J74: /home/ubuntu/BLYP_COMPLETE_FEATURE_LIST.md:103 | K74: Required | L74: Applicable BLYP member | M74: BLYP mobile application and supporting production services | N74: Responsive dynamic participant tiles | O74: Not explicitly defined in the product source; requires accountable product approval before production sign-off. | Q74: Partial | R74: live layouts exist; the specified communal layout does not. | S74: Unknown | T74: Unknown | U74: Unknown | V74: Unknown | W74: Unknown | X74: Unknown | Y74: Unknown | Z74: Unknown | AA74: Unknown | AB74: Unknown | AE74: Unknown | AF74: No exact feature-level physical path was resolved from the reviewed evidence. | AG74: Unknown | AH74: Unknown | AI74: Searched src/; A prior area review labelled this 'Partial', but did not supply a feature-level physical mapping; the authoritative state is therefore Unknown. | AJ74: Unknown | AK74: EV-04-0013 | AO74: 8bc0dcb2a1da1b21368c5536aaeef829d587f316 | AP74: Low | AQ74: Not assessed | AR74: Not assessed | AS74: Not assessed | AT74: Not assessed | AU74: Not assessed | AV74: Not assessed | AW74: Not assessed | AX74: Not assessed | AY74: Not assessed | AZ74: Not assessed | BA74: Not assessed | BB74: Not assessed | BC74: Not assessed | BD74: Not assessed | BE74: Not assessed | BF74: Production readiness cannot be assessed until the exact physical implementation and runtime path are traced. | BG74: Map the feature to exact client, server, data, worker and configuration locations, then verify its runtime path. | BK74: Evidence reconciled against the reviewed source revision. No production approval is inferred from implementation or file presence. | BL74: 2026-08-02
A75: BLYP-04-014 | C75: Always-on communal topic live rooms | D75: 4 | E75: 14 | F75: Feature | G75: Gift leader receives the largest tile | H75: Gift leader receives the largest tile | I75: /home/ubuntu/blyp_product_requirements.md :: Section 4 — Always-on communal topic live rooms | J75: /home/ubuntu/BLYP_COMPLETE_FEATURE_LIST.md:104 | K75: Required | L75: Applicable BLYP member | M75: BLYP mobile application and supporting production services | N75: Gift leader receives the largest tile | O75: Not explicitly defined in the product source; requires accountable product approval before production sign-off. | Q75: No evidence | S75: Unknown | T75: Unknown | U75: Unknown | V75: Unknown | W75: Unknown | X75: Unknown | Y75: Unknown | Z75: Unknown | AA75: Unknown | AB75: Unknown | AE75: Unknown | AF75: No exact feature-level physical path was resolved from the reviewed evidence. | AG75: Unknown | AH75: Unknown | AI75: Searched src/; A prior area review labelled this 'Partial', but did not supply a feature-level physical mapping; the authoritative state is therefore Unknown. | AJ75: Unknown | AK75: EV-04-0014 | AO75: 8bc0dcb2a1da1b21368c5536aaeef829d587f316 | AP75: Low | AQ75: Not assessed | AR75: Not assessed | AS75: Not assessed | AT75: Not assessed | AU75: Not assessed | AV75: Not assessed | AW75: Not assessed | AX75: Not assessed | AY75: Not assessed | AZ75: Not assessed | BA75: Not assessed | BB75: Not assessed | BC75: Not assessed | BD75: Not assessed | BE75: Not assessed | BF75: Production readiness cannot be assessed until the exact physical implementation and runtime path are traced. | BG75: Map the feature to exact client, server, data, worker and configuration locations, then verify its runtime path. | BK75: Evidence reconciled against the reviewed source revision. No production approval is inferred from implementation or file presence. | BL75: 2026-08-02
A76: BLYP-04-015 | C76: Always-on communal topic live rooms | D76: 4 | E76: 15 | F76: Feature | G76: Everyone remains visible during ranking changes | H76: Everyone remains visible during ranking changes | I76: /home/ubuntu/blyp_product_requirements.md :: Section 4 — Always-on communal topic live rooms | J76: /home/ubuntu/BLYP_COMPLETE_FEATURE_LIST.md:105 | K76: Required | L76: Applicable BLYP member | M76: BLYP mobile application and supporting production services | N76: Everyone remains visible during ranking changes | O76: Not explicitly defined in the product source; requires accountable product approval before production sign-off. | Q76: No evidence | S76: Unknown | T76: Unknown | U76: Unknown | V76: Unknown | W76: Unknown | X76: Unknown | Y76: Unknown | Z76: Unknown | AA76: Unknown | AB76: Unknown | AE76: Unknown | AF76: No exact feature-level physical path was resolved from the reviewed evidence. | AG76: Unknown | AH76: Unknown | AI76: Searched src/; A prior area review labelled this 'Partial', but did not supply a feature-level physical mapping; the authoritative state is therefore Unknown. | AJ76: Unknown | AK76: EV-04-0015 | AO76: 8bc0dcb2a1da1b21368c5536aaeef829d587f316 | AP76: Low | AQ76: Not assessed | AR76: Not assessed | AS76: Not assessed | AT76: Not assessed | AU76: Not assessed | AV76: Not assessed | AW76: Not assessed | AX76: Not assessed | AY76: Not assessed | AZ76: Not assessed | BA76: Not assessed | BB76: Not assessed | BC76: Not assessed | BD76: Not assessed | BE76: Not assessed | BF76: Production readiness cannot be assessed until the exact physical implementation and runtime path are traced. | BG76: Map the feature to exact client, server, data, worker and configuration locations, then verify its runtime path. | BK76: Evidence reconciled against the reviewed source revision. No production approval is inferred from implementation or file presence. | BL76: 2026-08-02
A77: BLYP-04-016 | C77: Always-on communal topic live rooms | D77: 4 | E77: 16 | F77: Feature | G77: 24-hour gift-ranking cycle | H77: 24-hour gift-ranking cycle | I77: /home/ubuntu/blyp_product_requirements.md :: Section 4 — Always-on communal topic live rooms | J77: /home/ubuntu/BLYP_COMPLETE_FEATURE_LIST.md:106 | K77: Required | L77: Applicable BLYP member | M77: BLYP mobile application and supporting production services | N77: 24-hour gift-ranking cycle | O77: Not explicitly defined in the product source; requires accountable product approval before production sign-off. | Q77: No evidence | S77: Unknown | T77: Unknown | U77: Unknown | V77: Unknown | W77: Unknown | X77: Unknown | Y77: Unknown | Z77: Unknown | AA77: Unknown | AB77: Unknown | AE77: Unknown | AF77: No exact feature-level physical path was resolved from the reviewed evidence. | AG77: Unknown | AH77: Unknown | AI77: Searched src/; A prior area review labelled this 'Partial', but did not supply a feature-level physical mapping; the authoritative state is therefore Unknown. | AJ77: Unknown | AK77: EV-04-0016 | AO77: 8bc0dcb2a1da1b21368c5536aaeef829d587f316 | AP77: Low | AQ77: Not assessed | AR77: Not assessed | AS77: Not assessed | AT77: Not assessed | AU77: Not assessed | AV77: Not assessed | AW77: Not assessed | AX77: Not assessed | AY77: Not assessed | AZ77: Not assessed | BA77: Not assessed | BB77: Not assessed | BC77: Not assessed | BD77: Not assessed | BE77: Not assessed | BF77: Production readiness cannot be assessed until the exact physical implementation and runtime path are traced. | BG77: Map the feature to exact client, server, data, worker and configuration locations, then verify its runtime path. | BK77: Evidence reconciled against the reviewed source revision. No production approval is inferred from implementation or file presence. | BL77: 2026-08-02
A78: BLYP-04-017 | C78: Always-on communal topic live rooms | D78: 4 | E78: 17 | F78: Feature | G78: Visible ranking-reset countdown | H78: Visible ranking-reset countdown | I78: /home/ubuntu/blyp_product_requirements.md :: Section 4 — Always-on communal topic live rooms | J78: /home/ubuntu/BLYP_COMPLETE_FEATURE_LIST.md:107 | K78: Required | L78: Applicable BLYP member | M78: BLYP mobile application and supporting production services | N78: Visible ranking-reset countdown | O78: Not explicitly defined in the product source; requires accountable product approval before production sign-off. | Q78: No evidence | S78: Unknown | T78: Unknown | U78: Unknown | V78: Unknown | W78: Unknown | X78: Unknown | Y78: Unknown | Z78: Unknown | AA78: Unknown | AB78: Unknown | AE78: Unknown | AF78: No exact feature-level physical path was resolved from the reviewed evidence. | AG78: Unknown | AH78: Unknown | AI78: Searched src/; A prior area review labelled this 'Partial', but did not supply a feature-level physical mapping; the authoritative state is therefore Unknown. | AJ78: Unknown | AK78: EV-04-0017 | AO78: 8bc0dcb2a1da1b21368c5536aaeef829d587f316 | AP78: Low | AQ78: Not assessed | AR78: Not assessed | AS78: Not assessed | AT78: Not assessed | AU78: Not assessed | AV78: Not assessed | AW78: Not assessed | AX78: Not assessed | AY78: Not assessed | AZ78: Not assessed | BA78: Not assessed | BB78: Not assessed | BC78: Not assessed | BD78: Not assessed | BE78: Not assessed | BF78: Production readiness cannot be assessed until the exact physical implementation and runtime path are traced. | BG78: Map the feature to exact client, server, data, worker and configuration locations, then verify its runtime path. | BK78: Evidence reconciled against the reviewed source revision. No production approval is inferred from implementation or file presence. | BL78: 2026-08-02
A79: BLYP-04-018 | C79: Always-on communal topic live rooms | D79: 4 | E79: 18 | F79: Feature | G79: Daily ranking history | H79: Daily ranking history | I79: /home/ubuntu/blyp_product_requirements.md :: Section 4 — Always-on communal topic live rooms | J79: /home/ubuntu/BLYP_COMPLETE_FEATURE_LIST.md:108 | K79: Required | L79: Applicable BLYP member | M79: BLYP mobile application and supporting production services | N79: Daily ranking history | O79: Not explicitly defined in the product source; requires accountable product approval before production sign-off. | Q79: No evidence | S79: Unknown | T79: Unknown | U79: Unknown | V79: Unknown | W79: Unknown | X79: Unknown | Y79: Unknown | Z79: Unknown | AA79: Unknown | AB79: Unknown | AE79: Unknown | AF79: No exact feature-level physical path was resolved from the reviewed evidence. | AG79: Unknown | AH79: Unknown | AI79: Searched src/; A prior area review labelled this 'Partial', but did not supply a feature-level physical mapping; the authoritative state is therefore Unknown. | AJ79: Unknown | AK79: EV-04-0018 | AO79: 8bc0dcb2a1da1b21368c5536aaeef829d587f316 | AP79: Low | AQ79: Not assessed | AR79: Not assessed | AS79: Not assessed | AT79: Not assessed | AU79: Not assessed | AV79: Not assessed | AW79: Not assessed | AX79: Not assessed | AY79: Not assessed | AZ79: Not assessed | BA79: Not assessed | BB79: Not assessed | BC79: Not assessed | BD79: Not assessed | BE79: Not assessed | BF79: Production readiness cannot be assessed until the exact physical implementation and runtime path are traced. | BG79: Map the feature to exact client, server, data, worker and configuration locations, then verify its runtime path. | BK79: Evidence reconciled against the reviewed source revision. No production approval is inferred from implementation or file presence. | BL79: 2026-08-02
A80: BLYP-04-019 | C80: Always-on communal topic live rooms | D80: 4 | E80: 19 | F80: Rule | G80: Rate-limited layout changes | H80: Rate-limited layout changes | I80: /home/ubuntu/blyp_product_requirements.md :: Section 4 — Always-on communal topic live rooms | J80: /home/ubuntu/BLYP_COMPLETE_FEATURE_LIST.md:109 | K80: Required | L80: Applicable BLYP member | M80: BLYP mobile application and supporting production services | N80: Rate-limited layout changes | O80: Not explicitly defined in the product source; requires accountable product approval before production sign-off. | Q80: No evidence | S80: Unknown | T80: Unknown | U80: Unknown | V80: Unknown | W80: Unknown | X80: Unknown | Y80: Unknown | Z80: Unknown | AA80: Unknown | AB80: Unknown | AE80: Unknown | AF80: No exact feature-level physical path was resolved from the reviewed evidence. | AG80: Unknown | AH80: Unknown | AI80: Searched src/; A prior area review labelled this 'Partial', but did not supply a feature-level physical mapping; the authoritative state is therefore Unknown. | AJ80: Unknown | AK80: EV-04-0019 | AO80: 8bc0dcb2a1da1b21368c5536aaeef829d587f316 | AP80: Low | AQ80: Not assessed | AR80: Not assessed | AS80: Not assessed | AT80: Not assessed | AU80: Not assessed | AV80: Not assessed | AW80: Not assessed | AX80: Not assessed | AY80: Not assessed | AZ80: Not assessed | BA80: Not assessed | BB80: Not assessed | BC80: Not assessed | BD80: Not assessed | BE80: Not assessed | BF80: Production readiness cannot be assessed until the exact physical implementation and runtime path are traced. | BG80: Map the feature to exact client, server, data, worker and configuration locations, then verify its runtime path. | BK80: Evidence reconciled against the reviewed source revision. No production approval is inferred from implementation or file presence. | BL80: 2026-08-02
A81: BLYP-04-020 | C81: Always-on communal topic live rooms | D81: 4 | E81: 20 | F81: Feature | G81: Persistent Interest chat plus focused live-session chat | H81: Persistent Interest chat plus focused live-session chat | I81: /home/ubuntu/blyp_product_requirements.md :: Section 4 — Always-on communal topic live rooms | J81: /home/ubuntu/BLYP_COMPLETE_FEATURE_LIST.md:110 | K81: Required | L81: Applicable BLYP member | M81: BLYP mobile application and supporting production services | N81: Persistent Interest chat plus focused live-session chat | O81: Not explicitly defined in the product source; requires accountable product approval before production sign-off. | Q81: Partial | S81: Unknown | T81: Unknown | U81: Unknown | V81: Unknown | W81: Unknown | X81: Unknown | Y81: Unknown | Z81: Unknown | AA81: Unknown | AB81: Unknown | AE81: Unknown | AF81: No exact feature-level physical path was resolved from the reviewed evidence. | AG81: Unknown | AH81: Unknown | AI81: Searched src/; A prior area review labelled this 'Partial', but did not supply a feature-level physical mapping; the authoritative state is therefore Unknown. | AJ81: Unknown | AK81: EV-04-0020 | AO81: 8bc0dcb2a1da1b21368c5536aaeef829d587f316 | AP81: Low | AQ81: Not assessed | AR81: Not assessed | AS81: Not assessed | AT81: Not assessed | AU81: Not assessed | AV81: Not assessed | AW81: Not assessed | AX81: Not assessed | AY81: Not assessed | AZ81: Not assessed | BA81: Not assessed | BB81: Not assessed | BC81: Not assessed | BD81: Not assessed | BE81: Not assessed | BF81: Production readiness cannot be assessed until the exact physical implementation and runtime path are traced. | BG81: Map the feature to exact client, server, data, worker and configuration locations, then verify its runtime path. | BK81: Evidence reconciled against the reviewed source revision. No production approval is inferred from implementation or file presence. | BL81: 2026-08-02
A82: BLYP-05-001 | C82: Role-based Team Board | D82: 5 | E82: 1 | F82: Feature | G82: Team member board | H82: Team member board | I82: /home/ubuntu/blyp_product_requirements.md :: Section 5 — Role-based Team Board | J82: /home/ubuntu/BLYP_COMPLETE_FEATURE_LIST.md:116 | K82: Required | L82: Applicable BLYP member | M82: BLYP mobile application and supporting production services | N82: Team member board | O82: Not explicitly defined in the product source; requires accountable product approval before production sign-off. | Q82: No evidence | S82: Not found | T82: Not found | U82: Not found | V82: Not found | W82: Not found | X82: Not found | Y82: Not found | Z82: Not found | AA82: Not found | AB82: Unknown | AD82: No runtime path identified. | AE82: Not wired | AF82: No runtime path identified. | AG82: Not started | AH82: No | AI82: Searched src/screens/, src/components/, src/services/, src/hooks/, backend/, functions/ for 'team', 'Team', 'member board', 'TeamMemberBoard'. No dedicated screen, component, service, or route found. | AJ82: Not verified | AK82: EV-05-0017 | AO82: 8bc0dcb2a1da1b21368c5536aaeef829d587f316 | AP82: High | AQ82: Not assessed | AR82: Not assessed | AS82: Fail | AT82: Not assessed | AU82: Not assessed | AV82: Not assessed | AW82: Not assessed | AX82: Not assessed | AY82: Not assessed | AZ82: Not assessed | BA82: Not assessed | BB82: Not assessed | BC82: Not assessed | BD82: Not assessed | BE82: Development required | BF82: No source implementation found; Physical implementation is not complete against the stated requirement.; Searched src/screens/, src/components/, src/services/, src/hooks/, backend/, functions/ for 'team', 'Team', 'member board', 'TeamMemberBoard'. No dedicated screen, component, service, or route found. | BG82: Team member board screen, service, and backend route | BK82: Evidence reconciled against the reviewed source revision. No production approval is inferred from implementation or file presence. | BL82: 2026-08-02
A83: BLYP-05-002 | C83: Role-based Team Board | D83: 5 | E83: 2 | F83: Feature | G83: Personal contribution score | H83: Personal contribution score | I83: /home/ubuntu/blyp_product_requirements.md :: Section 5 — Role-based Team Board | J83: /home/ubuntu/BLYP_COMPLETE_FEATURE_LIST.md:117 | K83: Required | L83: Applicable BLYP member | M83: BLYP mobile application and supporting production services | N83: Personal contribution score | O83: Not explicitly defined in the product source; requires accountable product approval before production sign-off. | Q83: Scaffold only | S83: Not found | T83: Not found | U83: Not found | V83: Not found | W83: Not found | X83: Not found | Y83: Not found | Z83: Not found | AA83: Not found | AB83: Unknown | AD83: No runtime path identified. | AE83: Not wired | AF83: No runtime path identified. | AG83: Not started | AH83: No | AI83: Searched for 'contribution', 'personal contribution', 'contribution score'. No dedicated implementation found. activityTracker.js tracks raw events but no contribution score formula or display exists. | AJ83: Not verified | AK83: EV-05-0016; EV-05-0017 | AO83: 8bc0dcb2a1da1b21368c5536aaeef829d587f316 | AP83: High | AQ83: Not assessed | AR83: Not assessed | AS83: Fail | AT83: Not assessed | AU83: Not assessed | AV83: Not assessed | AW83: Not assessed | AX83: Not assessed | AY83: Not assessed | AZ83: Not assessed | BA83: Not assessed | BB83: Not assessed | BC83: Not assessed | BD83: Not assessed | BE83: Development required | BF83: No source implementation found; Physical implementation is not complete against the stated requirement.; Searched for 'contribution', 'personal contribution', 'contribution score'. No dedicated implementation found. activityTracker.js tracks raw events but no contribution score formula or display exists. | BG83: Contribution score calculation service, data store, and UI component | BK83: Evidence reconciled against the reviewed source revision. No production approval is inferred from implementation or file presence. | BL83: 2026-08-02
A84: BLYP-05-003 | C84: Role-based Team Board | D84: 5 | E84: 3 | F84: Feature | G84: Member ranking | H84: Member ranking | I84: /home/ubuntu/blyp_product_requirements.md :: Section 5 — Role-based Team Board | J84: /home/ubuntu/BLYP_COMPLETE_FEATURE_LIST.md:118 | K84: Required | L84: Applicable BLYP member | M84: BLYP mobile application and supporting production services | N84: Member ranking | O84: Not explicitly defined in the product source; requires accountable product approval before production sign-off. | Q84: Scaffold only | S84: Not found | T84: Not found | U84: Not found | V84: Not found | W84: Not found | X84: Not found | Y84: Not found | Z84: Not found | AA84: Not found | AB84: Unknown | AD84: No runtime path identified. | AE84: Not wired | AF84: No runtime path identified. | AG84: Not started | AH84: No | AI84: Searched for 'member ranking', 'ranking member', 'memberRank'. No team-scoped member ranking found. smartListGenerator.js ranks posts by engagement, not team members. | AJ84: Not verified | AK84: EV-05-0009; EV-05-0017 | AO84: 8bc0dcb2a1da1b21368c5536aaeef829d587f316 | AP84: High | AQ84: Not assessed | AR84: Not assessed | AS84: Fail | AT84: Not assessed | AU84: Not assessed | AV84: Not assessed | AW84: Not assessed | AX84: Not assessed | AY84: Not assessed | AZ84: Not assessed | BA84: Not assessed | BB84: Not assessed | BC84: Not assessed | BD84: Not assessed | BE84: Development required | BF84: No source implementation found; Physical implementation is not complete against the stated requirement.; Searched for 'member ranking', 'ranking member', 'memberRank'. No team-scoped member ranking found. smartListGenerator.js ranks posts by engagement, not team members. | BG84: Member ranking service, data store, and UI | BK84: Evidence reconciled against the reviewed source revision. No production approval is inferred from implementation or file presence. | BL84: 2026-08-02
A85: BLYP-05-004 | C85: Role-based Team Board | D85: 5 | E85: 4 | F85: Feature | G85: Member trends | H85: Member trends | I85: /home/ubuntu/blyp_product_requirements.md :: Section 5 — Role-based Team Board | J85: /home/ubuntu/BLYP_COMPLETE_FEATURE_LIST.md:119 | K85: Required | L85: Applicable BLYP member | M85: BLYP mobile application and supporting production services | N85: Member trends | O85: Not explicitly defined in the product source; requires accountable product approval before production sign-off. | Q85: No evidence | S85: Not found | T85: Not found | U85: Not found | V85: Not found | W85: Not found | X85: Not found | Y85: Not found | Z85: Not found | AA85: Not found | AB85: Unknown | AD85: No runtime path identified. | AE85: Not wired | AF85: No runtime path identified. | AG85: Not started | AH85: No | AI85: Searched for 'member trends', 'trends member'. No team-member trend tracking found. Trending content exists for posts/hashtags, not team members. | AJ85: Not verified | AK85: EV-05-0017 | AO85: 8bc0dcb2a1da1b21368c5536aaeef829d587f316 | AP85: High | AQ85: Not assessed | AR85: Not assessed | AS85: Fail | AT85: Not assessed | AU85: Not assessed | AV85: Not assessed | AW85: Not assessed | AX85: Not assessed | AY85: Not assessed | AZ85: Not assessed | BA85: Not assessed | BB85: Not assessed | BC85: Not assessed | BD85: Not assessed | BE85: Development required | BF85: No source implementation found; Physical implementation is not complete against the stated requirement.; Searched for 'member trends', 'trends member'. No team-member trend tracking found. Trending content exists for posts/hashtags, not team members. | BG85: Member trend tracking service, data store, and UI | BK85: Evidence reconciled against the reviewed source revision. No production approval is inferred from implementation or file presence. | BL85: 2026-08-02
A86: BLYP-05-005 | C86: Role-based Team Board | D86: 5 | E86: 5 | F86: Non-functional requirement | G86: Post-performance metrics | H86: Post-performance metrics | I86: /home/ubuntu/blyp_product_requirements.md :: Section 5 — Role-based Team Board | J86: /home/ubuntu/BLYP_COMPLETE_FEATURE_LIST.md:120 | K86: Required | L86: Applicable BLYP member | M86: Production platform and operations | N86: Post-performance metrics | O86: Not explicitly defined in the product source; requires accountable product approval before production sign-off. | P86: Gemini AI (optional, for AI-powered ranking); Firestore posts collection (likes, comments, shares fields) | Q86: Partial | R86: scattered analytics foundations exist. | S86: Partial | T86: WhatsAppPopularTab accessible from main feed | U86: src/components/WhatsAppPopularTab.js (postMetrics, engagementBadge) | V86: src/utils/smartListGenerator.js (generatePopularityRankings) | W86: Not found | X86: Firestore posts collection (likes, comments, shares fields) | Y86: Not found | Z86: Gemini AI (optional, for AI-powered ranking) | AA86: Not found | AB86: Unknown | AD86: Post metrics (likes, comments, shares) displayed in popular content tab. Engagement score computed client-side. Not team-scoped. | AE86: User reachable | AF86: WhatsAppPopularTab accessible from main feed; Post metrics (likes, comments, shares) displayed in popular content tab. Engagement score computed client-side. Not team-scoped. | AG86: Incomplete | AH86: No | AI86: Post-performance metrics exist for content discovery (WhatsAppPopularTab) but are not scoped to team members. No team-member post performance aggregation, no server-side post performance API for team context. | AJ86: Not verified | AK86: EV-05-0009; EV-05-0010 | AO86: 8bc0dcb2a1da1b21368c5536aaeef829d587f316 | AP86: Medium | AQ86: Not assessed | AR86: Not assessed | AS86: Fail | AT86: Not assessed | AU86: Not assessed | AV86: Not assessed | AW86: Not assessed | AX86: Not assessed | AY86: Not assessed | AZ86: Not assessed | BA86: Not assessed | BB86: Not assessed | BC86: Not assessed | BD86: Not assessed | BE86: Development required | BF86: Not team-scoped; no team member post-performance aggregation; Physical implementation is not complete against the stated requirement.; Post-performance metrics exist for content discovery (WhatsAppPopularTab) but are not scoped to team members. No team-member post performance aggregation, no server-side post performance API for team context. | BG86: Team-scoped post-performance aggregation service and UI | BK86: Evidence reconciled against the reviewed source revision. No production approval is inferred from implementation or file presence. | BL86: 2026-08-02
